Workbook
Name _Títulos_a_imprimir: Ofertas!$22:$22
Name aaa: #REF!
Name aaa: #REF!
Name GG: #REF!
Name GG: #REF!
Name OLE_LINK1: Ofertas!#REF!

Sheet Hoja2
A2: Año | B2: (Todas)
A3: Estado | B3: PG
A5: Etiquetas de fila | B5: Suma de Monto (M$) | C5: Suma de Horas Lic (hh)
A6: ACOTEC | B6: 1.5135 | C6: 41
A7: AF | B7: 0.8436 | C7: 22
A8: OS | B8: 0.6699 | C8: 19
A9: ALQUIMIA CONCEPTOS | B9: 76.226368 | C9: 2582
A10: IB | B10: 42.493848 | C10: 1341
A11: IC | B11: 19.608597 | C11: 695
A12: ID | B12: 8.085696 | C12: 309
A13: IP | B13: 5.554227 | C13: 207
A14: OS | B14: 0.484 | C14: 30
A15: Amec | B15: 6.5875 | C15: 155
A16: AT | B16: 6.5875 | C16: 155
A17: Anglo American | B17: 376.3785 | C17: 9883
... A41: ED | B41: 1.822 | C41: 75
A42: AO
A43: ASISTEP | B43: 0.1 | C43: 15
A44: PEM | B44: 0.1 | C44: 15
A45: Atacama Kozan | B45: 2.275 | C45: 95
A46: (en blanco) | B46: 2.275 | C46: 95
A47: Ausenco Brasil | B47: 50.52 | C47: 690
A48: AP | B48: 50.52 | C48: 690
A49: ID
A50: AUSENCO Chile | B50: 1.29276 | C50: 21
A51: CC | B51: 1.29276 | C51: 21
A52: AP
A53: BAS Concesionaria | B53: 5.92 | C53: 200
A54: ED | B54: 4.92 | C54: 150
A55: IB | B55: 1 | C55: 50
A56: BHP BILLITON | B56: 353.13229 | C56: 5511
A57: AO | B57: 214.72468 | C57: 3421
A58: ID | B58: 101.02813 | C58: 1250
A59: (en blanco) | B59: 37.379476 | C59: 840
A60: CANDELARIA | B60: 214.71088 | C60: 5867
A61: IB | B61: 152.63088 | C61: 4156
A62: IC | B62: 36.455 | C62: 1036
A63: ID | B63: 25.625 | C63: 675
A64: CAP Mineria | B64: 1087.8526 | C64: 27953
... A67: IC/IB/ID | B67: 85.306 | C67: 2097
A68: (en blanco) | B68: 35.463684
A69: ID | B69: 35.316 | C69: 630
A70: OS | B70: 8.1 | C70: 120
A71: CASERONES | B71: 3969.414 | C71: 104216
A72: ID | B72: 2489.006 | C72: 76847
A73: CA | B73: 601.19649 | C73: 1496
A74: AO | B74: 257.36478 | C74: 7364
A75: IC | B75: 130.07195 | C75: 4192
A76: PEM | B76: 99.072 | C76: 2064
A77: ED | B77: 88.1558 | C77: 2319
A78: IG | B78: 73.70825 | C78: 2916
A79: IB | B79: 73.0424 | C79: 2509
A80: IB/IC | B80: 66.64 | C80: 1808
... A86: (en blanco) | B86: 4.851 | C86: 44
A87: IB/ID
A88: CAUSSE S.A. | B88: 22.2 | C88: 860.40741
A89: IC | B89: 22.2 | C89: 860.40741
A90: CDM SMITH | B90: 11.699 | C90: 275
A91: IC | B91: 6.519 | C91: 125
A92: BENCH | B92: 5.18 | C92: 150
A93: CDM Smith | B93: 1.96 | C93: 40
A94: CC | B94: 1.96 | C94: 40
A95: CEMIN | B95: 16.925 | C95: 396
A96: IC | B96: 16.925 | C96: 396
A97: Centinela | B97: 106.67817 | C97: 2535
A98: IC | B98: 76.813774 | C98: 1872
A99: ED | B99: 29.8644 | C99: 663
... A109: (en blanco) | B109: 1.886 | C109: 70
A110: Codelco ANDINA | C110: 13
A111: ED | C111: 13
A112: Codelco CHUQUI | B112: 1537.7161 | C112: 40208
A113: ITO | B113: 1537.7161 | C113: 40208
A114: Codelco DMH | B114: 19.0224 | C114: 524
A115: IC | B115: 19.0224 | C115: 524
A116: Codelco SALVADOR | B116: 49.866389 | C116: 1931
A117: ID | B117: 46.048128 | C117: 1756
A118: (en blanco) | B118: 3.818261 | C118: 175
A119: Codelco TENIENTE | B119: 26.124748 | C119: 800
A120: AO | B120: 26.124748 | C120: 800
A121: COLLAHUASI | B121: 939.29232 | C121: 25985
A122: ID | B122: 304.62823 | C122: 9380
A123: AO | B123: 205.5784 | C123: 4435
... A131: ID | B131: 524.5704 | C131: 12527
A132: Consorcio
A133: (en blanco)
A134: COPRIM | B134: 34.8096 | C134: 735
A135: IC | B135: 34.8096 | C135: 735
A136: CRU Strategies | B136: 45.862414 | C136: 1189
A137: IC | B137: 27.685314 | C137: 820
A138: (en blanco) | B138: 17.5501 | C138: 350
A139: EP | B139: 0.627 | C139: 19
A140: El Soldado | B140: 165.92924 | C140: 5940
A141: ID | B141: 165.92924 | C141: 5940
A142: CA
A143: Empírica Consultores | B143: 1.9125 | C143: 85
A144: AP | B144: 1.9125 | C144: 85
A145: ENAMI | B145: 505.46986 | C145: 14272
A146: IB | B146: 414.3772 | C146: 11926
A147: ED | B147: 91.09266 | C147: 2346
A148: Foster Wheeler Chile | B148: 53.82909 | C148: 1424
...

Sheet Ofertas
C1: LISTADO DE PROPUESTAS AL | O1: TIPO DE NEGOCIACIÓN
C2: =NOW() -> 46090.713 | O2: ND | P2: Negociación Directa
E3: m2 | O3: LM | P3: Licitación Múltiple
O4: AC | P4: Apoyo Contratos | T4: Hoy | V4: =+TODAY() -> 46090
C5: TIPO DE SERVICIO | O5: LC | P5: Licitación Contrato Abierto | T5: Año anterior | V5: 40543
C6: IP/IC | D6: Proyecto T: Ingeniería de Perfil / Conceptual (Prefactibilidad) | O6: N/A | P6: No Aplica | T6: Dias | V6: =-V4+V5 -> -5547
C7: IB/ID/CO | D7: Proyecto P: Ingeniería Básica / de Detalle / de Contraparte | O7: ÁMBITO
C8: CC | D8: Proyecto D: Comisiones de Confianza, Auditoría, Estudio Estratégico, Diagnóstico, Benchmarking y Bases | O8: NAC | P8: Nacional
C9: EP(CM/C) | D9: Proyecto P: Ingeniería de Detalle, Adquisición y (Adm. Construcción / Construcción) | O9: INT | P9: Internacional
C10: AD | D10: Proyecto P: Adquisiciones | O10: ESTADO
C11: CA | D11: Proyecto F: Contratos Abiertos. Contrato Marco y Servicio de Asesoría | O11: PDS | P11: Por Definir Situación
C12: IT/AO/AC | D12: Proyecto S: Ingeniería de Terreno / Apoyo a Operaciones, Manual de Op. y Mant. y PEM / Adm. Construcción | O12: EP | P12: En Preparación
C13: TP | D13: Proyecto G: Transferencia de Profesionales | O13: NL | P13: Propuesta No Licitada
C14: CT | D14: Proyecto C: Capacitación a Terceros. Cursos, Seminarios, Talleres y Manuales | O14: DP | P14: Decisión del Cliente Pendiente
C15: VD | D15: Proyecto Q: Venta de Dragas y Elementos Relacionados | O15: PG | P15: Propuesta Ganada
C16: PR | D16: Precalificación, Inscripción y Registro. REGIC, SICEP | O16: PP | P16: Propuesta Perdida
C17: OS | D17: Otros Servicios | O17: PD | P17: Propuesta Declarada Desierta
O18: N/A | P18: No Aplica
V19: =+SUMIF(T:T,"DP",#REF!) -> #REF!
A22: Número Proyecto | B22: Numero | C22: Código Prop. | D22: Fecha Recep. | E22: Cliente | F22: Cliente Final | G22: Contacto | H22: Email | I22: Título | K22: Tipo Serv. | L22: Tipo Licitación | M22: Ámbito | N22: País | O22: Fecha Entrega | P22: Líder Técnico | Q22: Unidad de Negocio (antigua) | R22: Unidad de Negocio (Nueva) | S22: Comentario | T22: Estado | U22: Probabilidad | V22: Fecha Estado | W22: Horas Lic (hh) | X22: Monto (M$) | Y22: Tarifa Promedio | Z22: Razón propuesta perdida | AA22: Comentarios propuesta perdida o ganada | AB22: Código Proy. | AC22: Fecha de Inicio | AD22: Duración Servicio | AE22: Coord. | AF22: Seguimiento (Consultar) | AG22: Año | AH22: 2026 | AI22: 2025 | AJ22: 2024 | AK22: 2023 | AL22: 2022 | AM22: 2021 | AN22: 2020 | AO22: 2019 | AP22: 2018 | AQ22: 2017 | AR22: 2016 | AS22: 2015 | AT22: 2014 | AU22: 2013 | AV22: 2012 | AW22: 2011 | AX22: 2010 | AY22: A | AZ22: B | BA22: C | BB22: D | BC22: E | BD22: F | BE22: G | BF22: H
A23: =+IFERROR(VALUE(MID(AB23,4,4)),"") | B23: =VALUE(RIGHT(C23,LEN(C23)-2)) -> 2699 | C23: O-2699 | D23: 46084 | E23: Codelco | F23: DRT | G23: ARIBA | H23: ARIBA | I23: CM Planificación Minera Largo Plazo | K23: CM | L23: LM | M23: NAC | N23: #VALUE! | O23: 46104 | P23: TBD | Q23: CM | R23: CM | T23: NL | V23: 46085 | Y23: =IF(SUM(W23:W23)>0,X23/SUM(W23:W23)*1000000,"N/A") -> N/A | AG23: =YEAR(V23) -> 2026 | AH23: =+IF(AG23=$AH$22,MONTH(V23),"") -> 3 | AI23: =+IF(AG23=$AI$22,MONTH(V23),"") | AJ23: =+IF(AG23=$AJ$22,MONTH(V23),"") | AK23: =+IF(AG23=$AK$22,MONTH(V23),"") | AL23: =+IF(AG23=$AL$22,MONTH(V23),"") | AM23: =+IF($AG23=$AM$22,MONTH($D23),"") | AN23: =+IF($AG23=AN$22,MONTH($D23),"") | AO23: =+IF($AG23=AO$22,MONTH($D23),"") | AP23: =+IF($AG23=AP$22,MONTH($D23),"") | AQ23: =+IF($AG23=AQ$22,MONTH($D23),"") | AR23: =+IF($AG23=AR$22,MONTH($D23),"") | AS23: =+IF($AG23=AS$22,MONTH($D23),"") | AT23: =+IF($AG23=AT$22,MONTH($D23),"") | AU23: =+IF($AG23=AU$22,MONTH($D23),"") | ... AX23: =+IF($AG23=AX$22,MONTH($D23),"")
A24: =+IFERROR(VALUE(MID(AB24,4,4)),"") | B24: =VALUE(RIGHT(C24,LEN(C24)-2)) -> 2698 | C24: O-2698 | D24: 46085 | E24: Vale | F24: Vale | G24: Cassio Dayrell | H24: cassio.dayrell@vale.com | I24: ID Sistema de Selagem Rejeitoduto Lama - VGR-01 - VALE | K24: ID | L24: LC | M24: INT | N24: #VALUE! | O24: 46090 | P24: Gustavo Assis | Q24: TA | R24: RELAVES | T24: EP | V24: 46085 | Y24: =IF(SUM(W24:W24)>0,X24/SUM(W24:W24)*1000000,"N/A") -> N/A | AG24: =YEAR(V24) -> 2026 | AH24: =+IF(AG24=$AH$22,MONTH(V24),"") -> 3 | AI24: =+IF(AG24=$AI$22,MONTH(V24),"") | AJ24: =+IF(AG24=$AJ$22,MONTH(V24),"") | AK24: =+IF(AG24=$AK$22,MONTH(V24),"") | AL24: =+IF(AG24=$AL$22,MONTH(V24),"") | AM24: =+IF($AG24=$AM$22,MONTH($D24),"") | AN24: =+IF($AG24=AN$22,MONTH($D24),"") | AO24: =+IF($AG24=AO$22,MONTH($D24),"") | AP24: =+IF($AG24=AP$22,MONTH($D24),"") | AQ24: =+IF($AG24=AQ$22,MONTH($D24),"") | AR24: =+IF($AG24=AR$22,MONTH($D24),"") | AS24: =+IF($AG24=AS$22,MONTH($D24),"") | AT24: =+IF($AG24=AT$22,MONTH($D24),"") | AU24: =+IF($AG24=AU$22,MONTH($D24),"") | ... AX24: =+IF($AG24=AX$22,MONTH($D24),"")
A25: =+IFERROR(VALUE(MID(AB25,4,4)),"") | B25: =VALUE(RIGHT(C25,LEN(C25)-2)) -> 2697 | C25: O-2697 | D25: 46080 | E25: Aguas CAP | F25: Aguas CAP | G25: Claudia Castillo | H25: ccastilloc@aguascap.cl | I25: Proyecto Sistema de Impulsión y Transporte de Salmuera | K25: PRE | L25: LM | M25: NAC | N25: #VALUE! | O25: 46084 | P25: David Cerón | Q25: PI | R25: PIPELINES | T25: DP | V25: 46084 | Y25: =IF(SUM(W25:W25)>0,X25/SUM(W25:W25)*1000000,"N/A") -> N/A | AG25: =YEAR(V25) -> 2026 | AH25: =+IF(AG25=$AH$22,MONTH(V25),"") -> 3 | AI25: =+IF(AG25=$AI$22,MONTH(V25),"") | AJ25: =+IF(AG25=$AJ$22,MONTH(V25),"") | AK25: =+IF(AG25=$AK$22,MONTH(V25),"") | AL25: =+IF(AG25=$AL$22,MONTH(V25),"") | AM25: =+IF($AG25=$AM$22,MONTH($D25),"") | AN25: =+IF($AG25=AN$22,MONTH($D25),"") | AO25: =+IF($AG25=AO$22,MONTH($D25),"") | AP25: =+IF($AG25=AP$22,MONTH($D25),"") | AQ25: =+IF($AG25=AQ$22,MONTH($D25),"") | AR25: =+IF($AG25=AR$22,MONTH($D25),"") | AS25: =+IF($AG25=AS$22,MONTH($D25),"") | AT25: =+IF($AG25=AT$22,MONTH($D25),"") | AU25: =+IF($AG25=AU$22,MONTH($D25),"") | ... AX25: =+IF($AG25=AX$22,MONTH($D25),"")
A26: =+IFERROR(VALUE(MID(AB26,4,4)),"") | B26: =VALUE(RIGHT(C26,LEN(C26)-2)) -> 2696 | C26: O-2696 | D26: 46080 | E26: Vale | F26: Vale | G26: Erick Brito | H26: eric.brito@vale.com | I26: Reavaliação do Traçado da Tubulação de Rejeito - Mina de Fábrica | K26: RE | L26: LM | M26: INT | N26: #VALUE! | O26: 46083 | P26: Gustavo Assis | Q26: TA | R26: RELAVES | T26: DP | V26: 46087 | W26: 584 | X26: 20.246 | Y26: =IF(SUM(W26:W26)>0,X26/SUM(W26:W26)*1000000,"N/A") -> 34667.808 | AG26: =YEAR(V26) -> 2026 | AH26: =+IF(AG26=$AH$22,MONTH(V26),"") -> 3 | AI26: =+IF(AG26=$AI$22,MONTH(V26),"") | AJ26: =+IF(AG26=$AJ$22,MONTH(V26),"") | AK26: =+IF(AG26=$AK$22,MONTH(V26),"") | AL26: =+IF(AG26=$AL$22,MONTH(V26),"") | AM26: =+IF($AG26=$AM$22,MONTH($D26),"") | AN26: =+IF($AG26=AN$22,MONTH($D26),"") | AO26: =+IF($AG26=AO$22,MONTH($D26),"") | AP26: =+IF($AG26=AP$22,MONTH($D26),"") | AQ26: =+IF($AG26=AQ$22,MONTH($D26),"") | AR26: =+IF($AG26=AR$22,MONTH($D26),"") | AS26: =+IF($AG26=AS$22,MONTH($D26),"") | AT26: =+IF($AG26=AT$22,MONTH($D26),"") | AU26: =+IF($AG26=AU$22,MONTH($D26),"") | ... AX26: =+IF($AG26=AX$22,MONTH($D26),"")
A27: =+IFERROR(VALUE(MID(AB27,4,4)),"") | B27: =VALUE(RIGHT(C27,LEN(C27)-2)) -> 2695 | C27: O-2695 | D27: 46078 | E27: Vale | F27: Vale | G27: Wender Araujo | H27: c0711007@vale.com | I27: Revisão dos documentos do sistema de bombeamento das bombas do ES2058 VGR | K27: RE | L27: LC | M27: INT | N27: #VALUE! | O27: 46085 | P27: José Muñoz | Q27: PI | R27: PIPELINES | T27: DP | V27: 46085 | W27: 459 | X27: 28 | Y27: =IF(SUM(W27:W27)>0,X27/SUM(W27:W27)*1000000,"N/A") -> 61002.179 | AG27: =YEAR(V27) -> 2026 | AH27: =+IF(AG27=$AH$22,MONTH(V27),"") -> 3 | AI27: =+IF(AG27=$AI$22,MONTH(V27),"") | AJ27: =+IF(AG27=$AJ$22,MONTH(V27),"") | AK27: =+IF(AG27=$AK$22,MONTH(V27),"") | AL27: =+IF(AG27=$AL$22,MONTH(V27),"") | AM27: =+IF($AG27=$AM$22,MONTH($D27),"") | AN27: =+IF($AG27=AN$22,MONTH($D27),"") | AO27: =+IF($AG27=AO$22,MONTH($D27),"") | AP27: =+IF($AG27=AP$22,MONTH($D27),"") | AQ27: =+IF($AG27=AQ$22,MONTH($D27),"") | AR27: =+IF($AG27=AR$22,MONTH($D27),"") | AS27: =+IF($AG27=AS$22,MONTH($D27),"") | AT27: =+IF($AG27=AT$22,MONTH($D27),"") | AU27: =+IF($AG27=AU$22,MONTH($D27),"") | ... AX27: =+IF($AG27=AX$22,MONTH($D27),"")
A28: =+IFERROR(VALUE(MID(AB28,4,4)),"") | B28: =VALUE(RIGHT(C28,LEN(C28)-2)) -> 2694 | C28: O-2694 | D28: 46078 | E28: Besalco | F28: AngloAmerican | G28: Flavio Letelier | H28: flavio.letelier@besalco.cl | I28: Apoyo Ingeniería Refinoducto Definitivo Los Bronces | K28: ID | L28: LC | M28: NAC | N28: #VALUE! | O28: 46092 | P28: TBD | Q28: PI | R28: PIPELINES | T28: EP | V28: 46080 | Y28: =IF(SUM(W28:W28)>0,X28/SUM(W28:W28)*1000000,"N/A") -> N/A | AG28: =YEAR(V28) -> 2026 | AH28: =+IF(AG28=$AH$22,MONTH(V28),"") -> 2 | AI28: =+IF(AG28=$AI$22,MONTH(V28),"") | AJ28: =+IF(AG28=$AJ$22,MONTH(V28),"") | AK28: =+IF(AG28=$AK$22,MONTH(V28),"") | AL28: =+IF(AG28=$AL$22,MONTH(V28),"") | AM28: =+IF($AG28=$AM$22,MONTH($D28),"") | AN28: =+IF($AG28=AN$22,MONTH($D28),"") | AO28: =+IF($AG28=AO$22,MONTH($D28),"") | AP28: =+IF($AG28=AP$22,MONTH($D28),"") | AQ28: =+IF($AG28=AQ$22,MONTH($D28),"") | AR28: =+IF($AG28=AR$22,MONTH($D28),"") | AS28: =+IF($AG28=AS$22,MONTH($D28),"") | AT28: =+IF($AG28=AT$22,MONTH($D28),"") | AU28: =+IF($AG28=AU$22,MONTH($D28),"") | ... AX28: =+IF($AG28=AX$22,MONTH($D28),"")
A29: =+IFERROR(VALUE(MID(AB29,4,4)),"") | B29: =VALUE(RIGHT(C29,LEN(C29)-2)) -> 2693 | C29: O-2693 | D29: 46079 | E29: Vale | F29: Vale | G29: Erick Brito | H29: eric.brito@vale.com | I29: ID Projeto Detalhado para Sistema de Captação Barragem Maravilhas II Mina do Pico | K29: ID | L29: LM | M29: INT | N29: #VALUE! | O29: 46093 | P29: Gustavo Assis | Q29: TA | R29: RELAVES | T29: EP | V29: 46080 | Y29: =IF(SUM(W29:W29)>0,X29/SUM(W29:W29)*1000000,"N/A") -> N/A | AG29: =YEAR(V29) -> 2026 | AH29: =+IF(AG29=$AH$22,MONTH(V29),"") -> 2 | AI29: =+IF(AG29=$AI$22,MONTH(V29),"") | AJ29: =+IF(AG29=$AJ$22,MONTH(V29),"") | AK29: =+IF(AG29=$AK$22,MONTH(V29),"") | AL29: =+IF(AG29=$AL$22,MONTH(V29),"") | AM29: =+IF($AG29=$AM$22,MONTH($D29),"") | AN29: =+IF($AG29=AN$22,MONTH($D29),"") | AO29: =+IF($AG29=AO$22,MONTH($D29),"") | AP29: =+IF($AG29=AP$22,MONTH($D29),"") | AQ29: =+IF($AG29=AQ$22,MONTH($D29),"") | AR29: =+IF($AG29=AR$22,MONTH($D29),"") | AS29: =+IF($AG29=AS$22,MONTH($D29),"") | AT29: =+IF($AG29=AT$22,MONTH($D29),"") | AU29: =+IF($AG29=AU$22,MONTH($D29),"") | ... AX29: =+IF($AG29=AX$22,MONTH($D29),"")
A30: =+IFERROR(VALUE(MID(AB30,4,4)),"") | B30: =VALUE(RIGHT(C30,LEN(C30)-2)) -> 2692 | C30: O-2692 | D30: 46076 | E30: Vale | F30: Vale | G30: Cassio Dayrell | H30: cassio.dayrell@vale.com | I30: IB Fase 2 Otimização Circuito 0,15mm de VGR1 | K30: IB | L30: LM | M30: INT | N30: #VALUE! | O30: 46080 | P30: Gustavo Assis | Q30: TA | R30: RELAVES | T30: DP | U30: 0.1 | V30: 46080 | W30: 3386 | X30: 107 | Y30: =IF(SUM(W30:W30)>0,X30/SUM(W30:W30)*1000000,"N/A") -> 31600.709 | AG30: =YEAR(V30) -> 2026 | AH30: =+IF(AG30=$AH$22,MONTH(V30),"") -> 2 | AI30: =+IF(AG30=$AI$22,MONTH(V30),"") | AJ30: =+IF(AG30=$AJ$22,MONTH(V30),"") | AK30: =+IF(AG30=$AK$22,MONTH(V30),"") | AL30: =+IF(AG30=$AL$22,MONTH(V30),"") | AM30: =+IF($AG30=$AM$22,MONTH($D30),"") | AN30: =+IF($AG30=AN$22,MONTH($D30),"") | AO30: =+IF($AG30=AO$22,MONTH($D30),"") | AP30: =+IF($AG30=AP$22,MONTH($D30),"") | AQ30: =+IF($AG30=AQ$22,MONTH($D30),"") | AR30: =+IF($AG30=AR$22,MONTH($D30),"") | AS30: =+IF($AG30=AS$22,MONTH($D30),"") | AT30: =+IF($AG30=AT$22,MONTH($D30),"") | AU30: =+IF($AG30=AU$22,MONTH($D30),"") | ... AX30: =+IF($AG30=AX$22,MONTH($D30),"")
A31: =+IFERROR(VALUE(MID(AB31,4,4)),"") | B31: =VALUE(RIGHT(C31,LEN(C31)-2)) -> 2691 | C31: O-2691 | D31: 46073 | E31: Codelco | F31: DET | G31: ARIBA | H31: ARIBA | I31: CM Ingeniería y Estudios Multidisciplinarios GPRO - DET | K31: CM | L31: LM | M31: NAC | N31: #VALUE! | O31: 46154 | P31: David Cerón | Q31: CM | R31: CM | T31: EP | V31: 46073 | Y31: =IF(SUM(W31:W31)>0,X31/SUM(W31:W31)*1000000,"N/A") -> N/A | AG31: =YEAR(V31) -> 2026 | AH31: =+IF(AG31=$AH$22,MONTH(V31),"") -> 2 | AI31: =+IF(AG31=$AI$22,MONTH(V31),"") | AJ31: =+IF(AG31=$AJ$22,MONTH(V31),"") | AK31: =+IF(AG31=$AK$22,MONTH(V31),"") | AL31: =+IF(AG31=$AL$22,MONTH(V31),"") | AM31: =+IF($AG31=$AM$22,MONTH($D31),"") | AN31: =+IF($AG31=AN$22,MONTH($D31),"") | AO31: =+IF($AG31=AO$22,MONTH($D31),"") | AP31: =+IF($AG31=AP$22,MONTH($D31),"") | AQ31: =+IF($AG31=AQ$22,MONTH($D31),"") | AR31: =+IF($AG31=AR$22,MONTH($D31),"") | AS31: =+IF($AG31=AS$22,MONTH($D31),"") | AT31: =+IF($AG31=AT$22,MONTH($D31),"") | AU31: =+IF($AG31=AU$22,MONTH($D31),"") | ... AX31: =+IF($AG31=AX$22,MONTH($D31),"")
A32: =+IFERROR(VALUE(MID(AB32,4,4)),"") | B32: =VALUE(RIGHT(C32,LEN(C32)-2)) -> 2690 | C32: O-2690 | D32: 46072 | E32: Minera Zaldívar | F32: Minera Zaldívar | G32: Ariba | H32: ARIBA | I32: ID Losas y Topes Neumáticos Prefabricadas Chancador Primario | K32: ID | L32: LM | M32: NAC | N32: #VALUE! | O32: 46100 | P32: Luis Ilabarca | Q32: OT | R32: INFRA | T32: EP | V32: 46072 | Y32: =IF(SUM(W32:W32)>0,X32/SUM(W32:W32)*1000000,"N/A") -> N/A | AG32: =YEAR(V32) -> 2026 | AH32: =+IF(AG32=$AH$22,MONTH(V32),"") -> 2 | AI32: =+IF(AG32=$AI$22,MONTH(V32),"") | AJ32: =+IF(AG32=$AJ$22,MONTH(V32),"") | AK32: =+IF(AG32=$AK$22,MONTH(V32),"") | AL32: =+IF(AG32=$AL$22,MONTH(V32),"") | AM32: =+IF($AG32=$AM$22,MONTH($D32),"") | AN32: =+IF($AG32=AN$22,MONTH($D32),"") | AO32: =+IF($AG32=AO$22,MONTH($D32),"") | AP32: =+IF($AG32=AP$22,MONTH($D32),"") | AQ32: =+IF($AG32=AQ$22,MONTH($D32),"") | AR32: =+IF($AG32=AR$22,MONTH($D32),"") | AS32: =+IF($AG32=AS$22,MONTH($D32),"") | AT32: =+IF($AG32=AT$22,MONTH($D32),"") | AU32: =+IF($AG32=AU$22,MONTH($D32),"") | ... AX32: =+IF($AG32=AX$22,MONTH($D32),"")
A33: =+IFERROR(VALUE(MID(AB33,4,4)),"") | B33: =VALUE(RIGHT(C33,LEN(C33)-2)) -> 2689 | C33: O-2689 | D33: 46070 | E33: BHP | F33: Escondida | G33: Rita Gomes | H33: rita.gomes4@bhp.com | I33: Servicio de Gestión Integral de Proyectos Minera Escondida | K33: OS | L33: LM | M33: NAC | N33: #VALUE! | O33: 46076 | P33: - | Q33: OT | T33: NL | V33: 46076 | Y33: =IF(SUM(W33:W33)>0,X33/SUM(W33:W33)*1000000,"N/A") -> N/A | AG33: =YEAR(V33) -> 2026 | AH33: =+IF(AG33=$AH$22,MONTH(V33),"") -> 2 | AI33: =+IF(AG33=$AI$22,MONTH(V33),"") | AJ33: =+IF(AG33=$AJ$22,MONTH(V33),"") | AK33: =+IF(AG33=$AK$22,MONTH(V33),"") | AL33: =+IF(AG33=$AL$22,MONTH(V33),"") | AM33: =+IF($AG33=$AM$22,MONTH($D33),"") | AN33: =+IF($AG33=AN$22,MONTH($D33),"") | AO33: =+IF($AG33=AO$22,MONTH($D33),"") | AP33: =+IF($AG33=AP$22,MONTH($D33),"") | AQ33: =+IF($AG33=AQ$22,MONTH($D33),"") | AR33: =+IF($AG33=AR$22,MONTH($D33),"") | AS33: =+IF($AG33=AS$22,MONTH($D33),"") | AT33: =+IF($AG33=AT$22,MONTH($D33),"") | AU33: =+IF($AG33=AU$22,MONTH($D33),"") | ... AX33: =+IF($AG33=AX$22,MONTH($D33),"")
A34: =+IFERROR(VALUE(MID(AB34,4,4)),"") | B34: =VALUE(RIGHT(C34,LEN(C34)-2)) -> 2688 | C34: O-2688 | D34: 46070 | E34: Proforma | F34: Spence | G34: Dylan Vargas | H34: dvaras@proforma.cl | I34: Cursos Transporte Hidráulico de Relaves y Agua Operaciones Minera Spence | K34: CT | L34: ND | M34: NAC | N34: #VALUE! | O34: 46072 | P34: Pablo Vásquez | Q34: CO | R34: RELAVES | T34: DP | U34: 0.1 | V34: 46072 | W34: 125 | X34: 8 | Y34: =IF(SUM(W34:W34)>0,X34/SUM(W34:W34)*1000000,"N/A") -> 64000 | AG34: =YEAR(V34) -> 2026 | AH34: =+IF(AG34=$AH$22,MONTH(V34),"") -> 2 | AI34: =+IF(AG34=$AI$22,MONTH(V34),"") | AJ34: =+IF(AG34=$AJ$22,MONTH(V34),"") | AK34: =+IF(AG34=$AK$22,MONTH(V34),"") | AL34: =+IF(AG34=$AL$22,MONTH(V34),"") | AM34: =+IF($AG34=$AM$22,MONTH($D34),"") | AN34: =+IF($AG34=AN$22,MONTH($D34),"") | AO34: =+IF($AG34=AO$22,MONTH($D34),"") | AP34: =+IF($AG34=AP$22,MONTH($D34),"") | AQ34: =+IF($AG34=AQ$22,MONTH($D34),"") | AR34: =+IF($AG34=AR$22,MONTH($D34),"") | AS34: =+IF($AG34=AS$22,MONTH($D34),"") | AT34: =+IF($AG34=AT$22,MONTH($D34),"") | AU34: =+IF($AG34=AU$22,MONTH($D34),"") | ... AX34: =+IF($AG34=AX$22,MONTH($D34),"")
A35: =+IFERROR(VALUE(MID(AB35,4,4)),"") -> 271 | B35: =VALUE(RIGHT(C35,LEN(C35)-2)) -> 2687 | C35: O-2687 | D35: 46070 | E35: SGSCM | F35: SGSCM | G35: Félix Lastra | H35: Felix.Lastra@sgscm.cl | I35: Ingeniería de Detalles Implementación de Peinetas en Berma 11 | K35: ID | L35: ND | M35: NAC | N35: #VALUE! | O35: 46073 | P35: Fernando Calle | Q35: TA | R35: RELAVES | T35: PG | V35: 46076 | W35: 1355 | X35: 59 | Y35: =IF(SUM(W35:W35)>0,X35/SUM(W35:W35)*1000000,"N/A") -> 43542.435 | AB35: SH-0271 ODT-34 | AG35: =YEAR(V35) -> 2026 | AH35: =+IF(AG35=$AH$22,MONTH(V35),"") -> 2 | AI35: =+IF(AG35=$AI$22,MONTH(V35),"") | AJ35: =+IF(AG35=$AJ$22,MONTH(V35),"") | AK35: =+IF(AG35=$AK$22,MONTH(V35),"") | AL35: =+IF(AG35=$AL$22,MONTH(V35),"") | AM35: =+IF($AG35=$AM$22,MONTH($D35),"") | AN35: =+IF($AG35=AN$22,MONTH($D35),"") | AO35: =+IF($AG35=AO$22,MONTH($D35),"") | AP35: =+IF($AG35=AP$22,MONTH($D35),"") | AQ35: =+IF($AG35=AQ$22,MONTH($D35),"") | AR35: =+IF($AG35=AR$22,MONTH($D35),"") | AS35: =+IF($AG35=AS$22,MONTH($D35),"") | AT35: =+IF($AG35=AT$22,MONTH($D35),"") | AU35: =+IF($AG35=AU$22,MONTH($D35),"") | ... AX35: =+IF($AG35=AX$22,MONTH($D35),"")
A36: =+IFERROR(VALUE(MID(AB36,4,4)),"") | B36: =VALUE(RIGHT(C36,LEN(C36)-2)) -> 2686 | C36: O-2686 | D36: 46069 | E36: Codelco | F36: DET | G36: ARIBA | H36: ARIBA | I36: IB Mejoramiento Confiabilidad Sistema Eléctrico Planta Chancado Primario Colón | K36: IB | L36: LM | M36: NAC | N36: #VALUE! | O36: 46118 | P36: Vicente Salinas | Q36: OT | R36: INFRA | T36: NL | V36: 46069 | Y36: =IF(SUM(W36:W36)>0,X36/SUM(W36:W36)*1000000,"N/A") -> N/A | AG36: =YEAR(V36) -> 2026 | AH36: =+IF(AG36=$AH$22,MONTH(V36),"") -> 2 | AI36: =+IF(AG36=$AI$22,MONTH(V36),"") | AJ36: =+IF(AG36=$AJ$22,MONTH(V36),"") | AK36: =+IF(AG36=$AK$22,MONTH(V36),"") | AL36: =+IF(AG36=$AL$22,MONTH(V36),"") | AM36: =+IF($AG36=$AM$22,MONTH($D36),"") | AN36: =+IF($AG36=AN$22,MONTH($D36),"") | AO36: =+IF($AG36=AO$22,MONTH($D36),"") | AP36: =+IF($AG36=AP$22,MONTH($D36),"") | AQ36: =+IF($AG36=AQ$22,MONTH($D36),"") | AR36: =+IF($AG36=AR$22,MONTH($D36),"") | AS36: =+IF($AG36=AS$22,MONTH($D36),"") | AT36: =+IF($AG36=AT$22,MONTH($D36),"") | AU36: =+IF($AG36=AU$22,MONTH($D36),"") | ... AX36: =+IF($AG36=AX$22,MONTH($D36),"")
A37: =+IFERROR(VALUE(MID(AB37,4,4)),"") -> 352 | B37: =VALUE(RIGHT(C37,LEN(C37)-2)) -> 2685 | C37: O-2685 | D37: 46069 | E37: Codelco | F37: DMH | G37: ARIBA | H37: ARIBA | I37: Asistencia Técnica Proyectos Cierre Faenas | K37: OS | L37: LC | M37: NAC | N37: #VALUE! | O37: 46091 | P37: René Lagas | Q37: OT | R37: INFRA | T37: EP | V37: 46071 | Y37: =IF(SUM(W37:W37)>0,X37/SUM(W37:W37)*1000000,"N/A") -> N/A | AB37: SH-0352 ODS033 | AG37: =YEAR(V37) -> 2026 | AH37: =+IF(AG37=$AH$22,MONTH(V37),"") -> 2 | AI37: =+IF(AG37=$AI$22,MONTH(V37),"") | AJ37: =+IF(AG37=$AJ$22,MONTH(V37),"") | AK37: =+IF(AG37=$AK$22,MONTH(V37),"") | AL37: =+IF(AG37=$AL$22,MONTH(V37),"") | AM37: =+IF($AG37=$AM$22,MONTH($D37),"") | AN37: =+IF($AG37=AN$22,MONTH($D37),"") | AO37: =+IF($AG37=AO$22,MONTH($D37),"") | AP37: =+IF($AG37=AP$22,MONTH($D37),"") | AQ37: =+IF($AG37=AQ$22,MONTH($D37),"") | AR37: =+IF($AG37=AR$22,MONTH($D37),"") | AS37: =+IF($AG37=AS$22,MONTH($D37),"") | AT37: =+IF($AG37=AT$22,MONTH($D37),"") | AU37: =+IF($AG37=AU$22,MONTH($D37),"") | ... AX37: =+IF($AG37=AX$22,MONTH($D37),"")
A38: =+IFERROR(VALUE(MID(AB38,4,4)),"") | B38: =VALUE(RIGHT(C38,LEN(C38)-2)) -> 2684 | C38: O-2684 | D38: 46065 | E38: Vale | F38: Vale | G38: Wender Araujo | H38: arthur.pinto@vale.com | I38: IB/ID Derivação Adutora Itabirito para Cava Andaime - VGR | K38: ID | L38: LC | M38: INT | N38: #VALUE! | O38: 46087 | P38: Leandro Souza | Q38: PI | R38: PIPELINES | T38: EP | V38: 46073 | Y38: =IF(SUM(W38:W38)>0,X38/SUM(W38:W38)*1000000,"N/A") -> N/A | AG38: =YEAR(V38) -> 2026 | AH38: =+IF(AG38=$AH$22,MONTH(V38),"") -> 2 | AI38: =+IF(AG38=$AI$22,MONTH(V38),"") | AJ38: =+IF(AG38=$AJ$22,MONTH(V38),"") | AK38: =+IF(AG38=$AK$22,MONTH(V38),"") | AL38: =+IF(AG38=$AL$22,MONTH(V38),"") | AM38: =+IF($AG38=$AM$22,MONTH($D38),"") | AN38: =+IF($AG38=AN$22,MONTH($D38),"") | AO38: =+IF($AG38=AO$22,MONTH($D38),"") | AP38: =+IF($AG38=AP$22,MONTH($D38),"") | AQ38: =+IF($AG38=AQ$22,MONTH($D38),"") | AR38: =+IF($AG38=AR$22,MONTH($D38),"") | AS38: =+IF($AG38=AS$22,MONTH($D38),"") | AT38: =+IF($AG38=AT$22,MONTH($D38),"") | AU38: =+IF($AG38=AU$22,MONTH($D38),"") | ... AX38: =+IF($AG38=AX$22,MONTH($D38),"")
A39: =+IFERROR(VALUE(MID(AB39,4,4)),"") | B39: =VALUE(RIGHT(C39,LEN(C39)-2)) -> 2683 | C39: O-2683 | D39: 46065 | E39: Aguas CAP | F39: Aguas CAP | G39: Gabriela Pardo | H39: gpardo@aguascap.cl | I39: Ingeniería Implementación Planta de Filtrado | K39: ID | L39: LC | M39: NAC | N39: #VALUE! | O39: 46079 | P39: Carolina Bohn | Q39: PI | R39: PIPELINES | T39: DP | U39: 0.1 | V39: 46065 | W39: 4274 | X39: 197 | Y39: =IF(SUM(W39:W39)>0,X39/SUM(W39:W39)*1000000,"N/A") -> 46092.653 | AG39: =YEAR(V39) -> 2026 | AH39: =+IF(AG39=$AH$22,MONTH(V39),"") -> 2 | AI39: =+IF(AG39=$AI$22,MONTH(V39),"") | AJ39: =+IF(AG39=$AJ$22,MONTH(V39),"") | AK39: =+IF(AG39=$AK$22,MONTH(V39),"") | AL39: =+IF(AG39=$AL$22,MONTH(V39),"") | AM39: =+IF($AG39=$AM$22,MONTH($D39),"") | AN39: =+IF($AG39=AN$22,MONTH($D39),"") | AO39: =+IF($AG39=AO$22,MONTH($D39),"") | AP39: =+IF($AG39=AP$22,MONTH($D39),"") | AQ39: =+IF($AG39=AQ$22,MONTH($D39),"") | AR39: =+IF($AG39=AR$22,MONTH($D39),"") | AS39: =+IF($AG39=AS$22,MONTH($D39),"") | AT39: =+IF($AG39=AT$22,MONTH($D39),"") | AU39: =+IF($AG39=AU$22,MONTH($D39),"") | ... AX39: =+IF($AG39=AX$22,MONTH($D39),"")
A40: =+IFERROR(VALUE(MID(AB40,4,4)),"") | B40: =VALUE(RIGHT(C40,LEN(C40)-2)) -> 2682 | C40: O-2682 | D40: 46065 | E40: Centinela | F40: Centinela | G40: Constanza Alcayaga | H40: calcayaga.oti@mineracentinela.cl | I40: Cursos de Aguas y Relaves | K40: CT | L40: ND | M40: NAC | N40: #VALUE! | O40: 46078 | P40: José Muñoz | Q40: CO | R40: RELAVES | T40: DP | U40: 0.1 | V40: 46065 | W40: 228 | X40: 16 | Y40: =IF(SUM(W40:W40)>0,X40/SUM(W40:W40)*1000000,"N/A") -> 70175.439 | AG40: =YEAR(V40) -> 2026 | AH40: =+IF(AG40=$AH$22,MONTH(V40),"") -> 2 | AI40: =+IF(AG40=$AI$22,MONTH(V40),"") | AJ40: =+IF(AG40=$AJ$22,MONTH(V40),"") | AK40: =+IF(AG40=$AK$22,MONTH(V40),"") | AL40: =+IF(AG40=$AL$22,MONTH(V40),"") | AM40: =+IF($AG40=$AM$22,MONTH($D40),"") | AN40: =+IF($AG40=AN$22,MONTH($D40),"") | AO40: =+IF($AG40=AO$22,MONTH($D40),"") | AP40: =+IF($AG40=AP$22,MONTH($D40),"") | AQ40: =+IF($AG40=AQ$22,MONTH($D40),"") | AR40: =+IF($AG40=AR$22,MONTH($D40),"") | AS40: =+IF($AG40=AS$22,MONTH($D40),"") | AT40: =+IF($AG40=AT$22,MONTH($D40),"") | AU40: =+IF($AG40=AU$22,MONTH($D40),"") | ... AX40: =+IF($AG40=AX$22,MONTH($D40),"")
A41: =+IFERROR(VALUE(MID(AB41,4,4)),"") | B41: =VALUE(RIGHT(C41,LEN(C41)-2)) -> 2681 | C41: O-2681 | D41: 46064 | E41: IMECPRO | F41: Oxiquim | G41: Pablo Matus | H41: pablo.matus@imecpro.cl | I41: Diseño Ingeniería Tacos en Productivo | K41: IB | L41: ND | M41: NAC | N41: #VALUE! | O41: 46072 | P41: Luis Ilabarca | Q41: IN | R41: I+D | T41: DP | U41: 0.1 | V41: 46072 | W41: 1033 | X41: 52 | Y41: =IF(SUM(W41:W41)>0,X41/SUM(W41:W41)*1000000,"N/A") -> 50338.819 | AG41: =YEAR(V41) -> 2026 | AH41: =+IF(AG41=$AH$22,MONTH(V41),"") -> 2 | AI41: =+IF(AG41=$AI$22,MONTH(V41),"") | AJ41: =+IF(AG41=$AJ$22,MONTH(V41),"") | AK41: =+IF(AG41=$AK$22,MONTH(V41),"") | AL41: =+IF(AG41=$AL$22,MONTH(V41),"") | AM41: =+IF($AG41=$AM$22,MONTH($D41),"") | AN41: =+IF($AG41=AN$22,MONTH($D41),"") | AO41: =+IF($AG41=AO$22,MONTH($D41),"") | AP41: =+IF($AG41=AP$22,MONTH($D41),"") | AQ41: =+IF($AG41=AQ$22,MONTH($D41),"") | AR41: =+IF($AG41=AR$22,MONTH($D41),"") | AS41: =+IF($AG41=AS$22,MONTH($D41),"") | AT41: =+IF($AG41=AT$22,MONTH($D41),"") | AU41: =+IF($AG41=AU$22,MONTH($D41),"") | ... AX41: =+IF($AG41=AX$22,MONTH($D41),"")
A42: =+IFERROR(VALUE(MID(AB42,4,4)),"") | B42: =VALUE(RIGHT(C42,LEN(C42)-2)) -> 2680 | C42: O-2680 | D42: 46065 | E42: Codelco | F42: DAND | G42: ARIBA | H42: ARIBA | I42: IF Mejoramiento Condiciones Ambientales Sistema de Chancado | K42: IF | L42: LM | M42: NAC | N42: #VALUE! | O42: 46107 | P42: TBD | Q42: BP | R42: INFRA | T42: NL | V42: 46064 | Y42: =IF(SUM(W42:W42)>0,X42/SUM(W42:W42)*1000000,"N/A") -> N/A | AG42: =YEAR(V42) -> 2026 | AH42: =+IF(AG42=$AH$22,MONTH(V42),"") -> 2 | AI42: =+IF(AG42=$AI$22,MONTH(V42),"") | AJ42: =+IF(AG42=$AJ$22,MONTH(V42),"") | AK42: =+IF(AG42=$AK$22,MONTH(V42),"") | AL42: =+IF(AG42=$AL$22,MONTH(V42),"") | AM42: =+IF($AG42=$AM$22,MONTH($D42),"") | AN42: =+IF($AG42=AN$22,MONTH($D42),"") | AO42: =+IF($AG42=AO$22,MONTH($D42),"") | AP42: =+IF($AG42=AP$22,MONTH($D42),"") | AQ42: =+IF($AG42=AQ$22,MONTH($D42),"") | AR42: =+IF($AG42=AR$22,MONTH($D42),"") | AS42: =+IF($AG42=AS$22,MONTH($D42),"") | AT42: =+IF($AG42=AT$22,MONTH($D42),"") | AU42: =+IF($AG42=AU$22,MONTH($D42),"") | ... AX42: =+IF($AG42=AX$22,MONTH($D42),"")
A43: =+IFERROR(VALUE(MID(AB43,4,4)),"") | B43: =VALUE(RIGHT(C43,LEN(C43)-2)) -> 2679 | C43: O-2679 | D43: 46064 | E43: Vale | F43: Vale | G43: Arthur Fogaça | H43: arthur.pinto@vale.com | I43: ED Diagnóstico Rejeitoduto Forquilha IV - Mina de Fábrica | K43: ID | L43: LC | M43: INT | N43: #VALUE! | O43: 46073 | P43: Leandro Souza | Q43: TA | R43: RELAVES | T43: DP | U43: 0.1 | V43: 46073 | W43: 1314 | X43: 50 | Y43: =IF(SUM(W43:W43)>0,X43/SUM(W43:W43)*1000000,"N/A") -> 38051.75 | AG43: =YEAR(V43) -> 2026 | AH43: =+IF(AG43=$AH$22,MONTH(V43),"") -> 2 | AI43: =+IF(AG43=$AI$22,MONTH(V43),"") | AJ43: =+IF(AG43=$AJ$22,MONTH(V43),"") | AK43: =+IF(AG43=$AK$22,MONTH(V43),"") | AL43: =+IF(AG43=$AL$22,MONTH(V43),"") | AM43: =+IF($AG43=$AM$22,MONTH($D43),"") | AN43: =+IF($AG43=AN$22,MONTH($D43),"") | AO43: =+IF($AG43=AO$22,MONTH($D43),"") | AP43: =+IF($AG43=AP$22,MONTH($D43),"") | AQ43: =+IF($AG43=AQ$22,MONTH($D43),"") | AR43: =+IF($AG43=AR$22,MONTH($D43),"") | AS43: =+IF($AG43=AS$22,MONTH($D43),"") | AT43: =+IF($AG43=AT$22,MONTH($D43),"") | AU43: =+IF($AG43=AU$22,MONTH($D43),"") | ... AX43: =+IF($AG43=AX$22,MONTH($D43),"")
A44: =+IFERROR(VALUE(MID(AB44,4,4)),"") | B44: =VALUE(RIGHT(C44,LEN(C44)-2)) -> 2678 | C44: O-2678 | D44: 46063 | E44: Vale | F44: Vale | G44: Wagner Santos | H44: wagner.souza.santos@vale.com | I44: Modelagem chutes Carajás | K44: OS | L44: LC | M44: INT | N44: #VALUE! | O44: 46076 | P44: Leandro Souza | Q44: BP | R44: INFRA | T44: DP | U44: 0.1 | V44: 46073 | W44: 4892 | X44: 334 | Y44: =IF(SUM(W44:W44)>0,X44/SUM(W44:W44)*1000000,"N/A") -> 68274.734 | AG44: =YEAR(V44) -> 2026 | AH44: =+IF(AG44=$AH$22,MONTH(V44),"") -> 2 | AI44: =+IF(AG44=$AI$22,MONTH(V44),"") | AJ44: =+IF(AG44=$AJ$22,MONTH(V44),"") | AK44: =+IF(AG44=$AK$22,MONTH(V44),"") | AL44: =+IF(AG44=$AL$22,MONTH(V44),"") | AM44: =+IF($AG44=$AM$22,MONTH($D44),"") | AN44: =+IF($AG44=AN$22,MONTH($D44),"") | AO44: =+IF($AG44=AO$22,MONTH($D44),"") | AP44: =+IF($AG44=AP$22,MONTH($D44),"") | AQ44: =+IF($AG44=AQ$22,MONTH($D44),"") | AR44: =+IF($AG44=AR$22,MONTH($D44),"") | AS44: =+IF($AG44=AS$22,MONTH($D44),"") | AT44: =+IF($AG44=AT$22,MONTH($D44),"") | AU44: =+IF($AG44=AU$22,MONTH($D44),"") | ... AX44: =+IF($AG44=AX$22,MONTH($D44),"")
A45: =+IFERROR(VALUE(MID(AB45,4,4)),"") | B45: =VALUE(RIGHT(C45,LEN(C45)-2)) -> 2677 | C45: O-2677 | D45: 46063 | E45: Vale | F45: Vale | G45: Wagner Santos | H45: wagner.souza.santos@vale.com | I45: As Built de Tubulações de Agua Carajás | K45: ID | L45: LC | M45: INT | N45: #VALUE! | O45: 46076 | P45: Leandro Souza | Q45: PI | R45: PIPELINES | T45: PG | V45: 46090 | W45: 8207 | X45: 437 | Y45: =IF(SUM(W45:W45)>0,X45/SUM(W45:W45)*1000000,"N/A") -> 53247.228 | AG45: =YEAR(V45) -> 2026 | AH45: =+IF(AG45=$AH$22,MONTH(V45),"") -> 3 | AI45: =+IF(AG45=$AI$22,MONTH(V45),"") | AJ45: =+IF(AG45=$AJ$22,MONTH(V45),"") | AK45: =+IF(AG45=$AK$22,MONTH(V45),"") | AL45: =+IF(AG45=$AL$22,MONTH(V45),"") | AM45: =+IF($AG45=$AM$22,MONTH($D45),"") | AN45: =+IF($AG45=AN$22,MONTH($D45),"") | AO45: =+IF($AG45=AO$22,MONTH($D45),"") | AP45: =+IF($AG45=AP$22,MONTH($D45),"") | AQ45: =+IF($AG45=AQ$22,MONTH($D45),"") | AR45: =+IF($AG45=AR$22,MONTH($D45),"") | AS45: =+IF($AG45=AS$22,MONTH($D45),"") | AT45: =+IF($AG45=AT$22,MONTH($D45),"") | AU45: =+IF($AG45=AU$22,MONTH($D45),"") | ... AX45: =+IF($AG45=AX$22,MONTH($D45),"")
A46: =+IFERROR(VALUE(MID(AB46,4,4)),"") -> 468 | B46: =VALUE(RIGHT(C46,LEN(C46)-2)) -> 2676 | C46: O-2676 | D46: 46063 | E46: Aguas CAP | F46: Aguas CAP | G46: Martín Baliellas | H46: e_mbaliellas@aguascap.cl | I46: Actualización Capex Ingeniería Santo Domingo - Adicionales | K46: ID | L46: ND | M46: NAC | N46: #VALUE! | O46: 46070 | P46: José Muñoz | Q46: PI | R46: PIPELINES | T46: DP | U46: 0.1 | V46: 46070 | W46: 292 | X46: 13 | Y46: =IF(SUM(W46:W46)>0,X46/SUM(W46:W46)*1000000,"N/A") -> 44520.548 | AB46: SH-0468 ODS1 | AG46: =YEAR(V46) -> 2026 | AH46: =+IF(AG46=$AH$22,MONTH(V46),"") -> 2 | AI46: =+IF(AG46=$AI$22,MONTH(V46),"") | AJ46: =+IF(AG46=$AJ$22,MONTH(V46),"") | AK46: =+IF(AG46=$AK$22,MONTH(V46),"") | AL46: =+IF(AG46=$AL$22,MONTH(V46),"") | AM46: =+IF($AG46=$AM$22,MONTH($D46),"") | AN46: =+IF($AG46=AN$22,MONTH($D46),"") | AO46: =+IF($AG46=AO$22,MONTH($D46),"") | AP46: =+IF($AG46=AP$22,MONTH($D46),"") | AQ46: =+IF($AG46=AQ$22,MONTH($D46),"") | AR46: =+IF($AG46=AR$22,MONTH($D46),"") | AS46: =+IF($AG46=AS$22,MONTH($D46),"") | AT46: =+IF($AG46=AT$22,MONTH($D46),"") | AU46: =+IF($AG46=AU$22,MONTH($D46),"") | ... AX46: =+IF($AG46=AX$22,MONTH($D46),"")
A47: =+IFERROR(VALUE(MID(AB47,4,4)),"") | B47: =VALUE(RIGHT(C47,LEN(C47)-2)) -> 2675 | C47: O-2675 | D47: 46062 | E47: Caserones | F47: Caserones | G47: Nelson Carvajal Rodríguez | H47: nelson.carvajal@lundinmining.com | I47: Ingeniería de Detalles Aumento Parque 7G a 8G | K47: ID | L47: LC | M47: NAC | N47: #VALUE! | O47: 46085 | P47: Vicente Salinas/Paulo Olivares | Q47: OT | R47: INFRA | T47: DP | U47: 0.1 | V47: 46085 | W47: 2292 | X47: =2494*39800/1000000 -> 99.2612 | Y47: =IF(SUM(W47:W47)>0,X47/SUM(W47:W47)*1000000,"N/A") -> 43307.679 | AG47: =YEAR(V47) -> 2026 | AH47: =+IF(AG47=$AH$22,MONTH(V47),"") -> 3 | AI47: =+IF(AG47=$AI$22,MONTH(V47),"") | AJ47: =+IF(AG47=$AJ$22,MONTH(V47),"") | AK47: =+IF(AG47=$AK$22,MONTH(V47),"") | AL47: =+IF(AG47=$AL$22,MONTH(V47),"") | AM47: =+IF($AG47=$AM$22,MONTH($D47),"") | AN47: =+IF($AG47=AN$22,MONTH($D47),"") | AO47: =+IF($AG47=AO$22,MONTH($D47),"") | AP47: =+IF($AG47=AP$22,MONTH($D47),"") | AQ47: =+IF($AG47=AQ$22,MONTH($D47),"") | AR47: =+IF($AG47=AR$22,MONTH($D47),"") | AS47: =+IF($AG47=AS$22,MONTH($D47),"") | AT47: =+IF($AG47=AT$22,MONTH($D47),"") | AU47: =+IF($AG47=AU$22,MONTH($D47),"") | ... AX47: =+IF($AG47=AX$22,MONTH($D47),"")
A48: =+IFERROR(VALUE(MID(AB48,4,4)),"") | B48: =VALUE(RIGHT(C48,LEN(C48)-2)) -> 2674 | C48: O-2674 | D48: 46062 | E48: Vale | F48: Vale | G48: Samuel Pinto | H48: c0711007@vale.com | I48: CO Adutora Onça e Periquito | K48: RE | L48: LM | M48: INT | N48: #VALUE! | O48: 46091 | P48: Leandro Souza | Q48: PI | R48: PIPELINES | T48: NL | V48: 46073 | Y48: =IF(SUM(W48:W48)>0,X48/SUM(W48:W48)*1000000,"N/A") -> N/A | AG48: =YEAR(V48) -> 2026 | AH48: =+IF(AG48=$AH$22,MONTH(V48),"") -> 2 | AI48: =+IF(AG48=$AI$22,MONTH(V48),"") | AJ48: =+IF(AG48=$AJ$22,MONTH(V48),"") | AK48: =+IF(AG48=$AK$22,MONTH(V48),"") | AL48: =+IF(AG48=$AL$22,MONTH(V48),"") | AM48: =+IF($AG48=$AM$22,MONTH($D48),"") | AN48: =+IF($AG48=AN$22,MONTH($D48),"") | AO48: =+IF($AG48=AO$22,MONTH($D48),"") | AP48: =+IF($AG48=AP$22,MONTH($D48),"") | AQ48: =+IF($AG48=AQ$22,MONTH($D48),"") | AR48: =+IF($AG48=AR$22,MONTH($D48),"") | AS48: =+IF($AG48=AS$22,MONTH($D48),"") | AT48: =+IF($AG48=AT$22,MONTH($D48),"") | AU48: =+IF($AG48=AU$22,MONTH($D48),"") | ... AX48: =+IF($AG48=AX$22,MONTH($D48),"")
A49: =+IFERROR(VALUE(MID(AB49,4,4)),"") | B49: =VALUE(RIGHT(C49,LEN(C49)-2)) -> 2673 | C49: O-2673 | D49: 46062 | E49: Codelco | F49: DET | G49: Alex Vargas | H49: avarg017@contratistas.codelco.cl | I49: Inspección Operacional Sistema de Conducción de Pulpa - DET | K49: OS | L49: LM | M49: NAC | N49: #VALUE! | O49: 46120 | P49: TBD | Q49: PI | R49: PIPELINES | T49: NL | V49: 46062 | Y49: =IF(SUM(W49:W49)>0,X49/SUM(W49:W49)*1000000,"N/A") -> N/A | AG49: =YEAR(V49) -> 2026 | AH49: =+IF(AG49=$AH$22,MONTH(V49),"") -> 2 | AI49: =+IF(AG49=$AI$22,MONTH(V49),"") | AJ49: =+IF(AG49=$AJ$22,MONTH(V49),"") | AK49: =+IF(AG49=$AK$22,MONTH(V49),"") | AL49: =+IF(AG49=$AL$22,MONTH(V49),"") | AM49: =+IF($AG49=$AM$22,MONTH($D49),"") | AN49: =+IF($AG49=AN$22,MONTH($D49),"") | AO49: =+IF($AG49=AO$22,MONTH($D49),"") | AP49: =+IF($AG49=AP$22,MONTH($D49),"") | AQ49: =+IF($AG49=AQ$22,MONTH($D49),"") | AR49: =+IF($AG49=AR$22,MONTH($D49),"") | AS49: =+IF($AG49=AS$22,MONTH($D49),"") | AT49: =+IF($AG49=AT$22,MONTH($D49),"") | AU49: =+IF($AG49=AU$22,MONTH($D49),"") | ... AX49: =+IF($AG49=AX$22,MONTH($D49),"")
A50: =+IFERROR(VALUE(MID(AB50,4,4)),"") | B50: =VALUE(RIGHT(C50,LEN(C50)-2)) -> 2672 | C50: O-2672 | D50: 46062 | E50: GHD | F50: Candelaria | G50: Francisco Aranda | H50: Francisco.Aranda@ghd.com | I50: Inspección Estructural | K50: OS | L50: ND | M50: NAC | N50: #VALUE! | O50: 46065 | P50: Luís Ilabarca | Q50: OT | R50: OTHERS | T50: DP | U50: 0.1 | V50: 46064 | W50: 153 | X50: 8 | Y50: =IF(SUM(W50:W50)>0,X50/SUM(W50:W50)*1000000,"N/A") -> 52287.582 | AG50: =YEAR(V50) -> 2026 | AH50: =+IF(AG50=$AH$22,MONTH(V50),"") -> 2 | AI50: =+IF(AG50=$AI$22,MONTH(V50),"") | AJ50: =+IF(AG50=$AJ$22,MONTH(V50),"") | AK50: =+IF(AG50=$AK$22,MONTH(V50),"") | AL50: =+IF(AG50=$AL$22,MONTH(V50),"") | AM50: =+IF($AG50=$AM$22,MONTH($D50),"") | AN50: =+IF($AG50=AN$22,MONTH($D50),"") | AO50: =+IF($AG50=AO$22,MONTH($D50),"") | AP50: =+IF($AG50=AP$22,MONTH($D50),"") | AQ50: =+IF($AG50=AQ$22,MONTH($D50),"") | AR50: =+IF($AG50=AR$22,MONTH($D50),"") | AS50: =+IF($AG50=AS$22,MONTH($D50),"") | AT50: =+IF($AG50=AT$22,MONTH($D50),"") | AU50: =+IF($AG50=AU$22,MONTH($D50),"") | ... AX50: =+IF($AG50=AX$22,MONTH($D50),"")
A51: =+IFERROR(VALUE(MID(AB51,4,4)),"") -> 409 | B51: =VALUE(RIGHT(C51,LEN(C51)-2)) -> 2671 | C51: O-2671 | D51: 46062 | E51: Capstone Copper | F51: Mantoverde | G51: Nilson Saldías | H51: nilson.saldias@capstonecopper.com | I51: Empalizada Madera o Metálica | K51: IC | L51: ND | M51: NAC | N51: #VALUE! | O51: 46099 | P51: Pablo Vásquez | Q51: TA | R51: RELAVES | T51: EP | V51: 46062 | Y51: =IF(SUM(W51:W51)>0,X51/SUM(W51:W51)*1000000,"N/A") -> N/A | AB51: SH-0409 ODS1 | AG51: =YEAR(V51) -> 2026 | AH51: =+IF(AG51=$AH$22,MONTH(V51),"") -> 2 | AI51: =+IF(AG51=$AI$22,MONTH(V51),"") | AJ51: =+IF(AG51=$AJ$22,MONTH(V51),"") | AK51: =+IF(AG51=$AK$22,MONTH(V51),"") | AL51: =+IF(AG51=$AL$22,MONTH(V51),"") | AM51: =+IF($AG51=$AM$22,MONTH($D51),"") | AN51: =+IF($AG51=AN$22,MONTH($D51),"") | AO51: =+IF($AG51=AO$22,MONTH($D51),"") | AP51: =+IF($AG51=AP$22,MONTH($D51),"") | AQ51: =+IF($AG51=AQ$22,MONTH($D51),"") | AR51: =+IF($AG51=AR$22,MONTH($D51),"") | AS51: =+IF($AG51=AS$22,MONTH($D51),"") | AT51: =+IF($AG51=AT$22,MONTH($D51),"") | AU51: =+IF($AG51=AU$22,MONTH($D51),"") | ... AX51: =+IF($AG51=AX$22,MONTH($D51),"")
A52: =+IFERROR(VALUE(MID(AB52,4,4)),"") | B52: =VALUE(RIGHT(C52,LEN(C52)-2)) -> 2670 | C52: O-2670 | D52: 46058 | E52: Intasol | F52: AngloAmerican | G52: Milton Miranda | H52: milton@intasol.co.za | I52: Revisión Ingeniería Repulpeo Tranques Pérez Caldera | K52: RE | L52: ND | M52: NAC | N52: #VALUE! | O52: 46076 | P52: Hugo Andrade | Q52: TA | R52: RELAVES | T52: DP | U52: 0.01 | V52: 46078 | W52: 2279 | X52: =3323*39773/1000000 -> 132.16568 | Y52: =IF(SUM(W52:W52)>0,X52/SUM(W52:W52)*1000000,"N/A") -> 57992.839 | AG52: =YEAR(V52) -> 2026 | AH52: =+IF(AG52=$AH$22,MONTH(V52),"") -> 2 | AI52: =+IF(AG52=$AI$22,MONTH(V52),"") | AJ52: =+IF(AG52=$AJ$22,MONTH(V52),"") | AK52: =+IF(AG52=$AK$22,MONTH(V52),"") | AL52: =+IF(AG52=$AL$22,MONTH(V52),"") | AM52: =+IF($AG52=$AM$22,MONTH($D52),"") | AN52: =+IF($AG52=AN$22,MONTH($D52),"") | AO52: =+IF($AG52=AO$22,MONTH($D52),"") | AP52: =+IF($AG52=AP$22,MONTH($D52),"") | AQ52: =+IF($AG52=AQ$22,MONTH($D52),"") | AR52: =+IF($AG52=AR$22,MONTH($D52),"") | AS52: =+IF($AG52=AS$22,MONTH($D52),"") | AT52: =+IF($AG52=AT$22,MONTH($D52),"") | AU52: =+IF($AG52=AU$22,MONTH($D52),"") | ... AX52: =+IF($AG52=AX$22,MONTH($D52),"")
A53: =+IFERROR(VALUE(MID(AB53,4,4)),"") -> 466 | B53: =VALUE(RIGHT(C53,LEN(C53)-2)) -> 2669 | C53: O-2669 | D53: 46057 | E53: BHP | F53: BHP | G53: Rodrigo López | H53: rodrigo.a.lopez2@bhp.com | I53: Impermeabilización Celda 11 Etapa 2- Instrumentación | K53: ID | L53: ND | M53: NAC | N53: #VALUE! | O53: 46069 | P53: Cristian López | Q53: TA | R53: RELAVES | S53: Se realizará ODS1 con alcance de ODS2 incluido. | T53: NL | V53: 46062 | Y53: =IF(SUM(W53:W53)>0,X53/SUM(W53:W53)*1000000,"N/A") -> N/A | AB53: SH-0466 ODS02 | AG53: =YEAR(V53) -> 2026 | AH53: =+IF(AG53=$AH$22,MONTH(V53),"") -> 2 | AI53: =+IF(AG53=$AI$22,MONTH(V53),"") | AJ53: =+IF(AG53=$AJ$22,MONTH(V53),"") | AK53: =+IF(AG53=$AK$22,MONTH(V53),"") | AL53: =+IF(AG53=$AL$22,MONTH(V53),"") | AM53: =+IF($AG53=$AM$22,MONTH($D53),"") | AN53: =+IF($AG53=AN$22,MONTH($D53),"") | AO53: =+IF($AG53=AO$22,MONTH($D53),"") | AP53: =+IF($AG53=AP$22,MONTH($D53),"") | AQ53: =+IF($AG53=AQ$22,MONTH($D53),"") | AR53: =+IF($AG53=AR$22,MONTH($D53),"") | AS53: =+IF($AG53=AS$22,MONTH($D53),"") | AT53: =+IF($AG53=AT$22,MONTH($D53),"") | AU53: =+IF($AG53=AU$22,MONTH($D53),"") | ... AX53: =+IF($AG53=AX$22,MONTH($D53),"")
A54: =+IFERROR(VALUE(MID(AB54,4,4)),"") | B54: =VALUE(RIGHT(C54,LEN(C54)-2)) -> 2668 | C54: O-2668 | D54: 46057 | E54: Austral Gold | F54: Austral Gold | G54: Martin Arnaez | H54: martin.arnaez@australgold.com | I54: Ampliación Planta Casposo | K54: IC | L54: ND | M54: INT | N54: #VALUE! | O54: 46076 | P54: Patricia Lara | Q54: BP | R54: PLANTA | S54: Preliminar | T54: DP | U54: 0.1 | V54: 46059 | W54: 1990 | X54: 0 | Y54: =IF(SUM(W54:W54)>0,X54/SUM(W54:W54)*1000000,"N/A") -> 0 | AG54: =YEAR(V54) -> 2026 | AH54: =+IF(AG54=$AH$22,MONTH(V54),"") -> 2 | AI54: =+IF(AG54=$AI$22,MONTH(V54),"") | AJ54: =+IF(AG54=$AJ$22,MONTH(V54),"") | AK54: =+IF(AG54=$AK$22,MONTH(V54),"") | AL54: =+IF(AG54=$AL$22,MONTH(V54),"") | AM54: =+IF($AG54=$AM$22,MONTH($D54),"") | AN54: =+IF($AG54=AN$22,MONTH($D54),"") | AO54: =+IF($AG54=AO$22,MONTH($D54),"") | AP54: =+IF($AG54=AP$22,MONTH($D54),"") | AQ54: =+IF($AG54=AQ$22,MONTH($D54),"") | AR54: =+IF($AG54=AR$22,MONTH($D54),"") | AS54: =+IF($AG54=AS$22,MONTH($D54),"") | AT54: =+IF($AG54=AT$22,MONTH($D54),"") | AU54: =+IF($AG54=AU$22,MONTH($D54),"") | ... AX54: =+IF($AG54=AX$22,MONTH($D54),"")
A55: =+IFERROR(VALUE(MID(AB55,4,4)),"") | B55: =VALUE(RIGHT(C55,LEN(C55)-2)) -> 2667 | C55: O-2667 | D55: 46057 | E55: Caserones | F55: Caserones | G55: Nelson Carvajal Rodríguez | H55: nelson.carvajal@lundinmining.com | I55: Mejoramiento Layout Ingreso Caserones | K55: OS | L55: ND | M55: NAC | N55: #VALUE! | O55: 46071 | P55: Paulo Olivares | Q55: OT | R55: INFRA | T55: DP | U55: 0.1 | V55: 46069 | W55: 1317 | X55: 52 | Y55: =IF(SUM(W55:W55)>0,X55/SUM(W55:W55)*1000000,"N/A") -> 39483.675 | AG55: =YEAR(V55) -> 2026 | AH55: =+IF(AG55=$AH$22,MONTH(V55),"") -> 2 | AI55: =+IF(AG55=$AI$22,MONTH(V55),"") | AJ55: =+IF(AG55=$AJ$22,MONTH(V55),"") | AK55: =+IF(AG55=$AK$22,MONTH(V55),"") | AL55: =+IF(AG55=$AL$22,MONTH(V55),"") | AM55: =+IF($AG55=$AM$22,MONTH($D55),"") | AN55: =+IF($AG55=AN$22,MONTH($D55),"") | AO55: =+IF($AG55=AO$22,MONTH($D55),"") | AP55: =+IF($AG55=AP$22,MONTH($D55),"") | AQ55: =+IF($AG55=AQ$22,MONTH($D55),"") | AR55: =+IF($AG55=AR$22,MONTH($D55),"") | AS55: =+IF($AG55=AS$22,MONTH($D55),"") | AT55: =+IF($AG55=AT$22,MONTH($D55),"") | AU55: =+IF($AG55=AU$22,MONTH($D55),"") | ... AX55: =+IF($AG55=AX$22,MONTH($D55),"")
A56: =+IFERROR(VALUE(MID(AB56,4,4)),"") | B56: =VALUE(RIGHT(C56,LEN(C56)-2)) -> 2666 | C56: O-2666 | D56: 46056 | E56: Austral Gold | F56: Austral Gold | G56: Martin Arnaez | H56: martin.arnaez@australgold.com | I56: Trade Off Ampliación Planta Procesos Procesamiento Dique de Cola | K56: OS | L56: LM | M56: NAC | N56: #VALUE! | O56: 46076 | P56: Patricia Lara | Q56: BP | R56: PLANTA | S56: Preliminar | T56: DP | U56: 0.1 | V56: 46070 | W56: 976 | X56: 0 | Y56: =IF(SUM(W56:W56)>0,X56/SUM(W56:W56)*1000000,"N/A") -> 0 | AG56: =YEAR(V56) -> 2026 | AH56: =+IF(AG56=$AH$22,MONTH(V56),"") -> 2 | AI56: =+IF(AG56=$AI$22,MONTH(V56),"") | AJ56: =+IF(AG56=$AJ$22,MONTH(V56),"") | AK56: =+IF(AG56=$AK$22,MONTH(V56),"") | AL56: =+IF(AG56=$AL$22,MONTH(V56),"") | AM56: =+IF($AG56=$AM$22,MONTH($D56),"") | AN56: =+IF($AG56=AN$22,MONTH($D56),"") | AO56: =+IF($AG56=AO$22,MONTH($D56),"") | AP56: =+IF($AG56=AP$22,MONTH($D56),"") | AQ56: =+IF($AG56=AQ$22,MONTH($D56),"") | AR56: =+IF($AG56=AR$22,MONTH($D56),"") | AS56: =+IF($AG56=AS$22,MONTH($D56),"") | AT56: =+IF($AG56=AT$22,MONTH($D56),"") | AU56: =+IF($AG56=AU$22,MONTH($D56),"") | ... AX56: =+IF($AG56=AX$22,MONTH($D56),"")
A57: =+IFERROR(VALUE(MID(AB57,4,4)),"") | B57: =VALUE(RIGHT(C57,LEN(C57)-2)) -> 2665 | C57: O-2665 | D57: 46056 | E57: BHP | F57: Escondida | G57: Cynthia Zamorano | H57: cynthia.zamorano@bhp.com | I57: Servicio de Comisionamiento Proyecto LSTS-WP05 | K57: COM | L57: LC | M57: NAC | N57: #VALUE! | O57: 46090 | P57: David Cerón | Q57: TA | R57: RELAVES | T57: EP | V57: 46055 | Y57: =IF(SUM(W57:W57)>0,X57/SUM(W57:W57)*1000000,"N/A") -> N/A | AD57: g | AG57: =YEAR(V57) -> 2026 | AH57: =+IF(AG57=$AH$22,MONTH(V57),"") -> 2 | AI57: =+IF(AG57=$AI$22,MONTH(V57),"") | AJ57: =+IF(AG57=$AJ$22,MONTH(V57),"") | AK57: =+IF(AG57=$AK$22,MONTH(V57),"") | AL57: =+IF(AG57=$AL$22,MONTH(V57),"") | AM57: =+IF($AG57=$AM$22,MONTH($D57),"") | AN57: =+IF($AG57=AN$22,MONTH($D57),"") | AO57: =+IF($AG57=AO$22,MONTH($D57),"") | AP57: =+IF($AG57=AP$22,MONTH($D57),"") | AQ57: =+IF($AG57=AQ$22,MONTH($D57),"") | AR57: =+IF($AG57=AR$22,MONTH($D57),"") | AS57: =+IF($AG57=AS$22,MONTH($D57),"") | AT57: =+IF($AG57=AT$22,MONTH($D57),"") | AU57: =+IF($AG57=AU$22,MONTH($D57),"") | ... AX57: =+IF($AG57=AX$22,MONTH($D57),"")
A58: =+IFERROR(VALUE(MID(AB58,4,4)),"") | B58: =VALUE(RIGHT(C58,LEN(C58)-2)) -> 2664 | C58: O-2664 | D58: 46056 | E58: Caserones | F58: Caserones | G58: Nelson Carvajal Rodríguez | H58: nelson.carvajal@lundinmining.com | I58: Reparación Hormigón Planta Concentradora | K58: OS | L58: ND | M58: NAC | N58: #VALUE! | O58: 46097 | P58: Paulo Olivares | Q58: OT | R58: INFRA | T58: EP | V58: 46056 | Y58: =IF(SUM(W58:W58)>0,X58/SUM(W58:W58)*1000000,"N/A") -> N/A | AG58: =YEAR(V58) -> 2026 | AH58: =+IF(AG58=$AH$22,MONTH(V58),"") -> 2 | AI58: =+IF(AG58=$AI$22,MONTH(V58),"") | AJ58: =+IF(AG58=$AJ$22,MONTH(V58),"") | AK58: =+IF(AG58=$AK$22,MONTH(V58),"") | AL58: =+IF(AG58=$AL$22,MONTH(V58),"") | AM58: =+IF($AG58=$AM$22,MONTH($D58),"") | AN58: =+IF($AG58=AN$22,MONTH($D58),"") | AO58: =+IF($AG58=AO$22,MONTH($D58),"") | AP58: =+IF($AG58=AP$22,MONTH($D58),"") | AQ58: =+IF($AG58=AQ$22,MONTH($D58),"") | AR58: =+IF($AG58=AR$22,MONTH($D58),"") | AS58: =+IF($AG58=AS$22,MONTH($D58),"") | AT58: =+IF($AG58=AT$22,MONTH($D58),"") | AU58: =+IF($AG58=AU$22,MONTH($D58),"") | ... AX58: =+IF($AG58=AX$22,MONTH($D58),"")
A59: =+IFERROR(VALUE(MID(AB59,4,4)),"") | B59: =VALUE(RIGHT(C59,LEN(C59)-2)) -> 2663 | C59: O-2663 | D59: 46056 | E59: AngloAmerican | F59: AngloAmerican Los Bronces | G59: Miguel Fiol | H59: miguel.fiol@angloamerican.com | I59: Análisis Pruebas Flotación de Sedimentos Embalse Los Bronces | K59: OS | L59: LC | M59: NAC | N59: #VALUE! | O59: 46071 | P59: Patricia Lara | Q59: TA | R59: PLANTA | T59: DP | U59: 0.1 | V59: 46056 | W59: 222 | X59: 13 | Y59: =IF(SUM(W59:W59)>0,X59/SUM(W59:W59)*1000000,"N/A") -> 58558.559 | AG59: =YEAR(V59) -> 2026 | AH59: =+IF(AG59=$AH$22,MONTH(V59),"") -> 2 | AI59: =+IF(AG59=$AI$22,MONTH(V59),"") | AJ59: =+IF(AG59=$AJ$22,MONTH(V59),"") | AK59: =+IF(AG59=$AK$22,MONTH(V59),"") | AL59: =+IF(AG59=$AL$22,MONTH(V59),"") | AM59: =+IF($AG59=$AM$22,MONTH($D59),"") | AN59: =+IF($AG59=AN$22,MONTH($D59),"") | AO59: =+IF($AG59=AO$22,MONTH($D59),"") | AP59: =+IF($AG59=AP$22,MONTH($D59),"") | AQ59: =+IF($AG59=AQ$22,MONTH($D59),"") | AR59: =+IF($AG59=AR$22,MONTH($D59),"") | AS59: =+IF($AG59=AS$22,MONTH($D59),"") | AT59: =+IF($AG59=AT$22,MONTH($D59),"") | AU59: =+IF($AG59=AU$22,MONTH($D59),"") | ... AX59: =+IF($AG59=AX$22,MONTH($D59),"")
A60: =+IFERROR(VALUE(MID(AB60,4,4)),"") | B60: =VALUE(RIGHT(C60,LEN(C60)-2)) -> 2662 | C60: O-2662 | D60: 46055 | E60: BHP | F60: BHP | I60: Asesoría Relaves Spence SNCT | K60: AE | L60: ND | M60: NAC | N60: #VALUE! | O60: 46092 | P60: Pedro Valencia | Q60: TA | R60: RELAVES | T60: EP | V60: 46055 | Y60: =IF(SUM(W60:W60)>0,X60/SUM(W60:W60)*1000000,"N/A") -> N/A | AG60: =YEAR(V60) -> 2026 | AH60: =+IF(AG60=$AH$22,MONTH(V60),"") -> 2 | AI60: =+IF(AG60=$AI$22,MONTH(V60),"") | AJ60: =+IF(AG60=$AJ$22,MONTH(V60),"") | AK60: =+IF(AG60=$AK$22,MONTH(V60),"") | AL60: =+IF(AG60=$AL$22,MONTH(V60),"") | AM60: =+IF($AG60=$AM$22,MONTH($D60),"") | AN60: =+IF($AG60=AN$22,MONTH($D60),"") | AO60: =+IF($AG60=AO$22,MONTH($D60),"") | AP60: =+IF($AG60=AP$22,MONTH($D60),"") | AQ60: =+IF($AG60=AQ$22,MONTH($D60),"") | AR60: =+IF($AG60=AR$22,MONTH($D60),"") | AS60: =+IF($AG60=AS$22,MONTH($D60),"") | AT60: =+IF($AG60=AT$22,MONTH($D60),"") | AU60: =+IF($AG60=AU$22,MONTH($D60),"") | ... AX60: =+IF($AG60=AX$22,MONTH($D60),"")
A61: =+IFERROR(VALUE(MID(AB61,4,4)),"") | B61: =VALUE(RIGHT(C61,LEN(C61)-2)) -> 2661 | C61: O-2661 | D61: 46055 | E61: Centinela | F61: Centinela | G61: ARIBA | H61: ARIBA | I61: Contrato Marco Ingenierías Intermedias | K61: CM | L61: LM | M61: NAC | N61: #VALUE! | O61: 46097 | P61: José Muñoz | Q61: BP-PI-TA | R61: CM | T61: EP | V61: 46055 | Y61: =IF(SUM(W61:W61)>0,X61/SUM(W61:W61)*1000000,"N/A") -> N/A | AG61: =YEAR(V61) -> 2026 | AH61: =+IF(AG61=$AH$22,MONTH(V61),"") -> 2 | AI61: =+IF(AG61=$AI$22,MONTH(V61),"") | AJ61: =+IF(AG61=$AJ$22,MONTH(V61),"") | AK61: =+IF(AG61=$AK$22,MONTH(V61),"") | AL61: =+IF(AG61=$AL$22,MONTH(V61),"") | AM61: =+IF($AG61=$AM$22,MONTH($D61),"") | AN61: =+IF($AG61=AN$22,MONTH($D61),"") | AO61: =+IF($AG61=AO$22,MONTH($D61),"") | AP61: =+IF($AG61=AP$22,MONTH($D61),"") | AQ61: =+IF($AG61=AQ$22,MONTH($D61),"") | AR61: =+IF($AG61=AR$22,MONTH($D61),"") | AS61: =+IF($AG61=AS$22,MONTH($D61),"") | AT61: =+IF($AG61=AT$22,MONTH($D61),"") | AU61: =+IF($AG61=AU$22,MONTH($D61),"") | ... AX61: =+IF($AG61=AX$22,MONTH($D61),"")
A62: =+IFERROR(VALUE(MID(AB62,4,4)),"") | B62: =VALUE(RIGHT(C62,LEN(C62)-2)) -> 2660 | C62: O-2660 | D62: 46047 | E62: Codelco | F62: DAND | G62: ARIBA | H62: ARIBA | I62: Ingeniería de Estudios Complementarios para el Desarrollo del Negocio de Andina Post Ramsay | K62: OS | L62: LM | M62: NAC | N62: #VALUE! | O62: 46085 | P62: Patricia Lara | Q62: BP | R62: PLANTA | S62: 0.66666667 | T62: NL | V62: 46055 | Y62: =IF(SUM(W62:W62)>0,X62/SUM(W62:W62)*1000000,"N/A") -> N/A | AG62: =YEAR(V62) -> 2026 | AH62: =+IF(AG62=$AH$22,MONTH(V62),"") -> 2 | AI62: =+IF(AG62=$AI$22,MONTH(V62),"") | AJ62: =+IF(AG62=$AJ$22,MONTH(V62),"") | AK62: =+IF(AG62=$AK$22,MONTH(V62),"") | AL62: =+IF(AG62=$AL$22,MONTH(V62),"") | AM62: =+IF($AG62=$AM$22,MONTH($D62),"") | AN62: =+IF($AG62=AN$22,MONTH($D62),"") | AO62: =+IF($AG62=AO$22,MONTH($D62),"") | AP62: =+IF($AG62=AP$22,MONTH($D62),"") | AQ62: =+IF($AG62=AQ$22,MONTH($D62),"") | AR62: =+IF($AG62=AR$22,MONTH($D62),"") | AS62: =+IF($AG62=AS$22,MONTH($D62),"") | AT62: =+IF($AG62=AT$22,MONTH($D62),"") | AU62: =+IF($AG62=AU$22,MONTH($D62),"") | ... AX62: =+IF($AG62=AX$22,MONTH($D62),"")
A63: =+IFERROR(VALUE(MID(AB63,4,4)),"") | B63: =VALUE(RIGHT(C63,LEN(C63)-2)) -> 2659 | C63: O-2659 | D63: 46051 | E63: BHP | F63: Escondida | G63: Juan González | H63: juan.r.gonzalez1@bhp.com | I63: Budgetaria Comisionamiento Proyecto SCPY Ripios Disposal (SCPY-RD) | K63: COM | L63: LC | M63: NAC | N63: #VALUE! | O63: 46055 | P63: David Cerón | Q63: COM | R63: PLANTA | S63: Botadero de Ripios | T63: PP | V63: 46055 | W63: 2793 | X63: 138 | Y63: =IF(SUM(W63:W63)>0,X63/SUM(W63:W63)*1000000,"N/A") -> 49409.237 | AG63: =YEAR(V63) -> 2026 | AH63: =+IF(AG63=$AH$22,MONTH(V63),"") -> 2 | AI63: =+IF(AG63=$AI$22,MONTH(V63),"") | AJ63: =+IF(AG63=$AJ$22,MONTH(V63),"") | AK63: =+IF(AG63=$AK$22,MONTH(V63),"") | AL63: =+IF(AG63=$AL$22,MONTH(V63),"") | AM63: =+IF($AG63=$AM$22,MONTH($D63),"") | AN63: =+IF($AG63=AN$22,MONTH($D63),"") | AO63: =+IF($AG63=AO$22,MONTH($D63),"") | AP63: =+IF($AG63=AP$22,MONTH($D63),"") | AQ63: =+IF($AG63=AQ$22,MONTH($D63),"") | AR63: =+IF($AG63=AR$22,MONTH($D63),"") | AS63: =+IF($AG63=AS$22,MONTH($D63),"") | AT63: =+IF($AG63=AT$22,MONTH($D63),"") | AU63: =+IF($AG63=AU$22,MONTH($D63),"") | ... AX63: =+IF($AG63=AX$22,MONTH($D63),"")
A64: =+IFERROR(VALUE(MID(AB64,4,4)),"") -> 466 | B64: =VALUE(RIGHT(C64,LEN(C64)-2)) -> 2658 | C64: O-2658 | D64: 46049 | E64: BHP | F64: Spence | G64: BHP Supplier | H64: supplierportal.bhp.com | I64: Ingeniería de Detalles Impermeabilización de Celda 11 - Etapa 2 - ODS01 - SH-0466 | K64: ID | L64: LC | M64: NAC | N64: #VALUE! | O64: TBD | P64: Cristian López | Q64: TA | R64: RELAVES | T64: PG | V64: 46062 | W64: 1034 | X64: 58.422 | Y64: =IF(SUM(W64:W64)>0,X64/SUM(W64:W64)*1000000,"N/A") -> 56500.967 | AB64: SH-0466 ODS01 | AG64: =YEAR(V64) -> 2026 | AH64: =+IF(AG64=$AH$22,MONTH(V64),"") -> 2 | AI64: =+IF(AG64=$AI$22,MONTH(V64),"") | AJ64: =+IF(AG64=$AJ$22,MONTH(V64),"") | AK64: =+IF(AG64=$AK$22,MONTH(V64),"") | AL64: =+IF(AG64=$AL$22,MONTH(V64),"") | AM64: =+IF($AG64=$AM$22,MONTH($D64),"") | AN64: =+IF($AG64=AN$22,MONTH($D64),"") | AO64: =+IF($AG64=AO$22,MONTH($D64),"") | AP64: =+IF($AG64=AP$22,MONTH($D64),"") | AQ64: =+IF($AG64=AQ$22,MONTH($D64),"") | AR64: =+IF($AG64=AR$22,MONTH($D64),"") | AS64: =+IF($AG64=AS$22,MONTH($D64),"") | AT64: =+IF($AG64=AT$22,MONTH($D64),"") | AU64: =+IF($AG64=AU$22,MONTH($D64),"") | ... AX64: =+IF($AG64=AX$22,MONTH($D64),"")
A65: =+IFERROR(VALUE(MID(AB65,4,4)),"") | B65: =VALUE(RIGHT(C65,LEN(C65)-2)) -> 2657 | C65: O-2657 | D65: 46048 | E65: Metaproject | F65: AngloAmerican | G65: Fabian Chacana Moreira | H65: fchacana@metaprojectgroup.com | I65: Proceso de Segmentación y Precalificación de Proveedores y Contratistas | K65: PRE | L65: LM | M65: NAC | N65: #VALUE! | O65: 46091 | P65: Tomás Fernández | Q65: OT | R65: PRE | T65: EP | V65: 46066 | Y65: =IF(SUM(W65:W65)>0,X65/SUM(W65:W65)*1000000,"N/A") -> N/A | AG65: =YEAR(V65) -> 2026 | AH65: =+IF(AG65=$AH$22,MONTH(V65),"") -> 2 | AI65: =+IF(AG65=$AI$22,MONTH(V65),"") | AJ65: =+IF(AG65=$AJ$22,MONTH(V65),"") | AK65: =+IF(AG65=$AK$22,MONTH(V65),"") | AL65: =+IF(AG65=$AL$22,MONTH(V65),"") | AM65: =+IF($AG65=$AM$22,MONTH($D65),"") | AN65: =+IF($AG65=AN$22,MONTH($D65),"") | AO65: =+IF($AG65=AO$22,MONTH($D65),"") | AP65: =+IF($AG65=AP$22,MONTH($D65),"") | AQ65: =+IF($AG65=AQ$22,MONTH($D65),"") | AR65: =+IF($AG65=AR$22,MONTH($D65),"") | AS65: =+IF($AG65=AS$22,MONTH($D65),"") | AT65: =+IF($AG65=AT$22,MONTH($D65),"") | AU65: =+IF($AG65=AU$22,MONTH($D65),"") | ... AX65: =+IF($AG65=AX$22,MONTH($D65),"")
A66: =+IFERROR(VALUE(MID(AB66,4,4)),"") -> 271 | B66: =VALUE(RIGHT(C66,LEN(C66)-2)) -> 2656 | C66: O-2656 | D66: 46045 | E66: SGSCM | F66: SGSCM | G66: Félix Lastra | H66: Felix.Lastra@sgscm.cl | I66: Ingeniería Conceptual y Detalle – Operación de Sistema de Transporte de Relaves de Etapas Próximas de Crecimiento | K66: ID | L66: ND | M66: NAC | N66: #VALUE! | O66: 46045 | P66: Fernando Calle | Q66: TA | R66: RELAVES | S66: En Rev. 1 | T66: PG | V66: 46072 | W66: 3992 | X66: 168.742 | Y66: =IF(SUM(W66:W66)>0,X66/SUM(W66:W66)*1000000,"N/A") -> 42270.04 | AB66: SH-0271 ODT-33 | AG66: =YEAR(V66) -> 2026 | AH66: =+IF(AG66=$AH$22,MONTH(V66),"") -> 2 | AI66: =+IF(AG66=$AI$22,MONTH(V66),"") | AJ66: =+IF(AG66=$AJ$22,MONTH(V66),"") | AK66: =+IF(AG66=$AK$22,MONTH(V66),"") | AL66: =+IF(AG66=$AL$22,MONTH(V66),"") | AM66: =+IF($AG66=$AM$22,MONTH($D66),"") | AN66: =+IF($AG66=AN$22,MONTH($D66),"") | AO66: =+IF($AG66=AO$22,MONTH($D66),"") | AP66: =+IF($AG66=AP$22,MONTH($D66),"") | AQ66: =+IF($AG66=AQ$22,MONTH($D66),"") | AR66: =+IF($AG66=AR$22,MONTH($D66),"") | AS66: =+IF($AG66=AS$22,MONTH($D66),"") | AT66: =+IF($AG66=AT$22,MONTH($D66),"") | AU66: =+IF($AG66=AU$22,MONTH($D66),"") | ... AX66: =+IF($AG66=AX$22,MONTH($D66),"")
A67: =+IFERROR(VALUE(MID(AB67,4,4)),"") -> 271 | B67: =VALUE(RIGHT(C67,LEN(C67)-2)) -> 2655 | C67: O-2655 | D67: 46045 | E67: SGSCM | F67: SGSCM | G67: Félix Lastra | H67: Felix.Lastra@sgscm.cl | I67: Ingeniería Detalle - Conexión líneas 800mm y 900mm en Cruceta Principal | K67: ID | L67: ND | M67: NAC | N67: #VALUE! | O67: 46045 | P67: Fernando Calle | Q67: TA | R67: RELAVES | S67: En Rev. 1 | T67: PG | V67: 46072 | W67: 614 | X67: 25.513 | Y67: =IF(SUM(W67:W67)>0,X67/SUM(W67:W67)*1000000,"N/A") -> 41552.117 | AB67: SH-0271 ODT-32 | AG67: =YEAR(V67) -> 2026 | AH67: =+IF(AG67=$AH$22,MONTH(V67),"") -> 2 | AI67: =+IF(AG67=$AI$22,MONTH(V67),"") | AJ67: =+IF(AG67=$AJ$22,MONTH(V67),"") | AK67: =+IF(AG67=$AK$22,MONTH(V67),"") | AL67: =+IF(AG67=$AL$22,MONTH(V67),"") | AM67: =+IF($AG67=$AM$22,MONTH($D67),"") | AN67: =+IF($AG67=AN$22,MONTH($D67),"") | AO67: =+IF($AG67=AO$22,MONTH($D67),"") | AP67: =+IF($AG67=AP$22,MONTH($D67),"") | AQ67: =+IF($AG67=AQ$22,MONTH($D67),"") | AR67: =+IF($AG67=AR$22,MONTH($D67),"") | AS67: =+IF($AG67=AS$22,MONTH($D67),"") | AT67: =+IF($AG67=AT$22,MONTH($D67),"") | AU67: =+IF($AG67=AU$22,MONTH($D67),"") | ... AX67: =+IF($AG67=AX$22,MONTH($D67),"")
A68: =+IFERROR(VALUE(MID(AB68,4,4)),"") -> 271 | B68: =VALUE(RIGHT(C68,LEN(C68)-2)) -> 2654 | C68: O-2654 | D68: 46045 | E68: SGSCM | F68: SGSCM | G68: Félix Lastra | H68: Felix.Lastra@sgscm.cl | I68: Ingeniería Conceptual y Detalle - Instalación de Placas Orificio para Operación Bombeada y Conexión Estanque de Relaves a Línea de HDPE 800mm | K68: ID | L68: ND | M68: NAC | N68: #VALUE! | O68: 46045 | P68: Fernando Calle | Q68: TA | R68: RELAVES | S68: En Rev. 1 | T68: PG | V68: 46072 | W68: 2088 | X68: 93.415 | Y68: =IF(SUM(W68:W68)>0,X68/SUM(W68:W68)*1000000,"N/A") -> 44738.985 | AB68: SH-0271 ODT-31 | AG68: =YEAR(V68) -> 2026 | AH68: =+IF(AG68=$AH$22,MONTH(V68),"") -> 2 | AI68: =+IF(AG68=$AI$22,MONTH(V68),"") | AJ68: =+IF(AG68=$AJ$22,MONTH(V68),"") | AK68: =+IF(AG68=$AK$22,MONTH(V68),"") | AL68: =+IF(AG68=$AL$22,MONTH(V68),"") | AM68: =+IF($AG68=$AM$22,MONTH($D68),"") | AN68: =+IF($AG68=AN$22,MONTH($D68),"") | AO68: =+IF($AG68=AO$22,MONTH($D68),"") | AP68: =+IF($AG68=AP$22,MONTH($D68),"") | AQ68: =+IF($AG68=AQ$22,MONTH($D68),"") | AR68: =+IF($AG68=AR$22,MONTH($D68),"") | AS68: =+IF($AG68=AS$22,MONTH($D68),"") | AT68: =+IF($AG68=AT$22,MONTH($D68),"") | AU68: =+IF($AG68=AU$22,MONTH($D68),"") | ... AX68: =+IF($AG68=AX$22,MONTH($D68),"")
A69: =+IFERROR(VALUE(MID(AB69,4,4)),"") -> 368 | B69: =VALUE(RIGHT(C69,LEN(C69)-2)) -> 2653 | C69: O-2653 | D69: 46045 | E69: BHP | F69: Spence | G69: Marcos Madrid | H69: marcos.madrid@bhp.com | I69: Modificación al Listado de Entregables y Actividades por requerimientos del desarrollo de la ingeniería | K69: OS | L69: ND | M69: NAC | N69: #VALUE! | O69: 46045 | P69: Cristian López | Q69: OT | R69: RELAVES | T69: DP | V69: 46044 | W69: -46.9 | X69: 12.781 | Y69: =IF(SUM(W69:W69)>0,X69/SUM(W69:W69)*1000000,"N/A") -> N/A | AB69: SH-0368 (NOC 11) | AD69: N/A | AG69: =YEAR(V69) -> 2026 | AH69: =+IF(AG69=$AH$22,MONTH(V69),"") -> 1 | AI69: =+IF(AG69=$AI$22,MONTH(V69),"") | AJ69: =+IF(AG69=$AJ$22,MONTH(V69),"") | AK69: =+IF(AG69=$AK$22,MONTH(V69),"") | AL69: =+IF(AG69=$AL$22,MONTH(V69),"") | AM69: =+IF($AG69=$AM$22,MONTH($D69),"") | AN69: =+IF($AG69=AN$22,MONTH($D69),"") | AO69: =+IF($AG69=AO$22,MONTH($D69),"") | AP69: =+IF($AG69=AP$22,MONTH($D69),"") | AQ69: =+IF($AG69=AQ$22,MONTH($D69),"") | AR69: =+IF($AG69=AR$22,MONTH($D69),"") | AS69: =+IF($AG69=AS$22,MONTH($D69),"") | AT69: =+IF($AG69=AT$22,MONTH($D69),"") | AU69: =+IF($AG69=AU$22,MONTH($D69),"") | ... AX69: =+IF($AG69=AX$22,MONTH($D69),"")
A70: =+IFERROR(VALUE(MID(AB70,4,4)),"") | B70: =VALUE(RIGHT(C70,LEN(C70)-2)) -> 2652 | C70: O-2652 | D70: 46044 | E70: Caserones | F70: Caserones | G70: Nelson Carvajal Rodríguez | H70: nelson.carvajal@lundinmining.com | I70: Ingeniería Conceptual Incorporación de 4to Chancador de Pebbles | K70: ID | L70: LC | M70: NAC | N70: #VALUE! | O70: 46077 | P70: Patricia Lara | Q70: BP | R70: PLANTA | T70: DP | U70: 0.1 | V70: 46059 | W70: 1522 | X70: =1525*39773/1000000 -> 60.653825 | Y70: =IF(SUM(W70:W70)>0,X70/SUM(W70:W70)*1000000,"N/A") -> 39851.396 | AG70: =YEAR(V70) -> 2026 | AH70: =+IF(AG70=$AH$22,MONTH(V70),"") -> 2 | AI70: =+IF(AG70=$AI$22,MONTH(V70),"") | AJ70: =+IF(AG70=$AJ$22,MONTH(V70),"") | AK70: =+IF(AG70=$AK$22,MONTH(V70),"") | AW70: =+IF($AG70=AW$22,MONTH($D70),"") | AX70: =+IF($AG70=AX$22,MONTH($D70),"")
A71: =+IFERROR(VALUE(MID(AB71,4,4)),"") | B71: =VALUE(RIGHT(C71,LEN(C71)-2)) -> 2651 | C71: O-2651 | D71: 46044 | E71: Caserones | F71: Caserones | G71: Nelson Carvajal Rodríguez | H71: nelson.carvajal@lundinmining.com | I71: Ingeniería Conceptual Incorporación de dos Celdas Columnares en Planta de Flotación | K71: ID | L71: LC | M71: NAC | N71: #VALUE! | O71: 46077 | P71: Patricia Lara | Q71: BP | R71: PLANTA | T71: DP | U71: 0.1 | V71: 46059 | W71: 1995 | X71: =2249*39773/1000000 -> 89.449477 | Y71: =IF(SUM(W71:W71)>0,X71/SUM(W71:W71)*1000000,"N/A") -> 44836.831 | AG71: =YEAR(V71) -> 2026 | AH71: =+IF(AG71=$AH$22,MONTH(V71),"") -> 2 | AI71: =+IF(AG71=$AI$22,MONTH(V71),"") | AJ71: =+IF(AG71=$AJ$22,MONTH(V71),"") | AK71: =+IF(AG71=$AK$22,MONTH(V71),"") | AW71: =+IF($AG71=AW$22,MONTH($D71),"") | AX71: =+IF($AG71=AX$22,MONTH($D71),"")
A72: =+IFERROR(VALUE(MID(AB72,4,4)),"") | B72: =VALUE(RIGHT(C72,LEN(C72)-2)) -> 2650 | C72: O-2650 | D72: 46044 | E72: Codelco | F72: DET | G72: ARIBA | H72: ARIBA | I72: Contrato Marco Servicios de Ingeniería Proyectos Agua | K72: CM | L72: LM | M72: NAC | N72: #VALUE! | O72: 46100 | P72: José Muñoz | Q72: BP | R72: PIPELINES | T72: NL | V72: 46044 | Y72: =IF(SUM(W72:W72)>0,X72/SUM(W72:W72)*1000000,"N/A") -> N/A | AG72: =YEAR(V72) -> 2026 | AH72: =+IF(AG72=$AH$22,MONTH(V72),"") -> 1 | AI72: =+IF(AG72=$AI$22,MONTH(V72),"") | AJ72: =+IF(AG72=$AJ$22,MONTH(V72),"") | AK72: =+IF(AG72=$AK$22,MONTH(V72),"") | AW72: =+IF($AG72=AW$22,MONTH($D72),"") | AX72: =+IF($AG72=AX$22,MONTH($D72),"")
A73: =+IFERROR(VALUE(MID(AB73,4,4)),"") | B73: =VALUE(RIGHT(C73,LEN(C73)-2)) -> 2649 | C73: O-2649 | D73: 46043 | E73: Minera San Gerónimo | F73: AngloAmerican | G73: Jaime Araya | H73: jaime.araya@cmsg.cl | I73: Contrato Marco Servicios de Ingeniería - Minera San Gerónimo | K73: CM | L73: LM | M73: NAC | N73: #VALUE! | O73: 46063 | P73: Waldo Bustos | Q73: BP | R73: CM | T73: DP | U73: 0.01 | V73: 46064 | W73: 1000 | X73: 42 | Y73: =IF(SUM(W73:W73)>0,X73/SUM(W73:W73)*1000000,"N/A") -> 42000 | AG73: =YEAR(V73) -> 2026 | AH73: =+IF(AG73=$AH$22,MONTH(V73),"") -> 2 | AI73: =+IF(AG73=$AI$22,MONTH(V73),"") | AJ73: =+IF(AG73=$AJ$22,MONTH(V73),"") | AK73: =+IF(AG73=$AK$22,MONTH(V73),"") | AW73: =+IF($AG73=AW$22,MONTH($D73),"") | AX73: =+IF($AG73=AX$22,MONTH($D73),"")
A74: =+IFERROR(VALUE(MID(AB74,4,4)),"") | B74: =VALUE(RIGHT(C74,LEN(C74)-2)) -> 2648 | C74: O-2648 | D74: 46043 | E74: AngloAmerican | F74: AngloAmerican | I74: Balance Hidroquímico | K74: OS | L74: ND | M74: NAC | N74: #VALUE! | O74: 46064 | P74: Pamela Alhucema | Q74: BP | R74: PLANTA | T74: DP | U74: 0.1 | V74: 46064 | W74: 1817 | X74: 95 | Y74: =IF(SUM(W74:W74)>0,X74/SUM(W74:W74)*1000000,"N/A") -> 52283.985 | AG74: =YEAR(V74) -> 2026 | AH74: =+IF(AG74=$AH$22,MONTH(V74),"") -> 2 | AI74: =+IF(AG74=$AI$22,MONTH(V74),"") | AJ74: =+IF(AG74=$AJ$22,MONTH(V74),"") | AK74: =+IF(AG74=$AK$22,MONTH(V74),"") | AW74: =+IF($AG74=AW$22,MONTH($D74),"") | AX74: =+IF($AG74=AX$22,MONTH($D74),"")
A75: =+IFERROR(VALUE(MID(AB75,4,4)),"") | B75: =VALUE(RIGHT(C75,LEN(C75)-2)) -> 2647 | C75: O-2647 | D75: 46038 | E75: Codelco | F75: VP Relaves | G75: Gonzalo Caro | I75: Contrato Boutique Vicepresidencia Relaves | K75: IG | L75: ND | M75: NAC | N75: #VALUE! | O75: 46097 | P75: Luis Ilabarca | Q75: TA | R75: RELAVES | T75: EP | U75: 0 | V75: 46041 | Y75: =IF(SUM(W75:W75)>0,X75/SUM(W75:W75)*1000000,"N/A") -> N/A | AG75: =YEAR(V75) -> 2026 | AH75: =+IF(AG75=$AH$22,MONTH(V75),"") -> 1 | AI75: =+IF(AG75=$AI$22,MONTH(V75),"") | AJ75: =+IF(AG75=$AJ$22,MONTH(V75),"") | AK75: =+IF(AG75=$AK$22,MONTH(V75),"") | AW75: =+IF($AG75=AW$22,MONTH($D75),"") | AX75: =+IF($AG75=AX$22,MONTH($D75),"")
A76: =+IFERROR(VALUE(MID(AB76,4,4)),"") | B76: =VALUE(RIGHT(C76,LEN(C76)-2)) -> 2646 | C76: O-2646 | D76: 46038 | E76: Codelco | F76: DSAL | G76: Virgilio Saavedra Flores | H76: VSaav006@codelco.cl | I76: Mejoramiento Infraestructura Hídrica - DSAL | K76: IG | L76: ND | M76: NAC | N76: #VALUE! | O76: 46098 | P76: Luis Ilabarca | Q76: OT | R76: INFRA | T76: EP | U76: 0 | V76: 46041 | Y76: =IF(SUM(W76:W76)>0,X76/SUM(W76:W76)*1000000,"N/A") -> N/A | AG76: =YEAR(V76) -> 2026 | AH76: =+IF(AG76=$AH$22,MONTH(V76),"") -> 1 | AI76: =+IF(AG76=$AI$22,MONTH(V76),"") | AJ76: =+IF(AG76=$AJ$22,MONTH(V76),"") | AK76: =+IF(AG76=$AK$22,MONTH(V76),"") | AW76: =+IF($AG76=AW$22,MONTH($D76),"") | AX76: =+IF($AG76=AX$22,MONTH($D76),"")
A77: =+IFERROR(VALUE(MID(AB77,4,4)),"") | B77: =VALUE(RIGHT(C77,LEN(C77)-2)) -> 2645 | C77: O-2645 | D77: 46037 | E77: Codelco | F77: DAND | G77: ARIBA | H77: ARIBA | I77: Análisis del Estado de Elementos de Conducción, Manejo y Disposición de Relaves DAND | K77: OS | L77: LM | M77: NAC | N77: #VALUE! | O77: 46104 | P77: TBD | Q77: TA | R77: RELAVES | T77: NL | V77: 46041 | Y77: =IF(SUM(W77:W77)>0,X77/SUM(W77:W77)*1000000,"N/A") -> N/A | AG77: =YEAR(V77) -> 2026 | AH77: =+IF(AG77=$AH$22,MONTH(V77),"") -> 1 | AI77: =+IF(AG77=$AI$22,MONTH(V77),"") | AJ77: =+IF(AG77=$AJ$22,MONTH(V77),"") | AK77: =+IF(AG77=$AK$22,MONTH(V77),"") | AL77: =+IF(AG77=$AL$22,MONTH(V77),"") | AM77: =+IF($AG77=$AM$22,MONTH($D77),"") | AN77: =+IF($AG77=AN$22,MONTH($D77),"") | AO77: =+IF($AG77=AO$22,MONTH($D77),"") | AP77: =+IF($AG77=AP$22,MONTH($D77),"") | AQ77: =+IF($AG77=AQ$22,MONTH($D77),"") | AR77: =+IF($AG77=AR$22,MONTH($D77),"") | AS77: =+IF($AG77=AS$22,MONTH($D77),"") | AT77: =+IF($AG77=AT$22,MONTH($D77),"") | AU77: =+IF($AG77=AU$22,MONTH($D77),"") | ... AX77: =+IF($AG77=AX$22,MONTH($D77),"")
A78: =+IFERROR(VALUE(MID(AB78,4,4)),"") | B78: =VALUE(RIGHT(C78,LEN(C78)-2)) -> 2644 | C78: O-2644 | D78: 46031 | E78: Sociedad Manríquez S.A. | F78: Aguas Pacífico | G78: Miguel Ángel Soto | H78: sergio.rosales@aguaspacifico.cl | I78: Asesoría Especializada Luis Ilabarca Tranque Pampa Austral | K78: AE | L78: ND | M78: NAC | N78: #VALUE! | O78: 46036 | P78: Luis Ilabarca | Q78: TA | R78: RELAVES | T78: DP | U78: 0.2 | V78: 46036 | W78: 240 | X78: =240*2.5*39672/1000000 -> 23.8032 | Y78: =IF(SUM(W78:W78)>0,X78/SUM(W78:W78)*1000000,"N/A") -> 99180 | AG78: =YEAR(V78) -> 2026 | AH78: =+IF(AG78=$AH$22,MONTH(V78),"") -> 1 | AI78: =+IF(AG78=$AI$22,MONTH(V78),"") | AJ78: =+IF(AG78=$AJ$22,MONTH(V78),"") | AK78: =+IF(AG78=$AK$22,MONTH(V78),"") | AW78: =+IF($AG78=AW$22,MONTH($D78),"") | AX78: =+IF($AG78=AX$22,MONTH($D78),"")
A79: =+IFERROR(VALUE(MID(AB79,4,4)),"") -> 399 | B79: =VALUE(RIGHT(C79,LEN(C79)-2)) -> 2643 | C79: O-2643 | D79: 46035 | E79: CMP | F79: CMP | G79: Jacques Lito Rengifo Bravo | H79: jrengifo@cmp.cl | I79: Contrato Marco Servicio de Ingeniería Multidisciplinaria - ODS N°43 - Alcances EE-IN en ODS32 ID Integración Proyecto Solución Concentrado Planta Magnetita en Puerto Punta Totoralillo (SCPMP) - SH-0399 | K79: ID | L79: LC | M79: NAC | N79: #VALUE! | O79: 46037 | P79: Patricia Lara | Q79: BP | R79: PLANTA | T79: DP | U79: 0.1 | V79: 46035 | W79: 1118 | X79: 47.461 | Y79: =IF(SUM(W79:W79)>0,X79/SUM(W79:W79)*1000000,"N/A") -> 42451.699 | AB79: SH-0399 ODS N°43 | AG79: =YEAR(V79) -> 2026 | AH79: =+IF(AG79=$AH$22,MONTH(V79),"") -> 1 | AI79: =+IF(AG79=$AI$22,MONTH(V79),"") | AJ79: =+IF(AG79=$AJ$22,MONTH(V79),"") | AK79: =+IF(AG79=$AK$22,MONTH(V79),"") | AW79: =+IF($AG79=AW$22,MONTH($D79),"") | AX79: =+IF($AG79=AX$22,MONTH($D79),"")
A80: =+IFERROR(VALUE(MID(AB80,4,4)),"") -> 366 | B80: =VALUE(RIGHT(C80,LEN(C80)-2)) -> 2642 | C80: O-2642 | D80: 46028 | E80: VALE | F80: VALE | G80: Paulo Karol | H80: paulo.karol@vale.com | I80: Engenharia Hidraulica - Apoio Tecnico Engenharia Vale - NOC03 | K80: AP | L80: LM | M80: INT | N80: #VALUE! | O80: 46029 | P80: Dolglas Souza | Q80: OT | R80: RELAVES | S80: Revisión 6. 18 meses. Contrato Marco y Apoyo en Terreno. | T80: PG | V80: 46031 | Y80: =IF(SUM(W80:W80)>0,X80/SUM(W80:W80)*1000000,"N/A") -> N/A | AB80: SH-0366 NOC3 | AG80: =YEAR(V80) -> 2026 | AH80: =+IF(AG80=$AH$22,MONTH(V80),"") -> 1 | AI80: =+IF(AG80=$AI$22,MONTH(V80),"") | AJ80: =+IF(AG80=$AJ$22,MONTH(V80),"") | AK80: =+IF(AG80=$AK$22,MONTH(V80),"") | AW80: =+IF($AG80=AW$22,MONTH($D80),"") | AX80: =+IF($AG80=AX$22,MONTH($D80),"")
A81: =+IFERROR(VALUE(MID(AB81,4,4)),"") -> 467 | B81: =VALUE(RIGHT(C81,LEN(C81)-2)) -> 2641 | C81: O-2641 | D81: 46020 | E81: Grupo Errázuriz | F81: Grupo Errázuriz | G81: Alejandro Puelles | H81: apuelles@grupoerrazuriz.cl | I81: Ingeniería de Prefactibilidad Ampliación Planta Tambillos ODS01 CM - Grupo Errázuriz | K81: IPref | L81: LC | M81: NAC | N81: #VALUE! | O81: 46029 | P81: Patricia Lara | Q81: BP | R81: PLANTA | T81: PG | V81: 46031 | W81: 98 | X81: =218*39670/1000000 -> 8.64806 | Y81: =IF(SUM(W81:W81)>0,X81/SUM(W81:W81)*1000000,"N/A") -> 88245.51 | AB81: SH-0467 ODS01 | AG81: =YEAR(V81) -> 2026 | AH81: =+IF(AG81=$AH$22,MONTH(V81),"") -> 1 | AI81: =+IF(AG81=$AI$22,MONTH(V81),"") | AJ81: =+IF(AG81=$AJ$22,MONTH(V81),"") | AK81: =+IF(AG81=$AK$22,MONTH(V81),"") | AL81: =+IF(AG81=$AL$22,MONTH(V81),"") | AM81: =+IF($AG81=$AM$22,MONTH($D81),"") | AN81: =+IF($AG81=AN$22,MONTH($D81),"") | AO81: =+IF($AG81=AO$22,MONTH($D81),"") | AP81: =+IF($AG81=AP$22,MONTH($D81),"") | AQ81: =+IF($AG81=AQ$22,MONTH($D81),"") | AR81: =+IF($AG81=AR$22,MONTH($D81),"") | AS81: =+IF($AG81=AS$22,MONTH($D81),"") | AT81: =+IF($AG81=AT$22,MONTH($D81),"") | AU81: =+IF($AG81=AU$22,MONTH($D81),"") | ... AX81: =+IF($AG81=AX$22,MONTH($D81),"")
A82: =+IFERROR(VALUE(MID(AB82,4,4)),"") -> 390 | B82: =VALUE(RIGHT(C82,LEN(C82)-2)) -> 2640 | C82: O-2640 | D82: 45971 | E82: BHP | F82: Spence | H82: stephan.matulic@bhp.com | I82: Entregables Impactados por Cambio de Base Topográfica por parte de BHP - SH-0390 - PDN73 | K82: ID | L82: ND | M82: NAC | N82: #VALUE! | O82: 45976 | P82: Pedro Valencia | Q82: TA | R82: RELAVES | T82: PG | V82: 45981 | W82: 3364 | X82: 118.318 | Y82: =IF(SUM(W82:W82)>0,X82/SUM(W82:W82)*1000000,"N/A") -> 35171.819 | AB82: SH-0390 PDN73 | AG82: =YEAR(D82) -> 2025 | AH82: =+IF(AG82=$AH$22,MONTH(V82),"") | AI82: =+IF(AG82=$AI$22,MONTH(V82),"") -> 11 | AJ82: =+IF(AG82=$AJ$22,MONTH(V82),"") | AK82: =+IF(AG82=$AK$22,MONTH(V82),"") | AL82: =+IF(AG82=$AL$22,MONTH(V82),"") | AM82: =+IF($AG82=$AM$22,MONTH($D82),"") | AN82: =+IF($AG82=AN$22,MONTH($D82),"") | AO82: =+IF($AG82=AO$22,MONTH($D82),"") | AP82: =+IF($AG82=AP$22,MONTH($D82),"") | AQ82: =+IF($AG82=AQ$22,MONTH($D82),"") | AR82: =+IF($AG82=AR$22,MONTH($D82),"") | AS82: =+IF($AG82=AS$22,MONTH($D82),"") | AT82: =+IF($AG82=AT$22,MONTH($D82),"") | AU82: =+IF($AG82=AU$22,MONTH($D82),"") | ... AX82: =+IF($AG82=AX$22,MONTH($D82),"")
A83: =+IFERROR(VALUE(MID(AB83,4,4)),"") -> 390 | B83: =VALUE(RIGHT(C83,LEN(C83)-2)) -> 2639 | C83: O-2639 | D83: 45971 | E83: BHP | F83: Spence | H83: stephan.matulic@bhp.com | I83: Solicitud Respuestas a Consultas de Licitación Electromecánico y Actualización de Alcance Documentos SoW, Bases de Medición y Pago - SH-0390 - PDN71 | K83: ID | L83: ND | M83: NAC | N83: #VALUE! | O83: 45976 | P83: Pedro Valencia | Q83: TA | R83: RELAVES | T83: PG | V83: 45981 | W83: 625 | X83: 28.251 | Y83: =IF(SUM(W83:W83)>0,X83/SUM(W83:W83)*1000000,"N/A") -> 45201.6 | AB83: SH-0390 PDN71 | AG83: =YEAR(D83) -> 2025 | AH83: =+IF(AG83=$AH$22,MONTH(V83),"") | AI83: =+IF(AG83=$AI$22,MONTH(V83),"") -> 11 | AJ83: =+IF(AG83=$AJ$22,MONTH(V83),"") | AK83: =+IF(AG83=$AK$22,MONTH(V83),"") | AL83: =+IF(AG83=$AL$22,MONTH(V83),"") | AM83: =+IF($AG83=$AM$22,MONTH($D83),"") | AN83: =+IF($AG83=AN$22,MONTH($D83),"") | AO83: =+IF($AG83=AO$22,MONTH($D83),"") | AP83: =+IF($AG83=AP$22,MONTH($D83),"") | AQ83: =+IF($AG83=AQ$22,MONTH($D83),"") | AR83: =+IF($AG83=AR$22,MONTH($D83),"") | AS83: =+IF($AG83=AS$22,MONTH($D83),"") | AT83: =+IF($AG83=AT$22,MONTH($D83),"") | AU83: =+IF($AG83=AU$22,MONTH($D83),"") | ... AX83: =+IF($AG83=AX$22,MONTH($D83),"")
A84: =+IFERROR(VALUE(MID(AB84,4,4)),"") -> 390 | B84: =VALUE(RIGHT(C84,LEN(C84)-2)) -> 2638 | C84: O-2638 | D84: 45910 | E84: BHP | F84: Spence | H84: stephan.matulic@bhp.com | I84: Entregables Adicionales al Servicio de Ingeniería para Descarga Auxiliar Celda N°8 y Descarga Bypass MSO - SH-0390 - PDN70 | K84: ID | L84: ND | M84: NAC | N84: #VALUE! | O84: 45915 | P84: Pedro Valencia | Q84: TA | R84: RELAVES | T84: PG | V84: 45950 | W84: 656 | X84: 25.059 | Y84: =IF(SUM(W84:W84)>0,X84/SUM(W84:W84)*1000000,"N/A") -> 38199.695 | AB84: SH-0390 PDN70 | AG84: =YEAR(D84) -> 2025 | AH84: =+IF(AG84=$AH$22,MONTH(V84),"") | AI84: =+IF(AG84=$AI$22,MONTH(V84),"") -> 10 | AJ84: =+IF(AG84=$AJ$22,MONTH(V84),"") | AK84: =+IF(AG84=$AK$22,MONTH(V84),"") | AL84: =+IF(AG84=$AL$22,MONTH(V84),"") | AM84: =+IF($AG84=$AM$22,MONTH($D84),"") | AN84: =+IF($AG84=AN$22,MONTH($D84),"") | AO84: =+IF($AG84=AO$22,MONTH($D84),"") | AP84: =+IF($AG84=AP$22,MONTH($D84),"") | AQ84: =+IF($AG84=AQ$22,MONTH($D84),"") | AR84: =+IF($AG84=AR$22,MONTH($D84),"") | AS84: =+IF($AG84=AS$22,MONTH($D84),"") | AT84: =+IF($AG84=AT$22,MONTH($D84),"") | AU84: =+IF($AG84=AU$22,MONTH($D84),"") | ... AX84: =+IF($AG84=AX$22,MONTH($D84),"")
A85: =+IFERROR(VALUE(MID(AB85,4,4)),"") -> 390 | B85: =VALUE(RIGHT(C85,LEN(C85)-2)) -> 2637 | C85: O-2637 | D85: 45905 | E85: BHP | F85: Spence | H85: stephan.matulic@bhp.com | I85: Extensión de Plazo para Administración y Control de Proyecto - SH-0390 - PDN68 | K85: ID | L85: ND | M85: NAC | N85: #VALUE! | O85: 45910 | P85: Pedro Valencia | Q85: TA | R85: RELAVES | T85: PG | V85: 45915 | W85: 1121 | X85: 51.065 | Y85: =IF(SUM(W85:W85)>0,X85/SUM(W85:W85)*1000000,"N/A") -> 45553.078 | AB85: SH-0390 PDN68 | AG85: =YEAR(D85) -> 2025 | AH85: =+IF(AG85=$AH$22,MONTH(V85),"") | AI85: =+IF(AG85=$AI$22,MONTH(V85),"") -> 9 | AJ85: =+IF(AG85=$AJ$22,MONTH(V85),"") | AK85: =+IF(AG85=$AK$22,MONTH(V85),"") | AL85: =+IF(AG85=$AL$22,MONTH(V85),"") | AM85: =+IF($AG85=$AM$22,MONTH($D85),"") | AN85: =+IF($AG85=AN$22,MONTH($D85),"") | AO85: =+IF($AG85=AO$22,MONTH($D85),"") | AP85: =+IF($AG85=AP$22,MONTH($D85),"") | AQ85: =+IF($AG85=AQ$22,MONTH($D85),"") | AR85: =+IF($AG85=AR$22,MONTH($D85),"") | AS85: =+IF($AG85=AS$22,MONTH($D85),"") | AT85: =+IF($AG85=AT$22,MONTH($D85),"") | AU85: =+IF($AG85=AU$22,MONTH($D85),"") | ... AX85: =+IF($AG85=AX$22,MONTH($D85),"")
A86: =+IFERROR(VALUE(MID(AB86,4,4)),"") -> 390 | B86: =VALUE(RIGHT(C86,LEN(C86)-2)) -> 2636 | C86: O-2636 | D86: 45935 | E86: BHP | F86: Spence | H86: stephan.matulic@bhp.com | I86: Desarrollo de Ingeniería de Resultados Trade off Piscina Espesadores - SH-0390 - PDN66 | K86: ID | L86: ND | M86: NAC | N86: #VALUE! | O86: 45971 | P86: Pedro Valencia | Q86: TA | R86: RELAVES | T86: PG | V86: 45976 | W86: 8927 | X86: 354.17 | Y86: =IF(SUM(W86:W86)>0,X86/SUM(W86:W86)*1000000,"N/A") -> 39674.023 | AB86: SH-0390 PDN66 | AG86: =YEAR(D86) -> 2025 | AH86: =+IF(AG86=$AH$22,MONTH(V86),"") | AI86: =+IF(AG86=$AI$22,MONTH(V86),"") -> 11 | AJ86: =+IF(AG86=$AJ$22,MONTH(V86),"") | AK86: =+IF(AG86=$AK$22,MONTH(V86),"") | AL86: =+IF(AG86=$AL$22,MONTH(V86),"") | AM86: =+IF($AG86=$AM$22,MONTH($D86),"") | AN86: =+IF($AG86=AN$22,MONTH($D86),"") | AO86: =+IF($AG86=AO$22,MONTH($D86),"") | AP86: =+IF($AG86=AP$22,MONTH($D86),"") | AQ86: =+IF($AG86=AQ$22,MONTH($D86),"") | AR86: =+IF($AG86=AR$22,MONTH($D86),"") | AS86: =+IF($AG86=AS$22,MONTH($D86),"") | AT86: =+IF($AG86=AT$22,MONTH($D86),"") | AU86: =+IF($AG86=AU$22,MONTH($D86),"") | ... AX86: =+IF($AG86=AX$22,MONTH($D86),"")
A87: =+IFERROR(VALUE(MID(AB87,4,4)),"") -> 390 | B87: =VALUE(RIGHT(C87,LEN(C87)-2)) -> 2635 | C87: O-2635 | D87: 45874 | E87: BHP | F87: Spence | H87: stephan.matulic@bhp.com | I87: Extensión de Zanja de Relaves Existente - Solución de Interferencia con Caminos Proyectados - SH-0390 - PDN63 | K87: ID | L87: ND | M87: NAC | N87: #VALUE! | O87: 45884 | P87: Pedro Valencia | Q87: TA | R87: RELAVES | T87: PG | V87: 45915 | W87: 198 | X87: 6.24 | Y87: =IF(SUM(W87:W87)>0,X87/SUM(W87:W87)*1000000,"N/A") -> 31515.152 | AB87: SH-0390 PDN63 | AG87: =YEAR(D87) -> 2025 | AH87: =+IF(AG87=$AH$22,MONTH(V87),"") | AI87: =+IF(AG87=$AI$22,MONTH(V87),"") -> 9 | AJ87: =+IF(AG87=$AJ$22,MONTH(V87),"") | AK87: =+IF(AG87=$AK$22,MONTH(V87),"") | AL87: =+IF(AG87=$AL$22,MONTH(V87),"") | AM87: =+IF($AG87=$AM$22,MONTH($D87),"") | AN87: =+IF($AG87=AN$22,MONTH($D87),"") | AO87: =+IF($AG87=AO$22,MONTH($D87),"") | AP87: =+IF($AG87=AP$22,MONTH($D87),"") | AQ87: =+IF($AG87=AQ$22,MONTH($D87),"") | AR87: =+IF($AG87=AR$22,MONTH($D87),"") | AS87: =+IF($AG87=AS$22,MONTH($D87),"") | AT87: =+IF($AG87=AT$22,MONTH($D87),"") | AU87: =+IF($AG87=AU$22,MONTH($D87),"") | ... AX87: =+IF($AG87=AX$22,MONTH($D87),"")
A88: =+IFERROR(VALUE(MID(AB88,4,4)),"") -> 390 | B88: =VALUE(RIGHT(C88,LEN(C88)-2)) -> 2634 | C88: O-2634 | D88: 45935 | E88: BHP | F88: Spence | H88: stephan.matulic@bhp.com | I88: Presentación Técnica Equipo de Ejecución - SH-0390 - PDN61 | K88: ID | L88: ND | M88: NAC | N88: #VALUE! | O88: 45945 | P88: Pedro Valencia | Q88: TA | R88: RELAVES | T88: PG | V88: 45950 | W88: 80 | X88: 3.563 | Y88: =IF(SUM(W88:W88)>0,X88/SUM(W88:W88)*1000000,"N/A") -> 44537.5 | AB88: SH-0390 PDN61 | AG88: =YEAR(D88) -> 2025 | AH88: =+IF(AG88=$AH$22,MONTH(V88),"") | AI88: =+IF(AG88=$AI$22,MONTH(V88),"") -> 10 | AJ88: =+IF(AG88=$AJ$22,MONTH(V88),"") | AK88: =+IF(AG88=$AK$22,MONTH(V88),"") | AL88: =+IF(AG88=$AL$22,MONTH(V88),"") | AM88: =+IF($AG88=$AM$22,MONTH($D88),"") | AN88: =+IF($AG88=AN$22,MONTH($D88),"") | AO88: =+IF($AG88=AO$22,MONTH($D88),"") | AP88: =+IF($AG88=AP$22,MONTH($D88),"") | AQ88: =+IF($AG88=AQ$22,MONTH($D88),"") | AR88: =+IF($AG88=AR$22,MONTH($D88),"") | AS88: =+IF($AG88=AS$22,MONTH($D88),"") | AT88: =+IF($AG88=AT$22,MONTH($D88),"") | AU88: =+IF($AG88=AU$22,MONTH($D88),"") | ... AX88: =+IF($AG88=AX$22,MONTH($D88),"")
A89: =+IFERROR(VALUE(MID(AB89,4,4)),"") -> 390 | B89: =VALUE(RIGHT(C89,LEN(C89)-2)) -> 2633 | C89: O-2633 | D89: 45935 | E89: BHP | F89: Spence | H89: stephan.matulic@bhp.com | I89: Visita a Terreno Licitación Contratistas Electromecanico (Viaje Orlando Peralta) - SH-0390 - PDN58 | K89: ID | L89: ND | M89: NAC | N89: #VALUE! | O89: 45945 | P89: Pedro Valencia | Q89: TA | R89: RELAVES | T89: PG | V89: 45950 | W89: 12 | X89: 0.565 | Y89: =IF(SUM(W89:W89)>0,X89/SUM(W89:W89)*1000000,"N/A") -> 47083.333 | AB89: SH-0390 PDN58 | AG89: =YEAR(D89) -> 2025 | AH89: =+IF(AG89=$AH$22,MONTH(V89),"") | AI89: =+IF(AG89=$AI$22,MONTH(V89),"") -> 10 | AJ89: =+IF(AG89=$AJ$22,MONTH(V89),"") | AK89: =+IF(AG89=$AK$22,MONTH(V89),"") | AL89: =+IF(AG89=$AL$22,MONTH(V89),"") | AM89: =+IF($AG89=$AM$22,MONTH($D89),"") | AN89: =+IF($AG89=AN$22,MONTH($D89),"") | AO89: =+IF($AG89=AO$22,MONTH($D89),"") | AP89: =+IF($AG89=AP$22,MONTH($D89),"") | AQ89: =+IF($AG89=AQ$22,MONTH($D89),"") | AR89: =+IF($AG89=AR$22,MONTH($D89),"") | AS89: =+IF($AG89=AS$22,MONTH($D89),"") | AT89: =+IF($AG89=AT$22,MONTH($D89),"") | AU89: =+IF($AG89=AU$22,MONTH($D89),"") | ... AX89: =+IF($AG89=AX$22,MONTH($D89),"")
A90: =+IFERROR(VALUE(MID(AB90,4,4)),"") -> 390 | B90: =VALUE(RIGHT(C90,LEN(C90)-2)) -> 2632 | C90: O-2632 | D90: 45905 | E90: BHP | F90: Spence | H90: stephan.matulic@bhp.com | I90: Descarga Provisoria a Celda N°8 (actualización) - SH-0390 - PDN57 | K90: ID | L90: ND | M90: NAC | N90: #VALUE! | O90: 45915 | P90: Pedro Valencia | Q90: TA | R90: RELAVES | T90: PG | V90: 45920 | W90: 954 | X90: 34.819 | Y90: =IF(SUM(W90:W90)>0,X90/SUM(W90:W90)*1000000,"N/A") -> 36497.904 | AB90: SH-0390 PDN57 | AG90: =YEAR(D90) -> 2025 | AH90: =+IF(AG90=$AH$22,MONTH(V90),"") | AI90: =+IF(AG90=$AI$22,MONTH(V90),"") -> 9 | AJ90: =+IF(AG90=$AJ$22,MONTH(V90),"") | AK90: =+IF(AG90=$AK$22,MONTH(V90),"") | AL90: =+IF(AG90=$AL$22,MONTH(V90),"") | AM90: =+IF($AG90=$AM$22,MONTH($D90),"") | AN90: =+IF($AG90=AN$22,MONTH($D90),"") | AO90: =+IF($AG90=AO$22,MONTH($D90),"") | AP90: =+IF($AG90=AP$22,MONTH($D90),"") | AQ90: =+IF($AG90=AQ$22,MONTH($D90),"") | AR90: =+IF($AG90=AR$22,MONTH($D90),"") | AS90: =+IF($AG90=AS$22,MONTH($D90),"") | AT90: =+IF($AG90=AT$22,MONTH($D90),"") | AU90: =+IF($AG90=AU$22,MONTH($D90),"") | ... AX90: =+IF($AG90=AX$22,MONTH($D90),"")
A91: =+IFERROR(VALUE(MID(AB91,4,4)),"") -> 390 | B91: =VALUE(RIGHT(C91,LEN(C91)-2)) -> 2631 | C91: O-2631 | D91: 45935 | E91: BHP | F91: Spence | H91: stephan.matulic@bhp.com | I91: Análisis de Alternativas para Piscinas de Espesadores y Solicitudes de Operaciones - SH-0390 - PDN56 | K91: ID | L91: ND | M91: NAC | N91: #VALUE! | O91: 45945 | P91: Pedro Valencia | Q91: TA | R91: RELAVES | T91: PG | V91: 45950 | W91: 344 | X91: 14.166 | Y91: =IF(SUM(W91:W91)>0,X91/SUM(W91:W91)*1000000,"N/A") -> 41180.233 | AB91: SH-0390 PDN56 | AG91: =YEAR(D91) -> 2025 | AH91: =+IF(AG91=$AH$22,MONTH(V91),"") | AI91: =+IF(AG91=$AI$22,MONTH(V91),"") -> 10 | AJ91: =+IF(AG91=$AJ$22,MONTH(V91),"") | AK91: =+IF(AG91=$AK$22,MONTH(V91),"") | AL91: =+IF(AG91=$AL$22,MONTH(V91),"") | AM91: =+IF($AG91=$AM$22,MONTH($D91),"") | AN91: =+IF($AG91=AN$22,MONTH($D91),"") | AO91: =+IF($AG91=AO$22,MONTH($D91),"") | AP91: =+IF($AG91=AP$22,MONTH($D91),"") | AQ91: =+IF($AG91=AQ$22,MONTH($D91),"") | AR91: =+IF($AG91=AR$22,MONTH($D91),"") | AS91: =+IF($AG91=AS$22,MONTH($D91),"") | AT91: =+IF($AG91=AT$22,MONTH($D91),"") | AU91: =+IF($AG91=AU$22,MONTH($D91),"") | ... AX91: =+IF($AG91=AX$22,MONTH($D91),"")
A92: =+IFERROR(VALUE(MID(AB92,4,4)),"") -> 390 | B92: =VALUE(RIGHT(C92,LEN(C92)-2)) -> 2630 | C92: O-2630 | D92: 45905 | E92: BHP | F92: Spence | H92: stephan.matulic@bhp.com | I92: Gastos Generales y Utilidades - SH-0390 - PDN55 | K92: ID | L92: ND | M92: NAC | N92: #VALUE! | O92: 45915 | P92: Pedro Valencia | Q92: TA | R92: RELAVES | T92: PG | V92: 45920 | X92: 292.136 | Y92: =IF(SUM(W92:W92)>0,X92/SUM(W92:W92)*1000000,"N/A") -> N/A | AB92: SH-0390 PDN55 | AG92: =YEAR(D92) -> 2025 | AH92: =+IF(AG92=$AH$22,MONTH(V92),"") | AI92: =+IF(AG92=$AI$22,MONTH(V92),"") -> 9 | AJ92: =+IF(AG92=$AJ$22,MONTH(V92),"") | AK92: =+IF(AG92=$AK$22,MONTH(V92),"") | AL92: =+IF(AG92=$AL$22,MONTH(V92),"") | AM92: =+IF($AG92=$AM$22,MONTH($D92),"") | AN92: =+IF($AG92=AN$22,MONTH($D92),"") | AO92: =+IF($AG92=AO$22,MONTH($D92),"") | AP92: =+IF($AG92=AP$22,MONTH($D92),"") | AQ92: =+IF($AG92=AQ$22,MONTH($D92),"") | AR92: =+IF($AG92=AR$22,MONTH($D92),"") | AS92: =+IF($AG92=AS$22,MONTH($D92),"") | AT92: =+IF($AG92=AT$22,MONTH($D92),"") | AU92: =+IF($AG92=AU$22,MONTH($D92),"") | ... AX92: =+IF($AG92=AX$22,MONTH($D92),"")
A93: =+IFERROR(VALUE(MID(AB93,4,4)),"") -> 390 | B93: =VALUE(RIGHT(C93,LEN(C93)-2)) -> 2629 | C93: O-2629 | D93: 45843 | E93: BHP | F93: Spence | H93: stephan.matulic@bhp.com | I93: Incorporación VDF ABB a SE de PRECISION - SH-0390 - PDN54 | K93: ID | L93: ND | M93: NAC | N93: #VALUE! | O93: 45853 | P93: Pedro Valencia | Q93: TA | R93: RELAVES | T93: PG | V93: 45858 | W93: 150 | X93: 6.63 | Y93: =IF(SUM(W93:W93)>0,X93/SUM(W93:W93)*1000000,"N/A") -> 44200 | AB93: SH-0390 PDN54 | AG93: =YEAR(D93) -> 2025 | AH93: =+IF(AG93=$AH$22,MONTH(V93),"") | AI93: =+IF(AG93=$AI$22,MONTH(V93),"") -> 7 | AJ93: =+IF(AG93=$AJ$22,MONTH(V93),"") | AK93: =+IF(AG93=$AK$22,MONTH(V93),"") | AL93: =+IF(AG93=$AL$22,MONTH(V93),"") | AM93: =+IF($AG93=$AM$22,MONTH($D93),"") | AN93: =+IF($AG93=AN$22,MONTH($D93),"") | AO93: =+IF($AG93=AO$22,MONTH($D93),"") | AP93: =+IF($AG93=AP$22,MONTH($D93),"") | AQ93: =+IF($AG93=AQ$22,MONTH($D93),"") | AR93: =+IF($AG93=AR$22,MONTH($D93),"") | AS93: =+IF($AG93=AS$22,MONTH($D93),"") | AT93: =+IF($AG93=AT$22,MONTH($D93),"") | AU93: =+IF($AG93=AU$22,MONTH($D93),"") | ... AX93: =+IF($AG93=AX$22,MONTH($D93),"")
A94: =+IFERROR(VALUE(MID(AB94,4,4)),"") -> 390 | B94: =VALUE(RIGHT(C94,LEN(C94)-2)) -> 2628 | C94: O-2628 | D94: 45874 | E94: BHP | F94: Spence | H94: stephan.matulic@bhp.com | I94: Listado de Entregables INTERIM Integrado - SH-0390 - PDN52 | K94: ID | L94: ND | M94: NAC | N94: #VALUE! | O94: 45884 | P94: Pedro Valencia | Q94: TA | R94: RELAVES | T94: PG | V94: 45889 | W94: 37 | X94: 1.068 | Y94: =IF(SUM(W94:W94)>0,X94/SUM(W94:W94)*1000000,"N/A") -> 28864.865 | AB94: SH-0390 PDN52 | AG94: =YEAR(D94) -> 2025 | AH94: =+IF(AG94=$AH$22,MONTH(V94),"") | AI94: =+IF(AG94=$AI$22,MONTH(V94),"") -> 8 | AJ94: =+IF(AG94=$AJ$22,MONTH(V94),"") | AK94: =+IF(AG94=$AK$22,MONTH(V94),"") | AL94: =+IF(AG94=$AL$22,MONTH(V94),"") | AM94: =+IF($AG94=$AM$22,MONTH($D94),"") | AN94: =+IF($AG94=AN$22,MONTH($D94),"") | AO94: =+IF($AG94=AO$22,MONTH($D94),"") | AP94: =+IF($AG94=AP$22,MONTH($D94),"") | AQ94: =+IF($AG94=AQ$22,MONTH($D94),"") | AR94: =+IF($AG94=AR$22,MONTH($D94),"") | AS94: =+IF($AG94=AS$22,MONTH($D94),"") | AT94: =+IF($AG94=AT$22,MONTH($D94),"") | AU94: =+IF($AG94=AU$22,MONTH($D94),"") | ... AX94: =+IF($AG94=AX$22,MONTH($D94),"")
A95: =+IFERROR(VALUE(MID(AB95,4,4)),"") -> 390 | B95: =VALUE(RIGHT(C95,LEN(C95)-2)) -> 2627 | C95: O-2627 | D95: 45966 | E95: BHP | F95: Spence | H95: stephan.matulic@bhp.com | I95: Actividades Adicionales Simulación de Estimación de Movimiento de Tierra y Hormigones y Paquete de Compra CAPEX - SH-0390 - PDN51 | K95: ID | L95: ND | M95: NAC | N95: #VALUE! | O95: 45976 | P95: Pedro Valencia | Q95: TA | R95: RELAVES | T95: PG | V95: 45981 | W95: 80 | X95: 3.562 | Y95: =IF(SUM(W95:W95)>0,X95/SUM(W95:W95)*1000000,"N/A") -> 44525 | AB95: SH-0390 PDN51 | AG95: =YEAR(D95) -> 2025 | AH95: =+IF(AG95=$AH$22,MONTH(V95),"") | AI95: =+IF(AG95=$AI$22,MONTH(V95),"") -> 11 | AJ95: =+IF(AG95=$AJ$22,MONTH(V95),"") | AK95: =+IF(AG95=$AK$22,MONTH(V95),"") | AL95: =+IF(AG95=$AL$22,MONTH(V95),"") | AM95: =+IF($AG95=$AM$22,MONTH($D95),"") | AN95: =+IF($AG95=AN$22,MONTH($D95),"") | AO95: =+IF($AG95=AO$22,MONTH($D95),"") | AP95: =+IF($AG95=AP$22,MONTH($D95),"") | AQ95: =+IF($AG95=AQ$22,MONTH($D95),"") | AR95: =+IF($AG95=AR$22,MONTH($D95),"") | AS95: =+IF($AG95=AS$22,MONTH($D95),"") | AT95: =+IF($AG95=AT$22,MONTH($D95),"") | AU95: =+IF($AG95=AU$22,MONTH($D95),"") | ... AX95: =+IF($AG95=AX$22,MONTH($D95),"")
A96: =+IFERROR(VALUE(MID(AB96,4,4)),"") -> 390 | B96: =VALUE(RIGHT(C96,LEN(C96)-2)) -> 2626 | C96: O-2626 | D96: 45874 | E96: BHP | F96: Spence | H96: stephan.matulic@bhp.com | I96: Eliminación Alcance Ingeniería INTERIM (Apoyo IPR) - SH-0390 - PDN49 | K96: ID | L96: ND | M96: NAC | N96: #VALUE! | O96: 45884 | P96: Pedro Valencia | Q96: TA | R96: RELAVES | T96: PG | V96: 45889 | W96: -641 | X96: =-27.284 -> -27.284 | Y96: =IF(SUM(W96:W96)>0,X96/SUM(W96:W96)*1000000,"N/A") -> N/A | AB96: SH-0390 PDN49 | AG96: =YEAR(D96) -> 2025 | AH96: =+IF(AG96=$AH$22,MONTH(V96),"") | AI96: =+IF(AG96=$AI$22,MONTH(V96),"") -> 8 | AJ96: =+IF(AG96=$AJ$22,MONTH(V96),"") | AK96: =+IF(AG96=$AK$22,MONTH(V96),"") | AL96: =+IF(AG96=$AL$22,MONTH(V96),"") | AM96: =+IF($AG96=$AM$22,MONTH($D96),"") | AN96: =+IF($AG96=AN$22,MONTH($D96),"") | AO96: =+IF($AG96=AO$22,MONTH($D96),"") | AP96: =+IF($AG96=AP$22,MONTH($D96),"") | AQ96: =+IF($AG96=AQ$22,MONTH($D96),"") | AR96: =+IF($AG96=AR$22,MONTH($D96),"") | AS96: =+IF($AG96=AS$22,MONTH($D96),"") | AT96: =+IF($AG96=AT$22,MONTH($D96),"") | AU96: =+IF($AG96=AU$22,MONTH($D96),"") | ... AX96: =+IF($AG96=AX$22,MONTH($D96),"")
A97: =+IFERROR(VALUE(MID(AB97,4,4)),"") -> 390 | B97: =VALUE(RIGHT(C97,LEN(C97)-2)) -> 2625 | C97: O-2625 | D97: 45843 | E97: BHP | F97: Spence | H97: stephan.matulic@bhp.com | I97: Pruebas FAT, SAT Suministros en Proceso de Activación - SH-0390 - PDN48 | K97: ID | L97: ND | M97: NAC | N97: #VALUE! | O97: 45853 | P97: Pedro Valencia | Q97: TA | R97: RELAVES | T97: PG | V97: 45858 | W97: 87 | X97: 4.094 | Y97: =IF(SUM(W97:W97)>0,X97/SUM(W97:W97)*1000000,"N/A") -> 47057.471 | AB97: SH-0390 PDN48 | AG97: =YEAR(D97) -> 2025 | AH97: =+IF(AG97=$AH$22,MONTH(V97),"") | AI97: =+IF(AG97=$AI$22,MONTH(V97),"") -> 7 | AJ97: =+IF(AG97=$AJ$22,MONTH(V97),"") | AK97: =+IF(AG97=$AK$22,MONTH(V97),"") | AL97: =+IF(AG97=$AL$22,MONTH(V97),"") | AM97: =+IF($AG97=$AM$22,MONTH($D97),"") | AN97: =+IF($AG97=AN$22,MONTH($D97),"") | AO97: =+IF($AG97=AO$22,MONTH($D97),"") | AP97: =+IF($AG97=AP$22,MONTH($D97),"") | AQ97: =+IF($AG97=AQ$22,MONTH($D97),"") | AR97: =+IF($AG97=AR$22,MONTH($D97),"") | AS97: =+IF($AG97=AS$22,MONTH($D97),"") | AT97: =+IF($AG97=AT$22,MONTH($D97),"") | AU97: =+IF($AG97=AU$22,MONTH($D97),"") | ... AX97: =+IF($AG97=AX$22,MONTH($D97),"")
A98: =+IFERROR(VALUE(MID(AB98,4,4)),"") -> 390 | B98: =VALUE(RIGHT(C98,LEN(C98)-2)) -> 2624 | C98: O-2624 | D98: 45874 | E98: BHP | F98: Spence | H98: stephan.matulic@bhp.com | I98: Trazabilidad PDN 23 y PDN 39 - SH-0390 - PDN47 | K98: ID | L98: ND | M98: NAC | N98: #VALUE! | O98: 45884 | P98: Pedro Valencia | Q98: TA | R98: RELAVES | T98: PG | V98: 45885 | W98: -27 | X98: -0.669 | Y98: =IF(SUM(W98:W98)>0,X98/SUM(W98:W98)*1000000,"N/A") -> N/A | AB98: SH-0390 PDN47 | AG98: =YEAR(D98) -> 2025 | AH98: =+IF(AG98=$AH$22,MONTH(V98),"") | AI98: =+IF(AG98=$AI$22,MONTH(V98),"") -> 8 | AJ98: =+IF(AG98=$AJ$22,MONTH(V98),"") | AK98: =+IF(AG98=$AK$22,MONTH(V98),"") | AL98: =+IF(AG98=$AL$22,MONTH(V98),"") | AM98: =+IF($AG98=$AM$22,MONTH($D98),"") | AN98: =+IF($AG98=AN$22,MONTH($D98),"") | AO98: =+IF($AG98=AO$22,MONTH($D98),"") | AP98: =+IF($AG98=AP$22,MONTH($D98),"") | AQ98: =+IF($AG98=AQ$22,MONTH($D98),"") | AR98: =+IF($AG98=AR$22,MONTH($D98),"") | AS98: =+IF($AG98=AS$22,MONTH($D98),"") | AT98: =+IF($AG98=AT$22,MONTH($D98),"") | AU98: =+IF($AG98=AU$22,MONTH($D98),"") | ... AX98: =+IF($AG98=AX$22,MONTH($D98),"")
A99: =+IFERROR(VALUE(MID(AB99,4,4)),"") -> 390 | B99: =VALUE(RIGHT(C99,LEN(C99)-2)) -> 2623 | C99: O-2623 | D99: 45935 | E99: BHP | F99: Spence | H99: stephan.matulic@bhp.com | I99: Nota Técnica - Aceleración de Programa Etapa 1 - SH-0390 - PDN45 | K99: ID | L99: ND | M99: NAC | N99: #VALUE! | O99: 45945 | P99: Pedro Valencia | Q99: TA | R99: RELAVES | T99: PG | V99: 45946 | W99: 100 | X99: 4.494 | Y99: =IF(SUM(W99:W99)>0,X99/SUM(W99:W99)*1000000,"N/A") -> 44940 | AB99: SH-0390 PDN45 | AG99: =YEAR(D99) -> 2025 | AH99: =+IF(AG99=$AH$22,MONTH(V99),"") | AI99: =+IF(AG99=$AI$22,MONTH(V99),"") -> 10 | AJ99: =+IF(AG99=$AJ$22,MONTH(V99),"") | AK99: =+IF(AG99=$AK$22,MONTH(V99),"") | AL99: =+IF(AG99=$AL$22,MONTH(V99),"") | AM99: =+IF($AG99=$AM$22,MONTH($D99),"") | AN99: =+IF($AG99=AN$22,MONTH($D99),"") | AO99: =+IF($AG99=AO$22,MONTH($D99),"") | AP99: =+IF($AG99=AP$22,MONTH($D99),"") | AQ99: =+IF($AG99=AQ$22,MONTH($D99),"") | AR99: =+IF($AG99=AR$22,MONTH($D99),"") | AS99: =+IF($AG99=AS$22,MONTH($D99),"") | AT99: =+IF($AG99=AT$22,MONTH($D99),"") | AU99: =+IF($AG99=AU$22,MONTH($D99),"") | ... AX99: =+IF($AG99=AX$22,MONTH($D99),"")
A100: =+IFERROR(VALUE(MID(AB100,4,4)),"") -> 390 | B100: =VALUE(RIGHT(C100,LEN(C100)-2)) -> 2622 | C100: O-2622 | D100: 45782 | E100: BHP | F100: Spence | H100: stephan.matulic@bhp.com | I100: Actualización de Caracterización Reológica con Nuevos Datos Operacionales - SH-0390 - PDN43 | K100: ID | L100: ND | M100: NAC | N100: #VALUE! | O100: 45823 | P100: Pedro Valencia | Q100: TA | R100: RELAVES | T100: PG | V100: 45824 | W100: 145 | X100: 6.141 | Y100: =IF(SUM(W100:W100)>0,X100/SUM(W100:W100)*1000000,"N/A") -> 42351.724 | AB100: SH-0390 PDN43 | AG100: =YEAR(D100) -> 2025 | AH100: =+IF(AG100=$AH$22,MONTH(V100),"") | AI100: =+IF(AG100=$AI$22,MONTH(V100),"") -> 6 | AJ100: =+IF(AG100=$AJ$22,MONTH(V100),"") | AK100: =+IF(AG100=$AK$22,MONTH(V100),"") | AL100: =+IF(AG100=$AL$22,MONTH(V100),"") | AM100: =+IF($AG100=$AM$22,MONTH($D100),"") | AN100: =+IF($AG100=AN$22,MONTH($D100),"") | AO100: =+IF($AG100=AO$22,MONTH($D100),"") | AP100: =+IF($AG100=AP$22,MONTH($D100),"") | AQ100: =+IF($AG100=AQ$22,MONTH($D100),"") | AR100: =+IF($AG100=AR$22,MONTH($D100),"") | AS100: =+IF($AG100=AS$22,MONTH($D100),"") | AT100: =+IF($AG100=AT$22,MONTH($D100),"") | AU100: =+IF($AG100=AU$22,MONTH($D100),"") | ... AX100: =+IF($AG100=AX$22,MONTH($D100),"")
A101: =+IFERROR(VALUE(MID(AB101,4,4)),"") -> 390 | B101: =VALUE(RIGHT(C101,LEN(C101)-2)) -> 2621 | C101: O-2621 | D101: 45782 | E101: BHP | F101: Spence | H101: stephan.matulic@bhp.com | I101: Verificación Hidráulica - Impulsión de Relaves hacia Celda 11 (enero 2026) - SH-0390 - PDN42 | K101: ID | L101: ND | M101: NAC | N101: #VALUE! | O101: 45823 | P101: Pedro Valencia | Q101: TA | R101: RELAVES | T101: PG | V101: 45824 | W101: 789 | X101: 28.866 | Y101: =IF(SUM(W101:W101)>0,X101/SUM(W101:W101)*1000000,"N/A") -> 36585.551 | AB101: SH-0390 PDN42 | AG101: =YEAR(D101) -> 2025 | AH101: =+IF(AG101=$AH$22,MONTH(V101),"") | AI101: =+IF(AG101=$AI$22,MONTH(V101),"") -> 6 | AJ101: =+IF(AG101=$AJ$22,MONTH(V101),"") | AK101: =+IF(AG101=$AK$22,MONTH(V101),"") | AL101: =+IF(AG101=$AL$22,MONTH(V101),"") | AM101: =+IF($AG101=$AM$22,MONTH($D101),"") | AN101: =+IF($AG101=AN$22,MONTH($D101),"") | AO101: =+IF($AG101=AO$22,MONTH($D101),"") | AP101: =+IF($AG101=AP$22,MONTH($D101),"") | AQ101: =+IF($AG101=AQ$22,MONTH($D101),"") | AR101: =+IF($AG101=AR$22,MONTH($D101),"") | AS101: =+IF($AG101=AS$22,MONTH($D101),"") | AT101: =+IF($AG101=AT$22,MONTH($D101),"") | AU101: =+IF($AG101=AU$22,MONTH($D101),"") | ... AX101: =+IF($AG101=AX$22,MONTH($D101),"")
A102: =+IFERROR(VALUE(MID(AB102,4,4)),"") -> 390 | B102: =VALUE(RIGHT(C102,LEN(C102)-2)) -> 2620 | C102: O-2620 | D102: 45752 | E102: BHP | F102: Spence | H102: stephan.matulic@bhp.com | I102: Incorporación Conexión de Línea Sur de Relaves en la Estación Booster - SH-0390 - PDN41 | K102: ID | L102: ND | M102: NAC | N102: #VALUE! | O102: 45757 | P102: Pedro Valencia | Q102: TA | R102: RELAVES | T102: PG | V102: 45792 | W102: 1404 | X102: 53.868 | Y102: =IF(SUM(W102:W102)>0,X102/SUM(W102:W102)*1000000,"N/A") -> 38367.521 | AB102: SH-0390 PDN41 | AG102: =YEAR(D102) -> 2025 | AH102: =+IF(AG102=$AH$22,MONTH(V102),"") | AI102: =+IF(AG102=$AI$22,MONTH(V102),"") -> 5 | AJ102: =+IF(AG102=$AJ$22,MONTH(V102),"") | AK102: =+IF(AG102=$AK$22,MONTH(V102),"") | AL102: =+IF(AG102=$AL$22,MONTH(V102),"") | AM102: =+IF($AG102=$AM$22,MONTH($D102),"") | AN102: =+IF($AG102=AN$22,MONTH($D102),"") | AO102: =+IF($AG102=AO$22,MONTH($D102),"") | AP102: =+IF($AG102=AP$22,MONTH($D102),"") | AQ102: =+IF($AG102=AQ$22,MONTH($D102),"") | AR102: =+IF($AG102=AR$22,MONTH($D102),"") | AS102: =+IF($AG102=AS$22,MONTH($D102),"") | AT102: =+IF($AG102=AT$22,MONTH($D102),"") | AU102: =+IF($AG102=AU$22,MONTH($D102),"") | ... AX102: =+IF($AG102=AX$22,MONTH($D102),"")
...

Sheet Sheet1
A1: Razones de no adjudicación
A2: Costo
A3: Alcance
A4: Metodología
A5: Trabajo previo ejecutado por competidor adjudicado
A6: Otras

Sheet Hoja1
A22: Modulo | B22: Letra | C22: Descripcion | D22: Años de Experiencia
A23: Módulo A | B23: A | C23: Ingeniería estructural
A24: Módulo B | B24: B | C24: Ingeniería de Mantenimiento y Confiabilidad | D24: > = 8 Años
A25: Módulo C | B25: C | C25: Hidráulica, manejo de pulpas y Análisis CFD | D25: > = 5 Años
A26: Módulo D | B26: D | C26: Mecánica aplicada y Análisis FEA | D26: > = 5 Años
A27: Módulo E | B27: E | C27: Diseño de sistemas de transporte y manejo de sólidos a granel y análisis DEM | D27: > = 5 Años
A28: Módulo F | B28: F | C28: Diseño de máquinas y soluciones de Mantenibilidad | D28: > = 8 Años
A29: Módulo G | B29: G | C29: Electricidad e Instrumentación | D29: > = 5 Años
A30: Módulo H | B30: H | C30: Reingeniería | D30: > = 5 Años

Sheet Hoja3
L1: T. Promedio
C2: 1883 | E2: 47.2484 | F2: 25092.087 | G2: SH-0158 OS14 | H2: 2018 | I2: =IFERROR(F2*(C2/SUMIF(H:H,H2,C:C)),0) -> 25092.087 | K2: 2010 | L2: =SUMIF(H:H,K2,I:I) -> 42212.266
C3: 441 | E3: 11.172 | F3: 25333.333 | G3: SH-0158 OS13 | H3: 2017 | I3: =IFERROR(F3*(C3/SUMIF(H:H,H3,C:C)),0) -> 280.06317 | K3: 2011 | L3: =SUMIF(H:H,K3,I:I) -> 29980.385 | M3: =(L3-L2)/L2 -> -0.28977079
C4: 1315 | E4: 32.3871 | F4: 24628.973 | G4: SH-0158 OS12 | H4: 2017 | I4: =IFERROR(F4*(C4/SUMIF(H:H,H4,C:C)),0) -> 811.8899 | K4: 2012 | L4: =SUMIF(H:H,K4,I:I) -> 32701.369 | M4: =(L4-L3)/L3 -> 0.090758829
C5: 37 | E5: 1.4418 | F5: 38967.568 | G5: SH-0158 OS11 | H5: 2017 | I5: =IFERROR(F5*(C5/SUMIF(H:H,H5,C:C)),0) -> 36.143491 | K5: 2013 | L5: =SUMIF(H:H,K5,I:I) -> 34915.704 | M5: =(L5-L4)/L4 -> 0.067713831
C6: 1065 | E6: 34.591489 | F6: 32480.271 | H6: 2017 | I6: =IFERROR(F6*(C6/SUMIF(H:H,H6,C:C)),0) -> 867.15021 | K6: 2014 | L6: =SUMIF(H:H,K6,I:I) -> 39753.104 | M6: =(L6-L5)/L5 -> 0.13854509
C7: 1144 | E7: 29.4768 | F7: 25766.434 | G7: SH-0158 OS10 | H7: 2017 | I7: =IFERROR(F7*(C7/SUMIF(H:H,H7,C:C)),0) -> 738.93359 | K7: 2015 | L7: =SUMIF(H:H,K7,I:I) -> 33822.964 | M7: =(L7-L6)/L6 -> -0.14917426
C8: 109 | E8: 2.560908 | F8: 23494.569 | G8: SH-0173 | H8: 2017 | I8: =IFERROR(F8*(C8/SUMIF(H:H,H8,C:C)),0) -> 64.197639 | K8: 2016 | L8: =SUMIF(H:H,K8,I:I) -> 31922.001 | M8: =(L8-L7)/L7 -> -0.056203316
C9: 800 | E9: 26.124748 | F9: 32655.935 | G9: SH-0174 | H9: 2017 | I9: =IFERROR(F9*(C9/SUMIF(H:H,H9,C:C)),0) -> 654.90331 | K9: 2017 | L9: =SUMIF(H:H,K9,I:I) -> 26889.388 | M9: =(L9-L8)/L8 -> -0.15765343 | N9: =(L9-L7)/L7 -> -0.2049961
C10: 240 | E10: 8.0864 | F10: 33693.333 | G10: SH0158-OS09 | H10: 2017 | I10: =IFERROR(F10*(C10/SUMIF(H:H,H10,C:C)),0) -> 202.71239 | K10: 2018 | L10: =SUMIF(H:H,K10,I:I) -> 25092.087 | M10: =(L10-L9)/L9 -> -0.066840534
C11: 80 | E11: 2.926 | F11: 36575 | G11: SH0171 | H11: 2017 | I11: =IFERROR(F11*(C11/SUMIF(H:H,H11,C:C)),0) -> 73.349878
C12: 232 | E12: 7.5012 | F12: 32332.759 | G12: SH0170 | H12: 2017 | I12: =IFERROR(F12*(C12/SUMIF(H:H,H12,C:C)),0) -> 188.04242
C13: 30 | E13: 0.7238 | F13: 24126.667 | H13: 2017 | I13: =IFERROR(F13*(C13/SUMIF(H:H,H13,C:C)),0) -> 18.144444
C14: 525 | E14: 12.635 | F14: 24066.667 | G14: SH0158-OS08 | H14: 2017 | I14: =IFERROR(F14*(C14/SUMIF(H:H,H14,C:C)),0) -> 316.73811
C15: 1240 | E15: 27.664 | F15: 22309.677 | G15: SH0158-OS07 | H15: 2017 | I15: =IFERROR(F15*(C15/SUMIF(H:H,H15,C:C)),0) -> 693.48976
C16: 942 | E16: 25.024125 | F16: 26564.889 | G16: SH0158-OS06 | H16: 2017 | I16: =IFERROR(F16*(C16/SUMIF(H:H,H16,C:C)),0) -> 627.31256
C17: 175 | E17: 3.818261 | F17: 21818.634 | G17: SH0169 | H17: 2017 | I17: =IFERROR(F17*(C17/SUMIF(H:H,H17,C:C)),0) -> 95.717355
C18: 2135 | E18: 59.995262 | F18: 28100.825 | G18: SH0172 | H18: 2017 | I18: =IFERROR(F18*(C18/SUMIF(H:H,H18,C:C)),0) -> 1503.9799
C19: 396 | E19: 10.66372 | F19: 26928.586 | G19: SH0158-OS05 | H19: 2017 | I19: =IFERROR(F19*(C19/SUMIF(H:H,H19,C:C)),0) -> 267.32145
C20: 1058 | E20: 27.8768 | F20: 26348.582 | G20: SH0158-OS04 | H20: 2017 | I20: =IFERROR(F20*(C20/SUMIF(H:H,H20,C:C)),0) -> 698.8243
C21: 37 | E21: 1.4364 | F21: 38821.622 | G21: SH-0158 OS02 | H21: 2017 | I21: =IFERROR(F21*(C21/SUMIF(H:H,H21,C:C)),0) -> 36.008122
C22: 100 | E22: 2.66 | F22: 26600 | G22: SH-0164 | H22: 2017 | I22: =IFERROR(F22*(C22/SUMIF(H:H,H22,C:C)),0) -> 66.681708
C23: 192 | E23: 3.4216245 | F23: 17820.961 | G23: SH-0157 | H23: 2017 | I23: =IFERROR(F23*(C23/SUMIF(H:H,H23,C:C)),0) -> 85.774348
G24: SH-0159 | H24: 2017 | I24: =IFERROR(F24*(C24/SUMIF(H:H,H24,C:C)),0) -> 0
C25: 200 | G25: SH-0165 | H25: 2017 | I25: =IFERROR(F25*(C25/SUMIF(H:H,H25,C:C)),0) -> 0
C26: 20 | E26: 1.24285 | F26: 62142.5 | G26: SH-0160 | H26: 2017 | I26: =IFERROR(F26*(C26/SUMIF(H:H,H26,C:C)),0) -> 31.156151
C27: 142 | E27: 3.8159357 | F27: 26872.787 | G27: SH-0158 OS03 | H27: 2017 | I27: =IFERROR(F27*(C27/SUMIF(H:H,H27,C:C)),0) -> 95.659063
C28: 739 | E28: 29.736774 | F28: 40239.207 | G28: SH-0162 | H28: 2017 | I28: =IFERROR(F28*(C28/SUMIF(H:H,H28,C:C)),0) -> 745.4507
C29: 3159 | E29: 121.70334 | F29: 38525.907 | G29: SH-0166 | H29: 2017 | I29: =IFERROR(F29*(C29/SUMIF(H:H,H29,C:C)),0) -> 3050.8972
C30: 4000 | E30: 39.08722 | F30: 9771.805 | G30: SH-0146 | H30: 2017 | I30: =IFERROR(F30*(C30/SUMIF(H:H,H30,C:C)),0) -> 979.85059
C31: 445 | E31: 11.827655 | F31: 26579 | H31: 2017 | I31: =IFERROR(F31*(C31/SUMIF(H:H,H31,C:C)),0) -> 296.49934
C32: 210 | E32: 7.40259 | F32: 35250.429 | G32: SH-0156 | H32: 2017 | I32: =IFERROR(F32*(C32/SUMIF(H:H,H32,C:C)),0) -> 185.57043
C33: 397 | E33: 5.245035 | F33: 13211.675 | G33: SH-0151 | H33: 2017 | I33: =IFERROR(F33*(C33/SUMIF(H:H,H33,C:C)),0) -> 131.48417
G34: SH-0168 | H34: 2017 | I34: =IFERROR(F34*(C34/SUMIF(H:H,H34,C:C)),0) -> 0
C35: 468 | E35: 11.52348 | F35: 24622.821 | G35: SH-0163 | H35: 2017 | I35: =IFERROR(F35*(C35/SUMIF(H:H,H35,C:C)),0) -> 288.87418
C36: 810 | E36: 24.13059 | F36: 29790.852 | H36: 2017 | I36: =IFERROR(F36*(C36/SUMIF(H:H,H36,C:C)),0) -> 604.91314
C37: 524 | E37: 19.0224 | F37: 36302.29 | G37: SH-0154 | H37: 2017 | I37: =IFERROR(F37*(C37/SUMIF(H:H,H37,C:C)),0) -> 476.85944
C38: 2922 | E38: 82.052222 | F38: 28080.843 | G38: SH-0161 | H38: 2017 | I38: =IFERROR(F38*(C38/SUMIF(H:H,H38,C:C)),0) -> 2056.9106
C39: 621 | E39: 20.019808 | F39: 32238.016 | G39: SH-0153 | H39: 2017 | I39: =IFERROR(F39*(C39/SUMIF(H:H,H39,C:C)),0) -> 501.86278
C40: 2291 | E40: 69.21882 | F40: 30213.365 | G40: SH-0155 | H40: 2017 | I40: =IFERROR(F40*(C40/SUMIF(H:H,H40,C:C)),0) -> 1735.1989
C41: 53 | E41: 9.131805 | F41: 172298.21 | G41: SH-0113-OS89 | H41: 2017 | I41: =IFERROR(F41*(C41/SUMIF(H:H,H41,C:C)),0) -> 228.91893
C42: 150 | E42: 7.123275 | F42: 47488.5 | G42: SH-0152 | H42: 2017 | I42: =IFERROR(F42*(C42/SUMIF(H:H,H42,C:C)),0) -> 178.56847
C43: 10000 | E43: 260.6375 | F43: 26063.75 | G43: SH-0158 | H43: 2017 | I43: =IFERROR(F43*(C43/SUMIF(H:H,H43,C:C)),0) -> 6533.7418
C44: 243 | E44: 8.72185 | F44: 35892.387 | H44: 2017 | I44: =IFERROR(F44*(C44/SUMIF(H:H,H44,C:C)),0) -> 218.64205
C45: 204 | E45: 8.814 | F45: 43205.882 | G45: SH-0147 | H45: 2017 | I45: =IFERROR(F45*(C45/SUMIF(H:H,H45,C:C)),0) -> 220.95209
C46: 147 | E46: 4.4 | F46: 29931.973 | G46: SH-0146 | H46: 2016 | I46: =IFERROR(F46*(C46/SUMIF(H:H,H46,C:C)),0) -> 68.743555
C47: 1558 | E47: 52.268893 | F47: 33548.712 | G47: SH-0150 | H47: 2016 | I47: =IFERROR(F47*(C47/SUMIF(H:H,H47,C:C)),0) -> 816.62489
C48: 1133 | E48: 47.077 | F48: 41550.75 | G48: SH-0149 | H48: 2016 | I48: =IFERROR(F48*(C48/SUMIF(H:H,H48,C:C)),0) -> 735.50917
C49: 150 | E49: 4.8994 | F49: 32662.667 | G49: SH0113-OS82 | H49: 2016 | I49: =IFERROR(F49*(C49/SUMIF(H:H,H49,C:C)),0) -> 76.545949
C50: 40 | E50: 1.1528 | F50: 28820 | G50: SH0113-OS81 | H50: 2016 | I50: =IFERROR(F50*(C50/SUMIF(H:H,H50,C:C)),0) -> 18.010811
C51: 639 | E51: 16.8728 | F51: 26405.008 | G51: SH-0113 | H51: 2016 | I51: =IFERROR(F51*(C51/SUMIF(H:H,H51,C:C)),0) -> 263.61279
C52: 1111 | E52: 31.7544 | F52: 28581.818 | G52: SH0113-OS80 | H52: 2016 | I52: =IFERROR(F52*(C52/SUMIF(H:H,H52,C:C)),0) -> 496.11599
C53: 450 | E53: 12.8904 | F53: 28645.333 | G53: SH0113-OS79 | H53: 2016 | I53: =IFERROR(F53*(C53/SUMIF(H:H,H53,C:C)),0) -> 201.39362
C54: 1000 | E54: 28.6104 | F54: 28610.4 | G54: SH0113-OS78 | H54: 2016 | I54: =IFERROR(F54*(C54/SUMIF(H:H,H54,C:C)),0) -> 446.99559
C55: 150 | E55: 4.92 | F55: 32800 | G55: SH-0149 | H55: 2016 | I55: =IFERROR(F55*(C55/SUMIF(H:H,H55,C:C)),0) -> 76.867794
C56: 820 | E56: 30.80718 | F56: 37569.732 | G56: SH-0147 | H56: 2016 | I56: =IFERROR(F56*(C56/SUMIF(H:H,H56,C:C)),0) -> 481.31706
... C58: 320 | E58: 12.02614 | F58: 37581.688 | G58: SH-0145 | H58: 2016 | I58: =IFERROR(F58*(C58/SUMIF(H:H,H58,C:C)),0) -> 187.89082
C59: 663 | E59: 24.6 | F59: 37104.072 | H59: 2016 | I59: =IFERROR(F59*(C59/SUMIF(H:H,H59,C:C)),0) -> 384.33897
C60: 469 | E60: 13.9974 | F60: 29845.203 | G60: SH-0133 - OS77 | H60: 2016 | I60: =IFERROR(F60*(C60/SUMIF(H:H,H60,C:C)),0) -> 218.68887
C61: 1067 | E61: 48.76052 | F61: 45698.707 | G61: SH-0124 | H61: 2016 | I61: =IFERROR(F61*(C61/SUMIF(H:H,H61,C:C)),0) -> 761.81171
C62: 143 | E62: 5.611 | F62: 39237.762 | G62: SH-0148 | H62: 2016 | I62: =IFERROR(F62*(C62/SUMIF(H:H,H62,C:C)),0) -> 87.663657
C63: 3998 | E63: 99.190755 | F63: 24810.094 | G63: SH-0146 | H63: 2016 | I63: =IFERROR(F63*(C63/SUMIF(H:H,H63,C:C)),0) -> 1549.7103
C64: 814 | E64: 24.4524 | F64: 30039.803 | G64: SH0113 - OS76 | H64: 2016 | I64: =IFERROR(F64*(C64/SUMIF(H:H,H64,C:C)),0) -> 382.03293
C65: 50 | E65: 2.46 | G65: SH-0144 | H65: 2016 | I65: =IFERROR(F65*(C65/SUMIF(H:H,H65,C:C)),0) -> 0
C66: 605 | E66: 17.466 | F66: 28869.421 | G66: SH0113 - OS75 | H66: 2016 | I66: =IFERROR(F66*(C66/SUMIF(H:H,H66,C:C)),0) -> 272.88067
C67: 544 | E67: 16.6296 | F67: 30569.118 | G67: SH0113 - OS71 | H67: 2016 | I67: =IFERROR(F67*(C67/SUMIF(H:H,H67,C:C)),0) -> 259.81314
C68: 536 | E68: 18.669432 | F68: 34831.03 | G68: SH-0141 | H68: 2016 | I68: =IFERROR(F68*(C68/SUMIF(H:H,H68,C:C)),0) -> 291.68253
C69: 960 | E69: 27.4044 | F69: 28546.25 | G69: SH0113 - OS70 | H69: 2016 | I69: =IFERROR(F69*(C69/SUMIF(H:H,H69,C:C)),0) -> 428.15361
C70: 1330 | E70: 64.7472 | F70: 48682.105 | G70: SH-0140 | H70: 2016 | I70: =IFERROR(F70*(C70/SUMIF(H:H,H70,C:C)),0) -> 1011.5802
C71: 645 | E71: 19.557 | F71: 30320.93 | G71: SH0113 - OS69 | H71: 2016 | I71: =IFERROR(F71*(C71/SUMIF(H:H,H71,C:C)),0) -> 305.54948
C72: 1295 | E72: 40.230619 | F72: 31066.115 | G72: SH-0142 | H72: 2016 | I72: =IFERROR(F72*(C72/SUMIF(H:H,H72,C:C)),0) -> 628.54449
C73: 940 | E73: 28.6344 | F73: 30462.128 | G73: SH0113 - OS67 | H73: 2016 | I73: =IFERROR(F73*(C73/SUMIF(H:H,H73,C:C)),0) -> 447.37056
C74: 320 | E74: 12.5853 | F74: 39329.062 | G74: SH-0139 | H74: 2016 | I74: =IFERROR(F74*(C74/SUMIF(H:H,H74,C:C)),0) -> 196.62688
C75: 367 | E75: 12.0294 | F75: 32777.657 | G75: SH0113 - OS68 | H75: 2016 | I75: =IFERROR(F75*(C75/SUMIF(H:H,H75,C:C)),0) -> 187.94176
C76: 978 | E76: 27.2568 | F76: 27869.939 | G76: SH0113 - OS66 | H76: 2016 | I76: =IFERROR(F76*(C76/SUMIF(H:H,H76,C:C)),0) -> 425.84758
C77: 4339 | E77: 138.065 | F77: 31819.544 | G77: SH0113 - OS57@OS64 | H77: 2016 | I77: =IFERROR(F77*(C77/SUMIF(H:H,H77,C:C)),0) -> 2157.0634
... C86: 801 | E86: 23.4438 | F86: 29268.165 | G86: SH0113 - OS65 | H86: 2016 | I86: =IFERROR(F86*(C86/SUMIF(H:H,H86,C:C)),0) -> 366.27504
C87: 37 | E87: 1.5252 | F87: 41221.622 | H87: 2016 | I87: =IFERROR(F87*(C87/SUMIF(H:H,H87,C:C)),0) -> 23.829016
C88: 429 | E88: 21.9622 | F88: 51193.939 | H88: 2016 | I88: =IFERROR(F88*(C88/SUMIF(H:H,H88,C:C)),0) -> 343.12721
C89: 358 | E89: 11.648 | F89: 32536.313 | G89: SH0113-OS53 | H89: 2016 | I89: =IFERROR(F89*(C89/SUMIF(H:H,H89,C:C)),0) -> 181.98294
C90: 1386 | E90: 43.8272 | F90: 31621.356 | G90: SH0113-OS52 | H90: 2016 | I90: =IFERROR(F90*(C90/SUMIF(H:H,H90,C:C)),0) -> 684.73581
C91: 399 | E91: 13.1328 | F91: 32914.286 | G91: SH0113-OS51 | H91: 2016 | I91: =IFERROR(F91*(C91/SUMIF(H:H,H91,C:C)),0) -> 205.18076
C92: 547 | E92: 18.942 | F92: 34628.885 | G92: SH0113-OS54 | H92: 2016 | I92: =IFERROR(F92*(C92/SUMIF(H:H,H92,C:C)),0) -> 295.94101
C93: 125 | E93: 6.519 | F93: 52152 | G93: SH-0130 | H93: 2016 | I93: =IFERROR(F93*(C93/SUMIF(H:H,H93,C:C)),0) -> 101.84983
C94: 246 | E94: 8.3886 | F94: 34100 | G94: SH0113-OS50 | H94: 2016 | I94: =IFERROR(F94*(C94/SUMIF(H:H,H94,C:C)),0) -> 131.05959
C95: 3121 | E95: 137.1648 | F95: 43948.991 | G95: SH-0131 | H95: 2016 | I95: =IFERROR(F95*(C95/SUMIF(H:H,H95,C:C)),0) -> 2142.9991
C96: 22995 | E96: 624.14921 | F96: 27142.823 | G96: SH-0133 | H96: 2016 | I96: =IFERROR(F96*(C96/SUMIF(H:H,H96,C:C)),0) -> 9751.4173
C97: 2309 | E97: 79.1817 | F97: 34292.638 | G97: SH-0129 | H97: 2016 | I97: =IFERROR(F97*(C97/SUMIF(H:H,H97,C:C)),0) -> 1237.0981
C98: 330 | E98: 11.4432 | F98: 34676.364 | G98: SH0113-OS45 | H98: 2015 | I98: =IFERROR(F98*(C98/SUMIF(H:H,H98,C:C)),0) -> 231.09639
C99: 744 | E99: 43.758 | F99: 58814.516 | G99: SH-0124 | H99: 2015 | I99: =IFERROR(F99*(C99/SUMIF(H:H,H99,C:C)),0) -> 883.69651
C100: 350 | E100: 11.0208 | F100: 31488 | G100: SH0113-OS46 | H100: 2015 | I100: =IFERROR(F100*(C100/SUMIF(H:H,H100,C:C)),0) -> 222.56599
... C106: 894 | E106: 27.5028 | F106: 30763.758 | G106: SH0113-OS41 | H106: 2015 | I106: =IFERROR(F106*(C106/SUMIF(H:H,H106,C:C)),0) -> 555.42137
C107: 84 | E107: 3.0012 | F107: 35728.571 | H107: 2015 | I107: =IFERROR(F107*(C107/SUMIF(H:H,H107,C:C)),0) -> 60.609488
C108: 110 | E108: 4.059 | F108: 36900 | G108: SH0113-OS37 | H108: 2015 | I108: =IFERROR(F108*(C108/SUMIF(H:H,H108,C:C)),0) -> 81.971848
C109: 180 | E109: 7.0755 | F109: 39308.333 | H109: 2015 | I109: =IFERROR(F109*(C109/SUMIF(H:H,H109,C:C)),0) -> 142.89032
C110: 126 | E110: 7.8 | F110: 61904.762 | H110: 2015 | I110: =IFERROR(F110*(C110/SUMIF(H:H,H110,C:C)),0) -> 157.52166
C111: 95 | E111: 2.275 | F111: 23947.368 | H111: 2015 | I111: =IFERROR(F111*(C111/SUMIF(H:H,H111,C:C)),0) -> 45.943817
H112: 2015 | I112: =IFERROR(F112*(C112/SUMIF(H:H,H112,C:C)),0) -> 0
C113: 998 | E113: 23.1168 | F113: 23163.126 | H113: 2015 | I113: =IFERROR(F113*(C113/SUMIF(H:H,H113,C:C)),0) -> 466.84573
C114: 1553 | E114: 59.0154 | F114: 38000.901 | H114: 2015 | I114: =IFERROR(F114*(C114/SUMIF(H:H,H114,C:C)),0) -> 1191.821
...

Sheet Indicadores
AU2: HH EJECUTADAS | BN2: =SUMIFS(Ofertas!W2374:W2765,Ofertas!T2374:T2765,Indicadores!A6,Ofertas!AG2374:AG2765,Indicadores!B3) -> 8661 | BP2: AÑOS | BQ2: TIPO DE NEGOCIACIÓN
B3: 2010 | K3: 2010 | L3: ND | M3: NEGOCIACIÓN DIRECTA | T3: 2010 | U3: LM | V3: LICITACIÓN MÚLTIPLE | AU3: AÑO | AV3: HH REALES | BP3: 2010 | BQ3: ND | BR3: ND: Negociación Directa
B4: STATUS (a la fecha) | C4: Can. | D4: % | E4: hh Lic. | F4: % hh | G4: M$ Lic. | H4: % M$ | K4: STATUS (a la fecha) | L4: Can. | M4: % | N4: hh Lic. | O4: % hh | P4: M$ Lic. | Q4: % M$ | T4: STATUS (a la fecha) | U4: Can. | V4: % | W4: hh Lic. | X4: % hh | Y4: M$ Lic. | Z4: % M$ | AU4: 2010 | AV4: 6000 | BP4: 2011 | BQ4: LM | BR4: LM: Licitación Multiple
B5: Totales | C5: =SUM(C6:C10) -> 51 | D5: =SUM(D6:D10) -> 59.235294 | E5: =SUM(E6:E10) -> 58189 | F5: =SUM(F6:F10) -> 1 | G5: =SUM(G6:G10) -> 1776.7818 | H5: =SUM(H6:H10) -> 100 | K5: Totales | L5: =SUM(L6:L10) -> 45 | M5: =SUM(M6:M10) -> 100 | N5: =SUM(N6:N10) -> 32472 | O5: =SUM(O6:O10) -> 73.594512 | P5: =SUM(P6:P10) -> 1022.4408 | Q5: =SUM(Q6:Q10) -> 100 | T5: Totales | U5: =SUM(U6:U10) -> 6 | V5: =SUM(V6:V10) -> 100 | W5: =SUM(W6:W10) -> 25717 | X5: =SUM(X6:X10) -> 100 | Y5: =SUM(Y6:Y10) -> 754.341 | Z5: =SUM(Z6:Z10) -> 100 | AU5: 2011 | AV5: 25871.607 | BP5: 2012 | BQ5: AC | BR5: AC: Apoyo Contratos
A6: PG | B6: Propuestas Ganadas | C6: =COUNTIFS(Ofertas!$T$2242:$T$2765,Indicadores!A6,Ofertas!$AG$2242:$AG$2765,$B$3) -> 21 | D6: =C6/$C$5 -> 0.41176471 | E6: =SUMIFS(Ofertas!$W$2242:$W$2765,Ofertas!$T$2242:$T$2765,Indicadores!A6,Ofertas!$AG$2242:$AG$2765,Indicadores!$B$3) -> 8661 | F6: =E6/$E$5 -> 0.14884256 | G6: =SUMIFS(Ofertas!$X$2242:$X$2765,Ofertas!$T$2242:$T$2765,Indicadores!A6,Ofertas!$AG$2242:$AG$2765,Indicadores!$B$3) -> 365.60044 | H6: =G6/$G$5*100 -> 20.576553 | J6: PG | K6: Propuestas Ganadas | L6: =COUNTIFS(Ofertas!$T$2242:$T$2765,Indicadores!J6,Ofertas!$AG$2242:$AG$2765,$K$3,Ofertas!$L$2242:$L$2765,Indicadores!$L$3) -> 21 | M6: =L6/$L$5*100 -> 46.666667 | N6: =SUMIFS(Ofertas!$W$2242:$W$2765,Ofertas!$T$2242:$T$2765,Indicadores!J6,Ofertas!$AG$2242:$AG$2765,Indicadores!$K$3,Ofertas!$L$2242:$L$2765,Indicadores!$L$3) -> 8661 | O6: =N6/$N$5 -> 0.2667221 | P6: =SUMIFS(Ofertas!$X$2242:$X$2765,Ofertas!$T$2242:$T$2765,Indicadores!J6,Ofertas!$AG$2242:$AG$2765,Indicadores!$K$3,Ofertas!$L$2242:$L$2765,Indicadores!$L$3) -> 365.60044 | Q6: =P6/$P$5*100 -> 35.757616 | S6: PG | T6: Propuestas Ganadas | U6: =COUNTIFS(Ofertas!$T$2242:$T$2765,Indicadores!S6,Ofertas!$AG$2242:$AG$2765,$T$3,Ofertas!$L$2242:$L$2765,Indicadores!$U$3) -> 0 | V6: =U6/$U$5*100 -> 0 | W6: =SUMIFS(Ofertas!$W$2242:$W$2765,Ofertas!$T$2242:$T$2765,Indicadores!S6,Ofertas!$AG$2242:$AG$2765,Indicadores!$T$3,Ofertas!$L$2242:$L$2765,Indicadores!$U$3) -> 0 | X6: =W6/$W$5 -> 0 | Y6: =SUMIFS(Ofertas!$X$2242:$X$2765,Ofertas!$T$2242:$T$2765,Indicadores!S6,Ofertas!$AG$2242:$AG$2765,Indicadores!$T$3,Ofertas!$L$2242:$L$2765,Indicadores!$U$3) -> 0 | Z6: =Y6/$Y$5*100 -> 0 | AU6: 2012 | AV6: 25836.367 | BP6: 2013 | BQ6: LC | BR6: LC: Licitación Contrato Abierto
A7: PP | B7: Propuestas Perdidas | C7: =COUNTIFS(Ofertas!$T$2242:$T$2765,Indicadores!A7,Ofertas!$AG$2242:$AG$2765,$B$3) -> 30 | D7: =C7/$C$5*100 -> 58.823529 | E7: =SUMIFS(Ofertas!$W$2242:$W$2765,Ofertas!$T$2242:$T$2765,Indicadores!A7,Ofertas!$AG$2242:$AG$2765,Indicadores!$B$3) -> 49528 | F7: =E7/$E$5 -> 0.85115744 | G7: =SUMIFS(Ofertas!$X$2242:$X$2765,Ofertas!$T$2242:$T$2765,Indicadores!A7,Ofertas!$AG$2242:$AG$2765,Indicadores!$B$3) -> 1411.1813 | H7: =G7/$G$5*100 -> 79.423447 | J7: PP | K7: Propuestas Perdidas | L7: =COUNTIFS(Ofertas!$T$2242:$T$2765,Indicadores!J7,Ofertas!$AG$2242:$AG$2765,$K$3,Ofertas!$L$2242:$L$2765,Indicadores!$L$3) -> 24 | M7: =L7/$L$5*100 -> 53.333333 | N7: =SUMIFS(Ofertas!$W$2242:$W$2765,Ofertas!$T$2242:$T$2765,Indicadores!J7,Ofertas!$AG$2242:$AG$2765,Indicadores!$K$3,Ofertas!$L$2242:$L$2765,Indicadores!$L$3) -> 23811 | O7: =N7/$N$5*100 -> 73.32779 | P7: =SUMIFS(Ofertas!$X$2242:$X$2765,Ofertas!$T$2242:$T$2765,Indicadores!J7,Ofertas!$AG$2242:$AG$2765,Indicadores!$K$3,Ofertas!$L$2242:$L$2765,Indicadores!$L$3) -> 656.84032 | Q7: =P7/$P$5*100 -> 64.242384 | S7: PP | T7: Propuestas Perdidas | U7: =COUNTIFS(Ofertas!$T$2242:$T$2765,Indicadores!S7,Ofertas!$AG$2242:$AG$2765,$T$3,Ofertas!$L$2242:$L$2765,Indicadores!$U$3) -> 6 | V7: =U7/$U$5*100 -> 100 | W7: =SUMIFS(Ofertas!$W$2242:$W$2765,Ofertas!$T$2242:$T$2765,Indicadores!S7,Ofertas!$AG$2242:$AG$2765,Indicadores!$T$3,Ofertas!$L$2242:$L$2765,Indicadores!$U$3) -> 25717 | X7: =W7/$W$5*100 -> 100 | Y7: =SUMIFS(Ofertas!$X$2242:$X$2765,Ofertas!$T$2242:$T$2765,Indicadores!S7,Ofertas!$AG$2242:$AG$2765,Indicadores!$T$3,Ofertas!$L$2242:$L$2765,Indicadores!$U$3) -> 754.341 | Z7: =Y7/$Y$5*100 -> 100 | AU7: 2013 | AV7: 23559 | BP7: 2014 | BQ7: N/A | BR7: N/A: No Aplica
A8: PD | B8: Propuestas Desiertas | C8: =COUNTIFS(Ofertas!$T$2242:$T$2765,Indicadores!A8,Ofertas!$AG$2242:$AG$2765,$B$3) -> 0 | D8: =C8/$C$5*100 -> 0 | E8: =SUMIFS(Ofertas!$W$2242:$W$2765,Ofertas!$T$2242:$T$2765,Indicadores!A8,Ofertas!$AG$2242:$AG$2765,Indicadores!$B$3) -> 0 | F8: =E8/$E$5*100 -> 0 | G8: =SUMIFS(Ofertas!$X$2242:$X$2765,Ofertas!$T$2242:$T$2765,Indicadores!A8,Ofertas!$AG$2242:$AG$2765,Indicadores!$B$3) -> 0 | H8: =G8/$G$5*100 -> 0 | J8: PD | K8: Propuestas Desiertas | L8: =COUNTIFS(Ofertas!$T$2242:$T$2765,Indicadores!J8,Ofertas!$AG$2242:$AG$2765,$K$3,Ofertas!$L$2242:$L$2765,Indicadores!$L$3) -> 0 | M8: =L8/$L$5*100 -> 0 | N8: =SUMIFS(Ofertas!$W$2242:$W$2765,Ofertas!$T$2242:$T$2765,Indicadores!J8,Ofertas!$AG$2242:$AG$2765,Indicadores!$K$3,Ofertas!$L$2242:$L$2765,Indicadores!$L$3) -> 0 | O8: =N8/$N$5*100 -> 0 | P8: =SUMIFS(Ofertas!$X$2242:$X$2765,Ofertas!$T$2242:$T$2765,Indicadores!J8,Ofertas!$AG$2242:$AG$2765,Indicadores!$K$3,Ofertas!$L$2242:$L$2765,Indicadores!$L$3) -> 0 | Q8: =P8/$P$5*100 -> 0 | S8: PD | T8: Propuestas Desiertas | U8: =COUNTIFS(Ofertas!$T$2242:$T$2765,Indicadores!S8,Ofertas!$AG$2242:$AG$2765,$T$3,Ofertas!$L$2242:$L$2765,Indicadores!$U$3) -> 0 | V8: =U8/$U$5*100 -> 0 | W8: =SUMIFS(Ofertas!$W$2242:$W$2765,Ofertas!$T$2242:$T$2765,Indicadores!S8,Ofertas!$AG$2242:$AG$2765,Indicadores!$T$3,Ofertas!$L$2242:$L$2765,Indicadores!$U$3) -> 0 | X8: =W8/$W$5*100 -> 0 | Y8: =SUMIFS(Ofertas!$X$2242:$X$2765,Ofertas!$T$2242:$T$2765,Indicadores!S8,Ofertas!$AG$2242:$AG$2765,Indicadores!$T$3,Ofertas!$L$2242:$L$2765,Indicadores!$U$3) -> 0 | Z8: =Y8/$Y$5*100 -> 0 | AU8: 2014 | AV8: 33299 | BP8: 2015
A9: DP | B9: Decisión del Cliente Pendiente | C9: =COUNTIFS(Ofertas!$T$2242:$T$2765,Indicadores!A9,Ofertas!$AG$2242:$AG$2765,$B$3) -> 0 | D9: =C9/$C$5*100 -> 0 | E9: =SUMIFS(Ofertas!$W$2242:$W$2765,Ofertas!$T$2242:$T$2765,Indicadores!A9,Ofertas!$AG$2242:$AG$2765,Indicadores!$B$3) -> 0 | F9: =E9/$E$5*100 -> 0 | G9: =SUMIFS(Ofertas!$X$2242:$X$2765,Ofertas!$T$2242:$T$2765,Indicadores!A9,Ofertas!$AG$2242:$AG$2765,Indicadores!$B$3) -> 0 | H9: =G9/$G$5*100 -> 0 | J9: DP | K9: Decisión del Cliente Pendiente | L9: =COUNTIFS(Ofertas!$T$2242:$T$2765,Indicadores!J9,Ofertas!$AG$2242:$AG$2765,$K$3,Ofertas!$L$2242:$L$2765,Indicadores!$L$3) -> 0 | M9: =L9/$L$5*100 -> 0 | N9: =SUMIFS(Ofertas!$W$2242:$W$2765,Ofertas!$T$2242:$T$2765,Indicadores!J9,Ofertas!$AG$2242:$AG$2765,Indicadores!$K$3,Ofertas!$L$2242:$L$2765,Indicadores!$L$3) -> 0 | O9: =N9/$N$5*100 -> 0 | P9: =SUMIFS(Ofertas!$X$2242:$X$2765,Ofertas!$T$2242:$T$2765,Indicadores!J9,Ofertas!$AG$2242:$AG$2765,Indicadores!$K$3,Ofertas!$L$2242:$L$2765,Indicadores!$L$3) -> 0 | Q9: =P9/$P$5*100 -> 0 | S9: DP | T9: Decisión del Cliente Pendiente | U9: =COUNTIFS(Ofertas!$T$2242:$T$2765,Indicadores!S9,Ofertas!$AG$2242:$AG$2765,$T$3,Ofertas!$L$2242:$L$2765,Indicadores!$U$3) -> 0 | V9: =U9/$U$5*100 -> 0 | W9: =SUMIFS(Ofertas!$W$2242:$W$2765,Ofertas!$T$2242:$T$2765,Indicadores!S9,Ofertas!$AG$2242:$AG$2765,Indicadores!$T$3,Ofertas!$L$2242:$L$2765,Indicadores!$U$3) -> 0 | X9: =W9/$W$5*100 -> 0 | Y9: =SUMIFS(Ofertas!$X$2242:$X$2765,Ofertas!$T$2242:$T$2765,Indicadores!S9,Ofertas!$AG$2242:$AG$2765,Indicadores!$T$3,Ofertas!$L$2242:$L$2765,Indicadores!$U$3) -> 0 | Z9: =Y9/$Y$5*100 -> 0 | AU9: 2015 | AV9: 49033 | BP9: 2016
A10: EP | B10: Propuestas en Preparación | C10: =COUNTIFS(Ofertas!$T$2242:$T$2765,Indicadores!A10,Ofertas!$AG$2242:$AG$2765,$B$3) -> 0 | D10: =C10/$C$5*100 -> 0 | E10: =SUMIFS(Ofertas!$W$2242:$W$2765,Ofertas!$T$2242:$T$2765,Indicadores!A10,Ofertas!$AG$2242:$AG$2765,Indicadores!$B$3) -> 0 | F10: =E10/$E$5*100 -> 0 | G10: =SUMIFS(Ofertas!$X$2242:$X$2765,Ofertas!$T$2242:$T$2765,Indicadores!A10,Ofertas!$AG$2242:$AG$2765,Indicadores!$B$3) -> 0 | H10: =G10/$G$5*100 -> 0 | J10: EP | K10: Propuestas en Preparación | L10: =COUNTIFS(Ofertas!$T$2242:$T$2765,Indicadores!J10,Ofertas!$AG$2242:$AG$2765,$K$3,Ofertas!$L$2242:$L$2765,Indicadores!$L$3) -> 0 | M10: =L10/$L$5*100 -> 0 | N10: =SUMIFS(Ofertas!$W$2242:$W$2765,Ofertas!$T$2242:$T$2765,Indicadores!J10,Ofertas!$AG$2242:$AG$2765,Indicadores!$K$3,Ofertas!$L$2242:$L$2765,Indicadores!$L$3) -> 0 | O10: =N10/$N$5*100 -> 0 | P10: =SUMIFS(Ofertas!$X$2242:$X$2765,Ofertas!$T$2242:$T$2765,Indicadores!J10,Ofertas!$AG$2242:$AG$2765,Indicadores!$K$3,Ofertas!$L$2242:$L$2765,Indicadores!$L$3) -> 0 | Q10: =P10/$P$5*100 -> 0 | S10: EP | T10: Propuestas en Preparación | U10: =COUNTIFS(Ofertas!$T$2242:$T$2765,Indicadores!S10,Ofertas!$AG$2242:$AG$2765,$T$3,Ofertas!$L$2242:$L$2765,Indicadores!$U$3) -> 0 | V10: =U10/$U$5*100 -> 0 | W10: =SUMIFS(Ofertas!$W$2242:$W$2765,Ofertas!$T$2242:$T$2765,Indicadores!S10,Ofertas!$AG$2242:$AG$2765,Indicadores!$T$3,Ofertas!$L$2242:$L$2765,Indicadores!$U$3) -> 0 | X10: =W10/$W$5*100 -> 0 | Y10: =SUMIFS(Ofertas!$X$2242:$X$2765,Ofertas!$T$2242:$T$2765,Indicadores!S10,Ofertas!$AG$2242:$AG$2765,Indicadores!$T$3,Ofertas!$L$2242:$L$2765,Indicadores!$U$3) -> 0 | Z10: =Y10/$Y$5*100 -> 0 | AU10: 2016 | AV10: 76874.895
AU11: 2017 | AV11: 60269
B12: 2011 | K12: 2011 | L12: ND | M12: NEGOCIACIÓN DIRECTA | T12: 2011 | U12: LM | V12: LICITACIÓN MÚLTIPLE | AU12: 2018 | AV12: 42085
B13: STATUS (a la fecha) | C13: Can. | D13: % | E13: hh Lic. | F13: % hh | G13: M$ Lic. | H13: % M$ | K13: STATUS (a la fecha) | L13: Can. | M13: % | N13: hh Lic. | O13: % hh | P13: M$ Lic. | Q13: % M$ | T13: STATUS (a la fecha) | U13: Can. | V13: % | W13: hh Lic. | X13: % hh | Y13: M$ Lic. | Z13: % M$ | AU13: 2019 | AV13: 86458
B14: Totales | C14: =SUM(C15:C19) -> 50 | D14: =SUM(D15:D19) -> 50.5 | E14: =SUM(E15:E19) -> 102632.51 | F14: =SUM(F15:F19) -> 1 | G14: =SUM(G15:G19) -> 4304.8254 | H14: =SUM(H15:H19) -> 1 | K14: Totales | L14: =SUM(L15:L19) -> 42 | M14: =SUM(M15:M19) -> 100 | N14: =SUM(N15:N19) -> 27932.507 | O14: =SUM(O15:O19) -> 39.26026 | P14: =SUM(P15:P19) -> 896.68687 | Q14: =SUM(Q15:Q19) -> 100 | T14: Totales | U14: =SUM(U15:U19) -> 8 | V14: =SUM(V15:V19) -> 100 | W14: =SUM(W15:W19) -> 74700 | X14: =SUM(X15:X19) -> 100 | Y14: =SUM(Y15:Y19) -> 3408.1385 | Z14: =SUM(Z15:Z19) -> 100 | AU14: 2020 | AV14: 68104
A15: PG | B15: Propuestas Ganadas | C15: =COUNTIFS(Ofertas!$T$2242:$T$2765,Indicadores!A15,Ofertas!$AG$2242:$AG$2765,$B$12) -> 25 | D15: =C15/$C$14 -> 0.5 | E15: =SUMIFS(Ofertas!$W$2242:$W$2765,Ofertas!$T$2242:$T$2765,Indicadores!A15,Ofertas!$AG$2242:$AG$2765,Indicadores!$B$12) -> 17137.507 | F15: =E15/$E$14 -> 0.16697933 | G15: =SUMIFS(Ofertas!$X$2242:$X$2765,Ofertas!$T$2242:$T$2765,Indicadores!A15,Ofertas!$AG$2242:$AG$2765,Indicadores!$B$12) -> 501.15986 | H15: =G15/$G$14 -> 0.11641816 | J15: PG | K15: Propuestas Ganadas | L15: =COUNTIFS(Ofertas!$T$2242:$T$2765,Indicadores!J15,Ofertas!$AG$2242:$AG$2765,$K$12,Ofertas!$L$2242:$L$2765,Indicadores!$L$12) -> 25 | M15: =L15/$L$14*100 -> 59.52381 | N15: =SUMIFS(Ofertas!$W$2242:$W$2765,Ofertas!$T$2242:$T$2765,Indicadores!J15,Ofertas!$AG$2242:$AG$2765,Indicadores!$K$12,Ofertas!$L$2242:$L$2765,Indicadores!$L$12) -> 17137.507 | O15: =N15/$N$14 -> 0.61353273 | P15: =SUMIFS(Ofertas!$X$2242:$X$2765,Ofertas!$T$2242:$T$2765,Indicadores!J15,Ofertas!$AG$2242:$AG$2765,Indicadores!$K$12,Ofertas!$L$2242:$L$2765,Indicadores!$L$12) -> 501.15986 | Q15: =P15/$P$14*100 -> 55.890175 | S15: PG | T15: Propuestas Ganadas | U15: =COUNTIFS(Ofertas!$T$2242:$T$2765,Indicadores!S15,Ofertas!$AG$2242:$AG$2765,$T$12,Ofertas!$L$2242:$L$2765,Indicadores!$U$12) -> 0 | V15: =U15/$U$14*100 -> 0 | W15: =SUMIFS(Ofertas!$W$2242:$W$2765,Ofertas!$T$2242:$T$2765,Indicadores!S15,Ofertas!$AG$2242:$AG$2765,Indicadores!$T$12,Ofertas!$L$2242:$L$2765,Indicadores!$U$12) -> 0 | X15: =W15/$W$14 -> 0 | Y15: =SUMIFS(Ofertas!$X$2242:$X$2765,Ofertas!$T$2242:$T$2765,Indicadores!S15,Ofertas!$AG$2242:$AG$2765,Indicadores!$T$12,Ofertas!$L$2242:$L$2765,Indicadores!$U$12) -> 0 | Z15: =Y15/$Y$14*100 -> 0 | AU15: 2021 | AV15: 60000
A16: PP | B16: Propuestas Perdidas | C16: =COUNTIFS(Ofertas!$T$2242:$T$2765,Indicadores!A16,Ofertas!$AG$2242:$AG$2765,$B$12) -> 25 | D16: =C16/$C$14*100 -> 50 | E16: =SUMIFS(Ofertas!$W$2242:$W$2765,Ofertas!$T$2242:$T$2765,Indicadores!A16,Ofertas!$AG$2242:$AG$2765,Indicadores!$B$12) -> 85495 | F16: =E16/$E$14 -> 0.83302067 | G16: =SUMIFS(Ofertas!$X$2242:$X$2765,Ofertas!$T$2242:$T$2765,Indicadores!A16,Ofertas!$AG$2242:$AG$2765,Indicadores!$B$12) -> 3803.6655 | H16: =G16/$G$14 -> 0.88358184 | J16: PP | K16: Propuestas Perdidas | L16: =COUNTIFS(Ofertas!$T$2242:$T$2765,Indicadores!J16,Ofertas!$AG$2242:$AG$2765,$K$12,Ofertas!$L$2242:$L$2765,Indicadores!$L$12) -> 17 | M16: =L16/$L$14*100 -> 40.47619 | N16: =SUMIFS(Ofertas!$W$2242:$W$2765,Ofertas!$T$2242:$T$2765,Indicadores!J16,Ofertas!$AG$2242:$AG$2765,Indicadores!$K$12,Ofertas!$L$2242:$L$2765,Indicadores!$L$12) -> 10795 | O16: =N16/$N$14*100 -> 38.646727 | P16: =SUMIFS(Ofertas!$X$2242:$X$2765,Ofertas!$T$2242:$T$2765,Indicadores!J16,Ofertas!$AG$2242:$AG$2765,Indicadores!$K$12,Ofertas!$L$2242:$L$2765,Indicadores!$L$12) -> 395.52701 | Q16: =P16/$P$14*100 -> 44.109825 | S16: PP | T16: Propuestas Perdidas | U16: =COUNTIFS(Ofertas!$T$2242:$T$2765,Indicadores!S16,Ofertas!$AG$2242:$AG$2765,$T$12,Ofertas!$L$2242:$L$2765,Indicadores!$U$12) -> 8 | V16: =U16/$U$14*100 -> 100 | W16: =SUMIFS(Ofertas!$W$2242:$W$2765,Ofertas!$T$2242:$T$2765,Indicadores!S16,Ofertas!$AG$2242:$AG$2765,Indicadores!$T$12,Ofertas!$L$2242:$L$2765,Indicadores!$U$12) -> 74700 | X16: =W16/$W$14*100 -> 100 | Y16: =SUMIFS(Ofertas!$X$2242:$X$2765,Ofertas!$T$2242:$T$2765,Indicadores!S16,Ofertas!$AG$2242:$AG$2765,Indicadores!$T$12,Ofertas!$L$2242:$L$2765,Indicadores!$U$12) -> 3408.1385 | Z16: =Y16/$Y$14*100 -> 100
A17: PD | B17: Propuestas Desiertas | C17: =COUNTIFS(Ofertas!$T$2242:$T$2765,Indicadores!A17,Ofertas!$AG$2242:$AG$2765,$B$12) -> 0 | D17: =C17/$C$14*100 -> 0 | E17: =SUMIFS(Ofertas!$W$2242:$W$2765,Ofertas!$T$2242:$T$2765,Indicadores!A17,Ofertas!$AG$2242:$AG$2765,Indicadores!$B$12) -> 0 | F17: =E17/$E$5*100 -> 0 | G17: =SUMIFS(Ofertas!$X$2242:$X$2765,Ofertas!$T$2242:$T$2765,Indicadores!A17,Ofertas!$AG$2242:$AG$2765,Indicadores!$B$12) -> 0 | H17: =G17/$G$5*100 -> 0 | J17: PD | K17: Propuestas Desiertas | L17: =COUNTIFS(Ofertas!$T$2242:$T$2765,Indicadores!J17,Ofertas!$AG$2242:$AG$2765,$K$12,Ofertas!$L$2242:$L$2765,Indicadores!$L$12) -> 0 | M17: =L17/$L$14*100 -> 0 | N17: =SUMIFS(Ofertas!$W$2242:$W$2765,Ofertas!$T$2242:$T$2765,Indicadores!J17,Ofertas!$AG$2242:$AG$2765,Indicadores!$K$12,Ofertas!$L$2242:$L$2765,Indicadores!$L$12) -> 0 | O17: =N17/$N$14*100 -> 0 | P17: =SUMIFS(Ofertas!$X$2242:$X$2765,Ofertas!$T$2242:$T$2765,Indicadores!J17,Ofertas!$AG$2242:$AG$2765,Indicadores!$K$12,Ofertas!$L$2242:$L$2765,Indicadores!$L$12) -> 0 | Q17: =P17/$P$14*100 -> 0 | S17: PD | T17: Propuestas Desiertas | U17: =COUNTIFS(Ofertas!$T$2242:$T$2765,Indicadores!S17,Ofertas!$AG$2242:$AG$2765,$T$12,Ofertas!$L$2242:$L$2765,Indicadores!$U$12) -> 0 | V17: =U17/$U$14*100 -> 0 | W17: =SUMIFS(Ofertas!$W$2242:$W$2765,Ofertas!$T$2242:$T$2765,Indicadores!S17,Ofertas!$AG$2242:$AG$2765,Indicadores!$T$12,Ofertas!$L$2242:$L$2765,Indicadores!$U$12) -> 0 | X17: =W17/$W$14*100 -> 0 | Y17: =SUMIFS(Ofertas!$X$2242:$X$2765,Ofertas!$T$2242:$T$2765,Indicadores!S17,Ofertas!$AG$2242:$AG$2765,Indicadores!$T$12,Ofertas!$L$2242:$L$2765,Indicadores!$U$12) -> 0 | Z17: =Y17/$Y$14*100 -> 0
A18: DP | B18: Decisión del Cliente Pendiente | C18: =COUNTIFS(Ofertas!$T$2242:$T$2765,Indicadores!A18,Ofertas!$AG$2242:$AG$2765,$B$12) -> 0 | D18: =C18/$C$14*100 -> 0 | E18: =SUMIFS(Ofertas!$W$2242:$W$2765,Ofertas!$T$2242:$T$2765,Indicadores!A18,Ofertas!$AG$2242:$AG$2765,Indicadores!$B$12) -> 0 | F18: =E18/$E$5*100 -> 0 | G18: =SUMIFS(Ofertas!$X$2242:$X$2765,Ofertas!$T$2242:$T$2765,Indicadores!A18,Ofertas!$AG$2242:$AG$2765,Indicadores!$B$12) -> 0 | H18: =G18/$G$5*100 -> 0 | J18: DP | K18: Decisión del Cliente Pendiente | L18: =COUNTIFS(Ofertas!$T$2242:$T$2765,Indicadores!J18,Ofertas!$AG$2242:$AG$2765,$K$12,Ofertas!$L$2242:$L$2765,Indicadores!$L$12) -> 0 | M18: =L18/$L$14*100 -> 0 | N18: =SUMIFS(Ofertas!$W$2242:$W$2765,Ofertas!$T$2242:$T$2765,Indicadores!J18,Ofertas!$AG$2242:$AG$2765,Indicadores!$K$12,Ofertas!$L$2242:$L$2765,Indicadores!$L$12) -> 0 | O18: =N18/$N$14*100 -> 0 | P18: =SUMIFS(Ofertas!$X$2242:$X$2765,Ofertas!$T$2242:$T$2765,Indicadores!J18,Ofertas!$AG$2242:$AG$2765,Indicadores!$K$12,Ofertas!$L$2242:$L$2765,Indicadores!$L$12) -> 0 | Q18: =P18/$P$14*100 -> 0 | S18: DP | T18: Decisión del Cliente Pendiente | U18: =COUNTIFS(Ofertas!$T$2242:$T$2765,Indicadores!S18,Ofertas!$AG$2242:$AG$2765,$T$12,Ofertas!$L$2242:$L$2765,Indicadores!$U$12) -> 0 | V18: =U18/$U$14*100 -> 0 | W18: =SUMIFS(Ofertas!$W$2242:$W$2765,Ofertas!$T$2242:$T$2765,Indicadores!S18,Ofertas!$AG$2242:$AG$2765,Indicadores!$T$12,Ofertas!$L$2242:$L$2765,Indicadores!$U$12) -> 0 | X18: =W18/$W$14*100 -> 0 | Y18: =SUMIFS(Ofertas!$X$2242:$X$2765,Ofertas!$T$2242:$T$2765,Indicadores!S18,Ofertas!$AG$2242:$AG$2765,Indicadores!$T$12,Ofertas!$L$2242:$L$2765,Indicadores!$U$12) -> 0 | Z18: =Y18/$Y$14*100 -> 0
A19: EP | B19: Propuestas en Preparación | C19: =COUNTIFS(Ofertas!$T$2242:$T$2765,Indicadores!A19,Ofertas!$AG$2242:$AG$2765,$B$12) -> 0 | D19: =C19/$C$14*100 -> 0 | E19: =SUMIFS(Ofertas!$W$2242:$W$2765,Ofertas!$T$2242:$T$2765,Indicadores!A19,Ofertas!$AG$2242:$AG$2765,Indicadores!$B$12) -> 0 | F19: =E19/$E$5*100 -> 0 | G19: =SUMIFS(Ofertas!$X$2242:$X$2765,Ofertas!$T$2242:$T$2765,Indicadores!A19,Ofertas!$AG$2242:$AG$2765,Indicadores!$B$12) -> 0 | H19: =G19/$G$5*100 -> 0 | J19: EP | K19: Propuestas en Preparación | L19: =COUNTIFS(Ofertas!$T$2242:$T$2765,Indicadores!J19,Ofertas!$AG$2242:$AG$2765,$K$12,Ofertas!$L$2242:$L$2765,Indicadores!$L$12) -> 0 | M19: =L19/$L$14*100 -> 0 | N19: =SUMIFS(Ofertas!$W$2242:$W$2765,Ofertas!$T$2242:$T$2765,Indicadores!J19,Ofertas!$AG$2242:$AG$2765,Indicadores!$K$12,Ofertas!$L$2242:$L$2765,Indicadores!$L$12) -> 0 | O19: =N19/$N$14*100 -> 0 | P19: =SUMIFS(Ofertas!$X$2242:$X$2765,Ofertas!$T$2242:$T$2765,Indicadores!J19,Ofertas!$AG$2242:$AG$2765,Indicadores!$K$12,Ofertas!$L$2242:$L$2765,Indicadores!$L$12) -> 0 | Q19: =P19/$P$14*100 -> 0 | S19: EP | T19: Propuestas en Preparación | U19: =COUNTIFS(Ofertas!$T$2242:$T$2765,Indicadores!S19,Ofertas!$AG$2242:$AG$2765,$T$12,Ofertas!$L$2242:$L$2765,Indicadores!$U$12) -> 0 | V19: =U19/$U$14*100 -> 0 | W19: =SUMIFS(Ofertas!$W$2242:$W$2765,Ofertas!$T$2242:$T$2765,Indicadores!S19,Ofertas!$AG$2242:$AG$2765,Indicadores!$T$12,Ofertas!$L$2242:$L$2765,Indicadores!$U$12) -> 0 | X19: =W19/$W$14*100 -> 0 | Y19: =SUMIFS(Ofertas!$X$2242:$X$2765,Ofertas!$T$2242:$T$2765,Indicadores!S19,Ofertas!$AG$2242:$AG$2765,Indicadores!$T$12,Ofertas!$L$2242:$L$2765,Indicadores!$U$12) -> 0 | Z19: =Y19/$Y$14*100 -> 0
B21: 2012 | K21: 2012 | L21: ND | M21: NEGOCIACIÓN DIRECTA | T21: 2012 | U21: LM | V21: LICITACIÓN MÚLTIPLE
B22: STATUS (a la fecha) | C22: Can. | D22: % | E22: hh Lic. | F22: % hh | G22: M$ Lic. | H22: % M$ | K22: STATUS (a la fecha) | L22: Can. | M22: % | N22: hh Lic. | O22: % hh | P22: M$ Lic. | Q22: % M$ | T22: STATUS (a la fecha) | U22: Can. | V22: % | W22: hh Lic. | X22: % hh | Y22: M$ Lic. | Z22: % M$
B23: Totales | C23: =SUM(C24:C28) -> 60 | D23: =SUM(D24:D28) -> 1 | E23: =SUM(E24:E28) -> 128917.5 | F23: =SUM(F24:F28) -> 1 | G23: =SUM(G24:G28) -> 4372.6884 | H23: =SUM(H24:H28) -> 1 | K23: Totales | L23: =SUM(L24:L28) -> 52 | M23: =SUM(M24:M28) -> 100 | N23: =SUM(N24:N28) -> 92328.5 | O23: =SUM(O24:O28) -> 78.759099 | P23: =SUM(P24:P28) -> 3334.8189 | Q23: =SUM(Q24:Q28) -> 100 | T23: Totales | U23: =SUM(U24:U28) -> 8 | V23: =SUM(V24:V28) -> 100 | W23: =SUM(W24:W28) -> 36589 | X23: =SUM(X24:X28) -> 98.308918 | Y23: =SUM(Y24:Y28) -> 1037.8695 | Z23: =SUM(Z24:Z28) -> 100
A24: PG | B24: Propuestas Ganadas | C24: =COUNTIFS(Ofertas!$T$2242:$T$2765,Indicadores!A24,Ofertas!$AG$2242:$AG$2765,$B$21) -> 23 | D24: =C24/$C$23 -> 0.38333333 | E24: =SUMIFS(Ofertas!$W$2242:$W$2765,Ofertas!$T$2242:$T$2765,Indicadores!A24,Ofertas!$AG$2242:$AG$2765,Indicadores!$B$21) -> 20434.5 | F24: =E24/$E$23 -> 0.15850835 | G24: =SUMIFS(Ofertas!$X$2242:$X$2765,Ofertas!$T$2242:$T$2765,Indicadores!A24,Ofertas!$AG$2242:$AG$2765,Indicadores!$B$21) -> 668.23613 | H24: =G24/$G$23 -> 0.15282043 | J24: PG | K24: Propuestas Ganadas | L24: =COUNTIFS(Ofertas!$T$2242:$T$2765,Indicadores!J24,Ofertas!$AG$2242:$AG$2765,$K$21,Ofertas!$L$2242:$L$2765,Indicadores!$L$21) -> 22 | M24: =L24/$L$23*100 -> 42.307692 | N24: =SUMIFS(Ofertas!$W$2242:$W$2765,Ofertas!$T$2242:$T$2765,Indicadores!J24,Ofertas!$AG$2242:$AG$2765,Indicadores!$K$21,Ofertas!$L$2242:$L$2765,Indicadores!$L$21) -> 19809.5 | O24: =N24/$N$23 -> 0.21455455 | P24: =SUMIFS(Ofertas!$X$2242:$X$2765,Ofertas!$T$2242:$T$2765,Indicadores!J24,Ofertas!$AG$2242:$AG$2765,Indicadores!$K$21,Ofertas!$L$2242:$L$2765,Indicadores!$L$21) -> 641.43863 | Q24: =P24/$P$23*100 -> 19.234586 | S24: PG | T24: Propuestas Ganadas | U24: =COUNTIFS(Ofertas!$T$2242:$T$2765,Indicadores!S24,Ofertas!$AG$2242:$AG$2765,$T$21,Ofertas!$L$2242:$L$2765,Indicadores!$U$21) -> 1 | V24: =U24/$U$23*100 -> 12.5 | W24: =SUMIFS(Ofertas!$W$2242:$W$2765,Ofertas!$T$2242:$T$2765,Indicadores!S24,Ofertas!$AG$2242:$AG$2765,Indicadores!$T$21,Ofertas!$L$2242:$L$2765,Indicadores!$U$21) -> 625 | X24: =W24/$W$23 -> 0.017081637 | Y24: =SUMIFS(Ofertas!$X$2242:$X$2765,Ofertas!$T$2242:$T$2765,Indicadores!S24,Ofertas!$AG$2242:$AG$2765,Indicadores!$T$21,Ofertas!$L$2242:$L$2765,Indicadores!$U$21) -> 26.7975 | Z24: =Y24/$Y$23*100 -> 2.581972
A25: PP | B25: Propuestas Perdidas | C25: =COUNTIFS(Ofertas!$T$2242:$T$2765,Indicadores!A25,Ofertas!$AG$2242:$AG$2765,$B$21) -> 37 | D25: =C25/$C$23 -> 0.61666667 | E25: =SUMIFS(Ofertas!$W$2242:$W$2765,Ofertas!$T$2242:$T$2765,Indicadores!A25,Ofertas!$AG$2242:$AG$2765,Indicadores!$B$21) -> 108483 | F25: =E25/$E$23 -> 0.84149165 | G25: =SUMIFS(Ofertas!$X$2242:$X$2765,Ofertas!$T$2242:$T$2765,Indicadores!A25,Ofertas!$AG$2242:$AG$2765,Indicadores!$B$21) -> 3704.4523 | H25: =G25/$G$23 -> 0.84717957 | J25: PP | K25: Propuestas Perdidas | L25: =COUNTIFS(Ofertas!$T$2242:$T$2765,Indicadores!J25,Ofertas!$AG$2242:$AG$2765,$K$21,Ofertas!$L$2242:$L$2765,Indicadores!$L$21) -> 30 | M25: =L25/$L$23*100 -> 57.692308 | N25: =SUMIFS(Ofertas!$W$2242:$W$2765,Ofertas!$T$2242:$T$2765,Indicadores!J25,Ofertas!$AG$2242:$AG$2765,Indicadores!$K$21,Ofertas!$L$2242:$L$2765,Indicadores!$L$21) -> 72519 | O25: =N25/$N$23*100 -> 78.544545 | P25: =SUMIFS(Ofertas!$X$2242:$X$2765,Ofertas!$T$2242:$T$2765,Indicadores!J25,Ofertas!$AG$2242:$AG$2765,Indicadores!$K$21,Ofertas!$L$2242:$L$2765,Indicadores!$L$21) -> 2693.3803 | Q25: =P25/$P$23*100 -> 80.765414 | S25: PP | T25: Propuestas Perdidas | U25: =COUNTIFS(Ofertas!$T$2242:$T$2765,Indicadores!S25,Ofertas!$AG$2242:$AG$2765,$T$21,Ofertas!$L$2242:$L$2765,Indicadores!$U$21) -> 7 | V25: =U25/$U$23*100 -> 87.5 | W25: =SUMIFS(Ofertas!$W$2242:$W$2765,Ofertas!$T$2242:$T$2765,Indicadores!S25,Ofertas!$AG$2242:$AG$2765,Indicadores!$T$21,Ofertas!$L$2242:$L$2765,Indicadores!$U$21) -> 35964 | X25: =W25/$W$23*100 -> 98.291836 | Y25: =SUMIFS(Ofertas!$X$2242:$X$2765,Ofertas!$T$2242:$T$2765,Indicadores!S25,Ofertas!$AG$2242:$AG$2765,Indicadores!$T$21,Ofertas!$L$2242:$L$2765,Indicadores!$U$21) -> 1011.072 | Z25: =Y25/$Y$23*100 -> 97.418028
A26: PD | B26: Propuestas Desiertas | C26: =COUNTIFS(Ofertas!$T$2242:$T$2765,Indicadores!A26,Ofertas!$AG$2242:$AG$2765,$B$21) -> 0 | D26: =C26/$C$23 -> 0 | E26: =SUMIFS(Ofertas!$W$2242:$W$2765,Ofertas!$T$2242:$T$2765,Indicadores!A26,Ofertas!$AG$2242:$AG$2765,Indicadores!$B$21) -> 0 | F26: =E26/$E$23 -> 0 | G26: =SUMIFS(Ofertas!$X$2242:$X$2765,Ofertas!$T$2242:$T$2765,Indicadores!A26,Ofertas!$AG$2242:$AG$2765,Indicadores!$B$21) -> 0 | H26: =G26/$G$23 -> 0 | J26: PD | K26: Propuestas Desiertas | L26: =COUNTIFS(Ofertas!$T$2242:$T$2765,Indicadores!J26,Ofertas!$AG$2242:$AG$2765,$K$21,Ofertas!$L$2242:$L$2765,Indicadores!$L$21) -> 0 | M26: =L26/$L$23*100 -> 0 | N26: =SUMIFS(Ofertas!$W$2242:$W$2765,Ofertas!$T$2242:$T$2765,Indicadores!J26,Ofertas!$AG$2242:$AG$2765,Indicadores!$K$21,Ofertas!$L$2242:$L$2765,Indicadores!$L$21) -> 0 | O26: =N26/$N$23*100 -> 0 | P26: =SUMIFS(Ofertas!$X$2242:$X$2765,Ofertas!$T$2242:$T$2765,Indicadores!J26,Ofertas!$AG$2242:$AG$2765,Indicadores!$K$21,Ofertas!$L$2242:$L$2765,Indicadores!$L$21) -> 0 | Q26: =P26/$P$23*100 -> 0 | S26: PD | T26: Propuestas Desiertas | U26: =COUNTIFS(Ofertas!$T$2242:$T$2765,Indicadores!S26,Ofertas!$AG$2242:$AG$2765,$T$21,Ofertas!$L$2242:$L$2765,Indicadores!$U$21) -> 0 | V26: =U26/$U$23*100 -> 0 | W26: =SUMIFS(Ofertas!$W$2242:$W$2765,Ofertas!$T$2242:$T$2765,Indicadores!S26,Ofertas!$AG$2242:$AG$2765,Indicadores!$T$21,Ofertas!$L$2242:$L$2765,Indicadores!$U$21) -> 0 | X26: =W26/$W$23*100 -> 0 | Y26: =SUMIFS(Ofertas!$X$2242:$X$2765,Ofertas!$T$2242:$T$2765,Indicadores!S26,Ofertas!$AG$2242:$AG$2765,Indicadores!$T$21,Ofertas!$L$2242:$L$2765,Indicadores!$U$21) -> 0 | Z26: =Y26/$Y$23*100 -> 0
A27: DP | B27: Decisión del Cliente Pendiente | C27: =COUNTIFS(Ofertas!$T$2242:$T$2765,Indicadores!A27,Ofertas!$AG$2242:$AG$2765,$B$21) -> 0 | D27: =C27/$C$23 -> 0 | E27: =SUMIFS(Ofertas!$W$2242:$W$2765,Ofertas!$T$2242:$T$2765,Indicadores!A27,Ofertas!$AG$2242:$AG$2765,Indicadores!$B$21) -> 0 | F27: =E27/$E$23 -> 0 | G27: =SUMIFS(Ofertas!$X$2242:$X$2765,Ofertas!$T$2242:$T$2765,Indicadores!A27,Ofertas!$AG$2242:$AG$2765,Indicadores!$B$21) -> 0 | H27: =G27/$G$23 -> 0 | J27: DP | K27: Decisión del Cliente Pendiente | L27: =COUNTIFS(Ofertas!$T$2242:$T$2765,Indicadores!J27,Ofertas!$AG$2242:$AG$2765,$K$21,Ofertas!$L$2242:$L$2765,Indicadores!$L$21) -> 0 | M27: =L27/$L$23*100 -> 0 | N27: =SUMIFS(Ofertas!$W$2242:$W$2765,Ofertas!$T$2242:$T$2765,Indicadores!J27,Ofertas!$AG$2242:$AG$2765,Indicadores!$K$21,Ofertas!$L$2242:$L$2765,Indicadores!$L$21) -> 0 | O27: =N27/$N$23*100 -> 0 | P27: =SUMIFS(Ofertas!$X$2242:$X$2765,Ofertas!$T$2242:$T$2765,Indicadores!J27,Ofertas!$AG$2242:$AG$2765,Indicadores!$K$21,Ofertas!$L$2242:$L$2765,Indicadores!$L$21) -> 0 | Q27: =P27/$P$23*100 -> 0 | S27: DP | T27: Decisión del Cliente Pendiente | U27: =COUNTIFS(Ofertas!$T$2242:$T$2765,Indicadores!S27,Ofertas!$AG$2242:$AG$2765,$T$21,Ofertas!$L$2242:$L$2765,Indicadores!$U$21) -> 0 | V27: =U27/$U$23*100 -> 0 | W27: =SUMIFS(Ofertas!$W$2242:$W$2765,Ofertas!$T$2242:$T$2765,Indicadores!S27,Ofertas!$AG$2242:$AG$2765,Indicadores!$T$21,Ofertas!$L$2242:$L$2765,Indicadores!$U$21) -> 0 | X27: =W27/$W$23*100 -> 0 | Y27: =SUMIFS(Ofertas!$X$2242:$X$2765,Ofertas!$T$2242:$T$2765,Indicadores!S27,Ofertas!$AG$2242:$AG$2765,Indicadores!$T$21,Ofertas!$L$2242:$L$2765,Indicadores!$U$21) -> 0 | Z27: =Y27/$Y$23*100 -> 0
A28: EP | B28: Propuestas en Preparación | C28: =COUNTIFS(Ofertas!$T$2242:$T$2765,Indicadores!A28,Ofertas!$AG$2242:$AG$2765,$B$21) -> 0 | D28: =C28/$C$23 -> 0 | E28: =SUMIFS(Ofertas!$W$2242:$W$2765,Ofertas!$T$2242:$T$2765,Indicadores!A28,Ofertas!$AG$2242:$AG$2765,Indicadores!$B$21) -> 0 | F28: =E28/$E$23 -> 0 | G28: =SUMIFS(Ofertas!$X$2242:$X$2765,Ofertas!$T$2242:$T$2765,Indicadores!A28,Ofertas!$AG$2242:$AG$2765,Indicadores!$B$21) -> 0 | H28: =G28/$G$23 -> 0 | J28: EP | K28: Propuestas en Preparación | L28: =COUNTIFS(Ofertas!$T$2242:$T$2765,Indicadores!J28,Ofertas!$AG$2242:$AG$2765,$K$21,Ofertas!$L$2242:$L$2765,Indicadores!$L$21) -> 0 | M28: =L28/$L$23*100 -> 0 | N28: =SUMIFS(Ofertas!$W$2242:$W$2765,Ofertas!$T$2242:$T$2765,Indicadores!J28,Ofertas!$AG$2242:$AG$2765,Indicadores!$K$21,Ofertas!$L$2242:$L$2765,Indicadores!$L$21) -> 0 | O28: =N28/$N$23*100 -> 0 | P28: =SUMIFS(Ofertas!$X$2242:$X$2765,Ofertas!$T$2242:$T$2765,Indicadores!J28,Ofertas!$AG$2242:$AG$2765,Indicadores!$K$21,Ofertas!$L$2242:$L$2765,Indicadores!$L$21) -> 0 | Q28: =P28/$P$23*100 -> 0 | S28: EP | T28: Propuestas en Preparación | U28: =COUNTIFS(Ofertas!$T$2242:$T$2765,Indicadores!S28,Ofertas!$AG$2242:$AG$2765,$T$21,Ofertas!$L$2242:$L$2765,Indicadores!$U$21) -> 0 | V28: =U28/$U$23*100 -> 0 | W28: =SUMIFS(Ofertas!$W$2242:$W$2765,Ofertas!$T$2242:$T$2765,Indicadores!S28,Ofertas!$AG$2242:$AG$2765,Indicadores!$T$21,Ofertas!$L$2242:$L$2765,Indicadores!$U$21) -> 0 | X28: =W28/$W$23*100 -> 0 | Y28: =SUMIFS(Ofertas!$X$2242:$X$2765,Ofertas!$T$2242:$T$2765,Indicadores!S28,Ofertas!$AG$2242:$AG$2765,Indicadores!$T$21,Ofertas!$L$2242:$L$2765,Indicadores!$U$21) -> 0 | Z28: =Y28/$Y$23*100 -> 0
B30: 2013 | K30: 2013 | L30: ND | M30: NEGOCIACIÓN DIRECTA | T30: 2013 | U30: LM | V30: LICITACIÓN MÚLTIPLE
B31: STATUS (a la fecha) | C31: Can. | D31: % | E31: hh Lic. | F31: % hh | G31: M$ Lic. | H31: % M$ | K31: STATUS (a la fecha) | L31: Can. | M31: % | N31: hh Lic. | O31: % hh | P31: M$ Lic. | Q31: % M$ | T31: STATUS (a la fecha) | U31: Can. | V31: % | W31: hh Lic. | X31: % hh | Y31: M$ Lic. | Z31: % M$
B32: Totales | C32: =SUM(C33:C37) -> 69 | D32: =SUM(D33:D37) -> 1 | E32: =SUM(E33:E37) -> 96438.5 | F32: =SUM(F33:F37) -> 1 | G32: =SUM(G33:G37) -> 3530.496 | H32: =SUM(H33:H37) -> 1 | K32: Totales | L32: =SUM(L33:L37) -> 60 | M32: =SUM(M33:M37) -> 100 | N32: =SUM(N33:N37) -> 63384.5 | O32: =SUM(O33:O37) -> 82.85741 | P32: =SUM(P33:P37) -> 2473.5656 | Q32: =SUM(Q33:Q37) -> 100 | T32: Totales | U32: =SUM(U33:U37) -> 9 | V32: =SUM(V33:V37) -> 100 | W32: =SUM(W33:W37) -> 33054 | X32: =SUM(X33:X37) -> 98.092122 | Y32: =SUM(Y33:Y37) -> 1056.9304 | Z32: =SUM(Z33:Z37) -> 100
A33: PG | B33: Propuestas Ganadas | C33: =COUNTIFS(Ofertas!$T$2242:$T$2765,Indicadores!A33,Ofertas!$AG$2242:$AG$2765,$B$30) -> 21 | D33: =C33/$C$32 -> 0.30434783 | E33: =SUMIFS(Ofertas!$W$2242:$W$2765,Ofertas!$T$2242:$T$2765,Indicadores!A33,Ofertas!$AG$2242:$AG$2765,Indicadores!$B$30) -> 11612.5 | F33: =E33/$E$32 -> 0.12041353 | G33: =SUMIFS(Ofertas!$X$2242:$X$2765,Ofertas!$T$2242:$T$2765,Indicadores!A33,Ofertas!$AG$2242:$AG$2765,Indicadores!$B$30) -> 309.23764 | H33: =G33/$G$32 -> 0.087590422 | J33: PG | K33: Propuestas Ganadas | L33: =COUNTIFS(Ofertas!$T$2242:$T$2765,Indicadores!J33,Ofertas!$AG$2242:$AG$2765,$K$30,Ofertas!$L$2242:$L$2765,Indicadores!$L$30) -> 20 | M33: =L33/$L$32*100 -> 33.333333 | N33: =SUMIFS(Ofertas!$W$2242:$W$2765,Ofertas!$T$2242:$T$2765,Indicadores!J33,Ofertas!$AG$2242:$AG$2765,Indicadores!$K$30,Ofertas!$L$2242:$L$2765,Indicadores!$L$30) -> 10975.5 | O33: =N33/$N$32 -> 0.17315748 | P33: =SUMIFS(Ofertas!$X$2242:$X$2765,Ofertas!$T$2242:$T$2765,Indicadores!J33,Ofertas!$AG$2242:$AG$2765,Indicadores!$K$30,Ofertas!$L$2242:$L$2765,Indicadores!$L$30) -> 281.94264 | Q33: =P33/$P$32*100 -> 11.398228 | S33: PG | T33: Propuestas Ganadas | U33: =COUNTIFS(Ofertas!$T$2242:$T$2765,Indicadores!S33,Ofertas!$AG$2242:$AG$2765,$T$30,Ofertas!$L$2242:$L$2765,Indicadores!$U$30) -> 1 | V33: =U33/$U$32*100 -> 11.111111 | W33: =SUMIFS(Ofertas!$W$2242:$W$2765,Ofertas!$T$2242:$T$2765,Indicadores!S33,Ofertas!$AG$2242:$AG$2765,Indicadores!$T$30,Ofertas!$L$2242:$L$2765,Indicadores!$U$30) -> 637 | X33: =W33/$W$32 -> 0.019271495 | Y33: =SUMIFS(Ofertas!$X$2242:$X$2765,Ofertas!$T$2242:$T$2765,Indicadores!S33,Ofertas!$AG$2242:$AG$2765,Indicadores!$T$30,Ofertas!$L$2242:$L$2765,Indicadores!$U$30) -> 27.295 | Z33: =Y33/$Y$32*100 -> 2.5824784
A34: PP | B34: Propuestas Perdidas | C34: =COUNTIFS(Ofertas!$T$2242:$T$2765,Indicadores!A34,Ofertas!$AG$2242:$AG$2765,$B$30) -> 48 | D34: =C34/$C$32 -> 0.69565217 | E34: =SUMIFS(Ofertas!$W$2242:$W$2765,Ofertas!$T$2242:$T$2765,Indicadores!A34,Ofertas!$AG$2242:$AG$2765,Indicadores!$B$30) -> 84826 | F34: =E34/$E$32 -> 0.87958647 | G34: =SUMIFS(Ofertas!$X$2242:$X$2765,Ofertas!$T$2242:$T$2765,Indicadores!A34,Ofertas!$AG$2242:$AG$2765,Indicadores!$B$30) -> 3221.2584 | H34: =G34/$G$32 -> 0.91240958 | J34: PP | K34: Propuestas Perdidas | L34: =COUNTIFS(Ofertas!$T$2242:$T$2765,Indicadores!J34,Ofertas!$AG$2242:$AG$2765,$K$30,Ofertas!$L$2242:$L$2765,Indicadores!$L$30) -> 40 | M34: =L34/$L$32*100 -> 66.666667 | N34: =SUMIFS(Ofertas!$W$2242:$W$2765,Ofertas!$T$2242:$T$2765,Indicadores!J34,Ofertas!$AG$2242:$AG$2765,Indicadores!$K$30,Ofertas!$L$2242:$L$2765,Indicadores!$L$30) -> 52409 | O34: =N34/$N$32*100 -> 82.684252 | P34: =SUMIFS(Ofertas!$X$2242:$X$2765,Ofertas!$T$2242:$T$2765,Indicadores!J34,Ofertas!$AG$2242:$AG$2765,Indicadores!$K$30,Ofertas!$L$2242:$L$2765,Indicadores!$L$30) -> 2191.623 | Q34: =P34/$P$32*100 -> 88.601772 | S34: PP | T34: Propuestas Perdidas | U34: =COUNTIFS(Ofertas!$T$2242:$T$2765,Indicadores!S34,Ofertas!$AG$2242:$AG$2765,$T$30,Ofertas!$L$2242:$L$2765,Indicadores!$U$30) -> 8 | V34: =U34/$U$32*100 -> 88.888889 | W34: =SUMIFS(Ofertas!$W$2242:$W$2765,Ofertas!$T$2242:$T$2765,Indicadores!S34,Ofertas!$AG$2242:$AG$2765,Indicadores!$T$30,Ofertas!$L$2242:$L$2765,Indicadores!$U$30) -> 32417 | X34: =W34/$W$32*100 -> 98.07285 | Y34: =SUMIFS(Ofertas!$X$2242:$X$2765,Ofertas!$T$2242:$T$2765,Indicadores!S34,Ofertas!$AG$2242:$AG$2765,Indicadores!$T$30,Ofertas!$L$2242:$L$2765,Indicadores!$U$30) -> 1029.6354 | Z34: =Y34/$Y$32*100 -> 97.417522
A35: PD | B35: Propuestas Desiertas | C35: =COUNTIFS(Ofertas!$T$2242:$T$2765,Indicadores!A35,Ofertas!$AG$2242:$AG$2765,$B$30) -> 0 | D35: =C35/$C$32 -> 0 | E35: =SUMIFS(Ofertas!$W$2242:$W$2765,Ofertas!$T$2242:$T$2765,Indicadores!A35,Ofertas!$AG$2242:$AG$2765,Indicadores!$B$30) -> 0 | F35: =E35/$E$32 -> 0 | G35: =SUMIFS(Ofertas!$X$2242:$X$2765,Ofertas!$T$2242:$T$2765,Indicadores!A35,Ofertas!$AG$2242:$AG$2765,Indicadores!$B$30) -> 0 | H35: =G35/$G$32 -> 0 | J35: PD | K35: Propuestas Desiertas | L35: =COUNTIFS(Ofertas!$T$2242:$T$2765,Indicadores!J35,Ofertas!$AG$2242:$AG$2765,$K$30,Ofertas!$L$2242:$L$2765,Indicadores!$L$30) -> 0 | M35: =L35/$L$32*100 -> 0 | N35: =SUMIFS(Ofertas!$W$2242:$W$2765,Ofertas!$T$2242:$T$2765,Indicadores!J35,Ofertas!$AG$2242:$AG$2765,Indicadores!$K$30,Ofertas!$L$2242:$L$2765,Indicadores!$L$30) -> 0 | O35: =N35/$N$32*100 -> 0 | P35: =SUMIFS(Ofertas!$X$2242:$X$2765,Ofertas!$T$2242:$T$2765,Indicadores!J35,Ofertas!$AG$2242:$AG$2765,Indicadores!$K$30,Ofertas!$L$2242:$L$2765,Indicadores!$L$30) -> 0 | Q35: =P35/$P$32*100 -> 0 | S35: PD | T35: Propuestas Desiertas | U35: =COUNTIFS(Ofertas!$T$2242:$T$2765,Indicadores!S35,Ofertas!$AG$2242:$AG$2765,$T$30,Ofertas!$L$2242:$L$2765,Indicadores!$U$30) -> 0 | V35: =U35/$U$32*100 -> 0 | W35: =SUMIFS(Ofertas!$W$2242:$W$2765,Ofertas!$T$2242:$T$2765,Indicadores!S35,Ofertas!$AG$2242:$AG$2765,Indicadores!$T$30,Ofertas!$L$2242:$L$2765,Indicadores!$U$30) -> 0 | X35: =W35/$W$32*100 -> 0 | Y35: =SUMIFS(Ofertas!$X$2242:$X$2765,Ofertas!$T$2242:$T$2765,Indicadores!S35,Ofertas!$AG$2242:$AG$2765,Indicadores!$T$30,Ofertas!$L$2242:$L$2765,Indicadores!$U$30) -> 0 | Z35: =Y35/$Y$32*100 -> 0
A36: DP | B36: Decisión del Cliente Pendiente | C36: =COUNTIFS(Ofertas!$T$2242:$T$2765,Indicadores!A36,Ofertas!$AG$2242:$AG$2765,$B$30) -> 0 | D36: =C36/$C$32 -> 0 | E36: =SUMIFS(Ofertas!$W$2242:$W$2765,Ofertas!$T$2242:$T$2765,Indicadores!A36,Ofertas!$AG$2242:$AG$2765,Indicadores!$B$30) -> 0 | F36: =E36/$E$32 -> 0 | G36: =SUMIFS(Ofertas!$X$2242:$X$2765,Ofertas!$T$2242:$T$2765,Indicadores!A36,Ofertas!$AG$2242:$AG$2765,Indicadores!$B$30) -> 0 | H36: =G36/$G$32 -> 0 | J36: DP | K36: Decisión del Cliente Pendiente | L36: =COUNTIFS(Ofertas!$T$2242:$T$2765,Indicadores!J36,Ofertas!$AG$2242:$AG$2765,$K$30,Ofertas!$L$2242:$L$2765,Indicadores!$L$30) -> 0 | M36: =L36/$L$32*100 -> 0 | N36: =SUMIFS(Ofertas!$W$2242:$W$2765,Ofertas!$T$2242:$T$2765,Indicadores!J36,Ofertas!$AG$2242:$AG$2765,Indicadores!$K$30,Ofertas!$L$2242:$L$2765,Indicadores!$L$30) -> 0 | O36: =N36/$N$32*100 -> 0 | P36: =SUMIFS(Ofertas!$X$2242:$X$2765,Ofertas!$T$2242:$T$2765,Indicadores!J36,Ofertas!$AG$2242:$AG$2765,Indicadores!$K$30,Ofertas!$L$2242:$L$2765,Indicadores!$L$30) -> 0 | Q36: =P36/$P$32*100 -> 0 | S36: DP | T36: Decisión del Cliente Pendiente | U36: =COUNTIFS(Ofertas!$T$2242:$T$2765,Indicadores!S36,Ofertas!$AG$2242:$AG$2765,$T$30,Ofertas!$L$2242:$L$2765,Indicadores!$U$30) -> 0 | V36: =U36/$U$32*100 -> 0 | W36: =SUMIFS(Ofertas!$W$2242:$W$2765,Ofertas!$T$2242:$T$2765,Indicadores!S36,Ofertas!$AG$2242:$AG$2765,Indicadores!$T$30,Ofertas!$L$2242:$L$2765,Indicadores!$U$30) -> 0 | X36: =W36/$W$32*100 -> 0 | Y36: =SUMIFS(Ofertas!$X$2242:$X$2765,Ofertas!$T$2242:$T$2765,Indicadores!S36,Ofertas!$AG$2242:$AG$2765,Indicadores!$T$30,Ofertas!$L$2242:$L$2765,Indicadores!$U$30) -> 0 | Z36: =Y36/$Y$32*100 -> 0
A37: EP | B37: Propuestas en Preparación | C37: =COUNTIFS(Ofertas!$T$2242:$T$2765,Indicadores!A37,Ofertas!$AG$2242:$AG$2765,$B$30) -> 0 | D37: =C37/$C$32 -> 0 | E37: =SUMIFS(Ofertas!$W$2242:$W$2765,Ofertas!$T$2242:$T$2765,Indicadores!A37,Ofertas!$AG$2242:$AG$2765,Indicadores!$B$30) -> 0 | F37: =E37/$E$32 -> 0 | G37: =SUMIFS(Ofertas!$X$2242:$X$2765,Ofertas!$T$2242:$T$2765,Indicadores!A37,Ofertas!$AG$2242:$AG$2765,Indicadores!$B$30) -> 0 | H37: =G37/$G$32 -> 0 | J37: EP | K37: Propuestas en Preparación | L37: =COUNTIFS(Ofertas!$T$2242:$T$2765,Indicadores!J37,Ofertas!$AG$2242:$AG$2765,$K$30,Ofertas!$L$2242:$L$2765,Indicadores!$L$30) -> 0 | M37: =L37/$L$32*100 -> 0 | N37: =SUMIFS(Ofertas!$W$2242:$W$2765,Ofertas!$T$2242:$T$2765,Indicadores!J37,Ofertas!$AG$2242:$AG$2765,Indicadores!$K$30,Ofertas!$L$2242:$L$2765,Indicadores!$L$30) -> 0 | O37: =N37/$N$32*100 -> 0 | P37: =SUMIFS(Ofertas!$X$2242:$X$2765,Ofertas!$T$2242:$T$2765,Indicadores!J37,Ofertas!$AG$2242:$AG$2765,Indicadores!$K$30,Ofertas!$L$2242:$L$2765,Indicadores!$L$30) -> 0 | Q37: =P37/$P$32*100 -> 0 | S37: EP | T37: Propuestas en Preparación | U37: =COUNTIFS(Ofertas!$T$2242:$T$2765,Indicadores!S37,Ofertas!$AG$2242:$AG$2765,$T$30,Ofertas!$L$2242:$L$2765,Indicadores!$U$30) -> 0 | V37: =U37/$U$32*100 -> 0 | W37: =SUMIFS(Ofertas!$W$2242:$W$2765,Ofertas!$T$2242:$T$2765,Indicadores!S37,Ofertas!$AG$2242:$AG$2765,Indicadores!$T$30,Ofertas!$L$2242:$L$2765,Indicadores!$U$30) -> 0 | X37: =W37/$W$32*100 -> 0 | Y37: =SUMIFS(Ofertas!$X$2242:$X$2765,Ofertas!$T$2242:$T$2765,Indicadores!S37,Ofertas!$AG$2242:$AG$2765,Indicadores!$T$30,Ofertas!$L$2242:$L$2765,Indicadores!$U$30) -> 0 | Z37: =Y37/$Y$32*100 -> 0
B39: 2014 | K39: 2014 | L39: ND | M39: NEGOCIACIÓN DIRECTA | T39: 2014 | U39: LM | V39: LICITACIÓN MÚLTIPLE
B40: STATUS (a la fecha) | C40: Can. | D40: % | E40: hh Lic. | F40: % hh | G40: M$ Lic. | H40: % M$ | K40: STATUS (a la fecha) | L40: Can. | M40: % | N40: hh Lic. | O40: % hh | P40: M$ Lic. | Q40: % M$ | T40: STATUS (a la fecha) | U40: Can. | V40: % | W40: hh Lic. | X40: % hh | Y40: M$ Lic. | Z40: % M$
B41: Totales | C41: =SUM(C42:C46) -> 87 | D41: =SUM(D42:D46) -> 1 | E41: =SUM(E42:E46) -> 141753.5 | F41: =SUM(F42:F46) -> 1.0995676 | G41: =SUM(G42:G46) -> 5616.818 | H41: =SUM(H42:H46) -> 1 | K41: Totales | L41: =SUM(L42:L46) -> 64 | M41: =SUM(M42:M46) -> 100 | N41: =SUM(N42:N46) -> 71286.5 | O41: =SUM(O42:O46) -> 57.72816 | P41: =SUM(P42:P46) -> 2763.596 | Q41: =SUM(Q42:Q46) -> 100 | T41: Totales | U41: =SUM(U42:U46) -> 23 | V41: =SUM(V42:V46) -> 100 | W41: =SUM(W42:W46) -> 70467 | X41: =SUM(X42:X46) -> 99.03904 | Y41: =SUM(Y42:Y46) -> 2853.222 | Z41: =SUM(Z42:Z46) -> 100
A42: PG | B42: Propuestas Ganadas | C42: =COUNTIFS(Ofertas!$T$2242:$T$2765,Indicadores!A42,Ofertas!$AG$2242:$AG$2765,$B$39) -> 33 | D42: =C42/$C$41 -> 0.37931034 | E42: =SUMIFS(Ofertas!$W$2242:$W$2765,Ofertas!$T$2242:$T$2765,Indicadores!A42,Ofertas!$AG$2242:$AG$2765,Indicadores!$B$39) -> 31122.5 | F42: =E42/$E$23 -> 0.24141408 | G42: =SUMIFS(Ofertas!$X$2242:$X$2765,Ofertas!$T$2242:$T$2765,Indicadores!A42,Ofertas!$AG$2242:$AG$2765,Indicadores!$B$39) -> 1237.1612 | H42: =G42/$G$41 -> 0.22026016 | J42: PG | K42: Propuestas Ganadas | L42: =COUNTIFS(Ofertas!$T$2242:$T$2765,Indicadores!J42,Ofertas!$AG$2242:$AG$2765,$K$39,Ofertas!$L$2242:$L$2765,Indicadores!$L$39) -> 30 | M42: =L42/$L$41*100 -> 46.875 | N42: =SUMIFS(Ofertas!$W$2242:$W$2765,Ofertas!$T$2242:$T$2765,Indicadores!J42,Ofertas!$AG$2242:$AG$2765,Indicadores!$K$39,Ofertas!$L$2242:$L$2765,Indicadores!$L$39) -> 30438.5 | O42: =N42/$N$41 -> 0.42698828 | P42: =SUMIFS(Ofertas!$X$2242:$X$2765,Ofertas!$T$2242:$T$2765,Indicadores!J42,Ofertas!$AG$2242:$AG$2765,Indicadores!$K$39,Ofertas!$L$2242:$L$2765,Indicadores!$L$39) -> 1209.9052 | Q42: =P42/$P$41*100 -> 43.780103 | S42: PG | T42: Propuestas Ganadas | U42: =COUNTIFS(Ofertas!$T$2242:$T$2765,Indicadores!S42,Ofertas!$AG$2242:$AG$2765,$T$39,Ofertas!$L$2242:$L$2765,Indicadores!$U$39) -> 3 | V42: =U42/$U$41*100 -> 13.043478 | W42: =SUMIFS(Ofertas!$W$2242:$W$2765,Ofertas!$T$2242:$T$2765,Indicadores!S42,Ofertas!$AG$2242:$AG$2765,Indicadores!$T$39,Ofertas!$L$2242:$L$2765,Indicadores!$U$39) -> 684 | X42: =W42/$W$41 -> 0.0097066712 | Y42: =SUMIFS(Ofertas!$X$2242:$X$2765,Ofertas!$T$2242:$T$2765,Indicadores!S42,Ofertas!$AG$2242:$AG$2765,Indicadores!$T$39,Ofertas!$L$2242:$L$2765,Indicadores!$U$39) -> 27.25604 | Z42: =Y42/$Y$41*100 -> 0.95527232
A43: PP | B43: Propuestas Perdidas | C43: =COUNTIFS(Ofertas!$T$2242:$T$2765,Indicadores!A43,Ofertas!$AG$2242:$AG$2765,$B$39) -> 54 | D43: =C43/$C$41 -> 0.62068966 | E43: =SUMIFS(Ofertas!$W$2242:$W$2765,Ofertas!$T$2242:$T$2765,Indicadores!A43,Ofertas!$AG$2242:$AG$2765,Indicadores!$B$39) -> 110631 | F43: =E43/$E$23 -> 0.85815347 | G43: =SUMIFS(Ofertas!$X$2242:$X$2765,Ofertas!$T$2242:$T$2765,Indicadores!A43,Ofertas!$AG$2242:$AG$2765,Indicadores!$B$39) -> 4379.6568 | H43: =G43/$G$41 -> 0.77973984 | J43: PP | K43: Propuestas Perdidas | L43: =COUNTIFS(Ofertas!$T$2242:$T$2765,Indicadores!J43,Ofertas!$AG$2242:$AG$2765,$K$39,Ofertas!$L$2242:$L$2765,Indicadores!$L$39) -> 34 | M43: =L43/$L$41*100 -> 53.125 | N43: =SUMIFS(Ofertas!$W$2242:$W$2765,Ofertas!$T$2242:$T$2765,Indicadores!J43,Ofertas!$AG$2242:$AG$2765,Indicadores!$K$39,Ofertas!$L$2242:$L$2765,Indicadores!$L$39) -> 40848 | O43: =N43/$N$41*100 -> 57.301172 | P43: =SUMIFS(Ofertas!$X$2242:$X$2765,Ofertas!$T$2242:$T$2765,Indicadores!J43,Ofertas!$AG$2242:$AG$2765,Indicadores!$K$39,Ofertas!$L$2242:$L$2765,Indicadores!$L$39) -> 1553.6908 | Q43: =P43/$P$41*100 -> 56.219897 | S43: PP | T43: Propuestas Perdidas | U43: =COUNTIFS(Ofertas!$T$2242:$T$2765,Indicadores!S43,Ofertas!$AG$2242:$AG$2765,$T$39,Ofertas!$L$2242:$L$2765,Indicadores!$U$39) -> 20 | V43: =U43/$U$41*100 -> 86.956522 | W43: =SUMIFS(Ofertas!$W$2242:$W$2765,Ofertas!$T$2242:$T$2765,Indicadores!S43,Ofertas!$AG$2242:$AG$2765,Indicadores!$T$39,Ofertas!$L$2242:$L$2765,Indicadores!$U$39) -> 69783 | X43: =W43/$W$41*100 -> 99.029333 | Y43: =SUMIFS(Ofertas!$X$2242:$X$2765,Ofertas!$T$2242:$T$2765,Indicadores!S43,Ofertas!$AG$2242:$AG$2765,Indicadores!$T$39,Ofertas!$L$2242:$L$2765,Indicadores!$U$39) -> 2825.966 | Z43: =Y43/$Y$41*100 -> 99.044728
A44: PD | B44: Propuestas Desiertas | C44: =COUNTIFS(Ofertas!$T$2242:$T$2765,Indicadores!A44,Ofertas!$AG$2242:$AG$2765,$B$39) -> 0 | D44: =C44/$C$41 -> 0 | E44: =SUMIFS(Ofertas!$W$2242:$W$2765,Ofertas!$T$2242:$T$2765,Indicadores!A44,Ofertas!$AG$2242:$AG$2765,Indicadores!$B$39) -> 0 | F44: =E44/$E$23 -> 0 | G44: =SUMIFS(Ofertas!$X$2242:$X$2765,Ofertas!$T$2242:$T$2765,Indicadores!A44,Ofertas!$AG$2242:$AG$2765,Indicadores!$B$39) -> 0 | H44: =G44/$G$41 -> 0 | J44: PD | K44: Propuestas Desiertas | L44: =COUNTIFS(Ofertas!$T$2242:$T$2765,Indicadores!J44,Ofertas!$AG$2242:$AG$2765,$K$39,Ofertas!$L$2242:$L$2765,Indicadores!$L$39) -> 0 | M44: =L44/$L$41*100 -> 0 | N44: =SUMIFS(Ofertas!$W$2242:$W$2765,Ofertas!$T$2242:$T$2765,Indicadores!J44,Ofertas!$AG$2242:$AG$2765,Indicadores!$K$39,Ofertas!$L$2242:$L$2765,Indicadores!$L$39) -> 0 | O44: =N44/$N$41*100 -> 0 | P44: =SUMIFS(Ofertas!$X$2242:$X$2765,Ofertas!$T$2242:$T$2765,Indicadores!J44,Ofertas!$AG$2242:$AG$2765,Indicadores!$K$39,Ofertas!$L$2242:$L$2765,Indicadores!$L$39) -> 0 | Q44: =P44/$P$41*100 -> 0 | S44: PD | T44: Propuestas Desiertas | U44: =COUNTIFS(Ofertas!$T$2242:$T$2765,Indicadores!S44,Ofertas!$AG$2242:$AG$2765,$T$39,Ofertas!$L$2242:$L$2765,Indicadores!$U$39) -> 0 | V44: =U44/$U$41*100 -> 0 | W44: =SUMIFS(Ofertas!$W$2242:$W$2765,Ofertas!$T$2242:$T$2765,Indicadores!S44,Ofertas!$AG$2242:$AG$2765,Indicadores!$T$39,Ofertas!$L$2242:$L$2765,Indicadores!$U$39) -> 0 | X44: =W44/$W$41*100 -> 0 | Y44: =SUMIFS(Ofertas!$X$2242:$X$2765,Ofertas!$T$2242:$T$2765,Indicadores!S44,Ofertas!$AG$2242:$AG$2765,Indicadores!$T$39,Ofertas!$L$2242:$L$2765,Indicadores!$U$39) -> 0 | Z44: =Y44/$Y$41*100 -> 0
A45: DP | B45: Decisión del Cliente Pendiente | C45: =COUNTIFS(Ofertas!$T$2242:$T$2765,Indicadores!A45,Ofertas!$AG$2242:$AG$2765,$B$39) -> 0 | D45: =C45/$C$41 -> 0 | E45: =SUMIFS(Ofertas!$W$2242:$W$2765,Ofertas!$T$2242:$T$2765,Indicadores!A45,Ofertas!$AG$2242:$AG$2765,Indicadores!$B$39) -> 0 | F45: =E45/$E$23 -> 0 | G45: =SUMIFS(Ofertas!$X$2242:$X$2765,Ofertas!$T$2242:$T$2765,Indicadores!A45,Ofertas!$AG$2242:$AG$2765,Indicadores!$B$39) -> 0 | H45: =G45/$G$41 -> 0 | J45: DP | K45: Decisión del Cliente Pendiente | L45: =COUNTIFS(Ofertas!$T$2242:$T$2765,Indicadores!J45,Ofertas!$AG$2242:$AG$2765,$K$39,Ofertas!$L$2242:$L$2765,Indicadores!$L$39) -> 0 | M45: =L45/$L$41*100 -> 0 | N45: =SUMIFS(Ofertas!$W$2242:$W$2765,Ofertas!$T$2242:$T$2765,Indicadores!J45,Ofertas!$AG$2242:$AG$2765,Indicadores!$K$39,Ofertas!$L$2242:$L$2765,Indicadores!$L$39) -> 0 | O45: =N45/$N$41*100 -> 0 | P45: =SUMIFS(Ofertas!$X$2242:$X$2765,Ofertas!$T$2242:$T$2765,Indicadores!J45,Ofertas!$AG$2242:$AG$2765,Indicadores!$K$39,Ofertas!$L$2242:$L$2765,Indicadores!$L$39) -> 0 | Q45: =P45/$P$41*100 -> 0 | S45: DP | T45: Decisión del Cliente Pendiente | U45: =COUNTIFS(Ofertas!$T$2242:$T$2765,Indicadores!S45,Ofertas!$AG$2242:$AG$2765,$T$39,Ofertas!$L$2242:$L$2765,Indicadores!$U$39) -> 0 | V45: =U45/$U$41*100 -> 0 | W45: =SUMIFS(Ofertas!$W$2242:$W$2765,Ofertas!$T$2242:$T$2765,Indicadores!S45,Ofertas!$AG$2242:$AG$2765,Indicadores!$T$39,Ofertas!$L$2242:$L$2765,Indicadores!$U$39) -> 0 | X45: =W45/$W$41*100 -> 0 | Y45: =SUMIFS(Ofertas!$X$2242:$X$2765,Ofertas!$T$2242:$T$2765,Indicadores!S45,Ofertas!$AG$2242:$AG$2765,Indicadores!$T$39,Ofertas!$L$2242:$L$2765,Indicadores!$U$39) -> 0 | Z45: =Y45/$Y$41*100 -> 0
A46: EP | B46: Propuestas en Preparación | C46: =COUNTIFS(Ofertas!$T$2242:$T$2765,Indicadores!A46,Ofertas!$AG$2242:$AG$2765,$B$39) -> 0 | D46: =C46/$C$41 -> 0 | E46: =SUMIFS(Ofertas!$W$2242:$W$2765,Ofertas!$T$2242:$T$2765,Indicadores!A46,Ofertas!$AG$2242:$AG$2765,Indicadores!$B$39) -> 0 | F46: =E46/$E$23 -> 0 | G46: =SUMIFS(Ofertas!$X$2242:$X$2765,Ofertas!$T$2242:$T$2765,Indicadores!A46,Ofertas!$AG$2242:$AG$2765,Indicadores!$B$39) -> 0 | H46: =G46/$G$41 -> 0 | J46: EP | K46: Propuestas en Preparación | L46: =COUNTIFS(Ofertas!$T$2242:$T$2765,Indicadores!J46,Ofertas!$AG$2242:$AG$2765,$K$39,Ofertas!$L$2242:$L$2765,Indicadores!$L$39) -> 0 | M46: =L46/$L$41*100 -> 0 | N46: =SUMIFS(Ofertas!$W$2242:$W$2765,Ofertas!$T$2242:$T$2765,Indicadores!J46,Ofertas!$AG$2242:$AG$2765,Indicadores!$K$39,Ofertas!$L$2242:$L$2765,Indicadores!$L$39) -> 0 | O46: =N46/$N$41*100 -> 0 | P46: =SUMIFS(Ofertas!$X$2242:$X$2765,Ofertas!$T$2242:$T$2765,Indicadores!J46,Ofertas!$AG$2242:$AG$2765,Indicadores!$K$39,Ofertas!$L$2242:$L$2765,Indicadores!$L$39) -> 0 | Q46: =P46/$P$41*100 -> 0 | S46: EP | T46: Propuestas en Preparación | U46: =COUNTIFS(Ofertas!$T$2242:$T$2765,Indicadores!S46,Ofertas!$AG$2242:$AG$2765,$T$39,Ofertas!$L$2242:$L$2765,Indicadores!$U$39) -> 0 | V46: =U46/$U$41*100 -> 0 | W46: =SUMIFS(Ofertas!$W$2242:$W$2765,Ofertas!$T$2242:$T$2765,Indicadores!S46,Ofertas!$AG$2242:$AG$2765,Indicadores!$T$39,Ofertas!$L$2242:$L$2765,Indicadores!$U$39) -> 0 | X46: =W46/$W$41*100 -> 0 | Y46: =SUMIFS(Ofertas!$X$2242:$X$2765,Ofertas!$T$2242:$T$2765,Indicadores!S46,Ofertas!$AG$2242:$AG$2765,Indicadores!$T$39,Ofertas!$L$2242:$L$2765,Indicadores!$U$39) -> 0 | Z46: =Y46/$Y$41*100 -> 0
B48: 2015 | K48: 2015 | L48: ND | M48: NEGOCIACIÓN DIRECTA | T48: 2015 | U48: LM | V48: LICITACIÓN MÚLTIPLE
B49: STATUS (a la fecha) | C49: Can. | D49: % | E49: hh Lic. | F49: % hh | G49: M$ Lic. | H49: % M$ | K49: STATUS (a la fecha) | L49: Can. | M49: % | N49: hh Lic. | O49: % hh | P49: M$ Lic. | Q49: % M$ | T49: STATUS (a la fecha) | U49: Can. | V49: % | W49: hh Lic. | X49: % hh | Y49: M$ Lic. | Z49: % M$
B50: Totales | C50: =SUM(C51:C55) -> 131 | D50: =SUM(D51:D55) -> 1 | E50: =SUM(E51:E55) -> 201676 | F50: =SUM(F51:F55) -> 1 | G50: =SUM(G51:G55) -> 7060.6228 | H50: =SUM(H51:H55) -> 1 | K50: Totales | L50: =SUM(L51:L55) -> 101 | M50: =SUM(M51:M55) -> 100 | N50: =SUM(N51:N55) -> 110344 | O50: =SUM(O51:O55) -> 1 | P50: =SUM(P51:P55) -> 4153.6737 | Q50: =SUM(Q51:Q55) -> 100 | T50: Totales | U50: =SUM(U51:U55) -> 30 | V50: =SUM(V51:V55) -> 100 | W50: =SUM(W51:W55) -> 91332 | X50: =SUM(X51:X55) -> 92.955361 | Y50: =SUM(Y51:Y55) -> 2906.9491 | Z50: =SUM(Z51:Z55) -> 100
A51: PG | B51: Propuestas Ganadas | C51: =COUNTIFS(Ofertas!$T$2242:$T$2765,Indicadores!A51,Ofertas!$AG$2242:$AG$2765,$B$48) -> 67 | D51: =C51/$C$50 -> 0.51145038 | E51: =SUMIFS(Ofertas!$W$2242:$W$2765,Ofertas!$T$2242:$T$2765,Indicadores!A51,Ofertas!$AG$2242:$AG$2765,Indicadores!$B$48) -> 48113 | F51: =E51/$E$50 -> 0.23856582 | G51: =SUMIFS(Ofertas!$X$2242:$X$2765,Ofertas!$T$2242:$T$2765,Indicadores!A51,Ofertas!$AG$2242:$AG$2765,Indicadores!$B$48) -> 1646.8492 | H51: =G51/$G$50 -> 0.23324418 | J51: PG | K51: Propuestas Ganadas | L51: =COUNTIFS(Ofertas!$T$2242:$T$2765,Indicadores!J51,Ofertas!$AG$2242:$AG$2765,$K$48,Ofertas!$L$2242:$L$2765,Indicadores!$L$48) -> 64 | M51: =L51/$L$50*100 -> 63.366337 | N51: =SUMIFS(Ofertas!$W$2242:$W$2765,Ofertas!$T$2242:$T$2765,Indicadores!J51,Ofertas!$AG$2242:$AG$2765,Indicadores!$K$48,Ofertas!$L$2242:$L$2765,Indicadores!$L$48) -> 41614 | O51: =N51/$N$50 -> 0.3771297 | P51: =SUMIFS(Ofertas!$X$2242:$X$2765,Ofertas!$T$2242:$T$2765,Indicadores!J51,Ofertas!$AG$2242:$AG$2765,Indicadores!$K$48,Ofertas!$L$2242:$L$2765,Indicadores!$L$48) -> 1488.9592 | Q51: =P51/$P$50*100 -> 35.846802 | S51: PG | T51: Propuestas Ganadas | U51: =COUNTIFS(Ofertas!$T$2242:$T$2765,Indicadores!S51,Ofertas!$AG$2242:$AG$2765,$T$48,Ofertas!$L$2242:$L$2765,Indicadores!$U$48) -> 3 | V51: =U51/$U$50*100 -> 10 | W51: =SUMIFS(Ofertas!$W$2242:$W$2765,Ofertas!$T$2242:$T$2765,Indicadores!S51,Ofertas!$AG$2242:$AG$2765,Indicadores!$T$48,Ofertas!$L$2242:$L$2765,Indicadores!$U$48) -> 6499 | X51: =W51/$W$50 -> 0.071157973 | Y51: =SUMIFS(Ofertas!$X$2242:$X$2765,Ofertas!$T$2242:$T$2765,Indicadores!S51,Ofertas!$AG$2242:$AG$2765,Indicadores!$T$48,Ofertas!$L$2242:$L$2765,Indicadores!$U$48) -> 157.89 | Z51: =Y51/$Y$50*100 -> 5.4314676
A52: PP | B52: Propuestas Perdidas | C52: =COUNTIFS(Ofertas!$T$2242:$T$2765,Indicadores!A52,Ofertas!$AG$2242:$AG$2765,$B$48) -> 64 | D52: =C52/$C$50 -> 0.48854962 | E52: =SUMIFS(Ofertas!$W$2242:$W$2765,Ofertas!$T$2242:$T$2765,Indicadores!A52,Ofertas!$AG$2242:$AG$2765,Indicadores!$B$48) -> 153563 | F52: =E52/$E$50 -> 0.76143418 | G52: =SUMIFS(Ofertas!$X$2242:$X$2765,Ofertas!$T$2242:$T$2765,Indicadores!A52,Ofertas!$AG$2242:$AG$2765,Indicadores!$B$48) -> 5413.7736 | H52: =G52/$G$50 -> 0.76675582 | J52: PP | K52: Propuestas Perdidas | L52: =COUNTIFS(Ofertas!$T$2242:$T$2765,Indicadores!J52,Ofertas!$AG$2242:$AG$2765,$K$48,Ofertas!$L$2242:$L$2765,Indicadores!$L$48) -> 37 | M52: =L52/$L$50*100 -> 36.633663 | N52: =SUMIFS(Ofertas!$W$2242:$W$2765,Ofertas!$T$2242:$T$2765,Indicadores!J52,Ofertas!$AG$2242:$AG$2765,Indicadores!$K$48,Ofertas!$L$2242:$L$2765,Indicadores!$L$48) -> 68730 | O52: =N52/$N$50 -> 0.6228703 | P52: =SUMIFS(Ofertas!$X$2242:$X$2765,Ofertas!$T$2242:$T$2765,Indicadores!J52,Ofertas!$AG$2242:$AG$2765,Indicadores!$K$48,Ofertas!$L$2242:$L$2765,Indicadores!$L$48) -> 2664.7145 | Q52: =P52/$P$50*100 -> 64.153198 | S52: PP | T52: Propuestas Perdidas | U52: =COUNTIFS(Ofertas!$T$2242:$T$2765,Indicadores!S52,Ofertas!$AG$2242:$AG$2765,$T$48,Ofertas!$L$2242:$L$2765,Indicadores!$U$48) -> 27 | V52: =U52/$U$50*100 -> 90 | W52: =SUMIFS(Ofertas!$W$2242:$W$2765,Ofertas!$T$2242:$T$2765,Indicadores!S52,Ofertas!$AG$2242:$AG$2765,Indicadores!$T$48,Ofertas!$L$2242:$L$2765,Indicadores!$U$48) -> 84833 | X52: =W52/$W$50*100 -> 92.884203 | Y52: =SUMIFS(Ofertas!$X$2242:$X$2765,Ofertas!$T$2242:$T$2765,Indicadores!S52,Ofertas!$AG$2242:$AG$2765,Indicadores!$T$48,Ofertas!$L$2242:$L$2765,Indicadores!$U$48) -> 2749.0591 | Z52: =Y52/$Y$50*100 -> 94.568532
A53: PD | B53: Propuestas Desiertas | C53: =COUNTIFS(Ofertas!$T$2242:$T$2765,Indicadores!A53,Ofertas!$AG$2242:$AG$2765,$B$48) -> 0 | D53: =C53/$C$50 -> 0 | E53: =SUMIFS(Ofertas!$W$2242:$W$2765,Ofertas!$T$2242:$T$2765,Indicadores!A53,Ofertas!$AG$2242:$AG$2765,Indicadores!$B$48) -> 0 | F53: =E53/$E$50 -> 0 | G53: =SUMIFS(Ofertas!$X$2242:$X$2765,Ofertas!$T$2242:$T$2765,Indicadores!A53,Ofertas!$AG$2242:$AG$2765,Indicadores!$B$48) -> 0 | H53: =G53/$G$50 -> 0 | J53: PD | K53: Propuestas Desiertas | L53: =COUNTIFS(Ofertas!$T$2242:$T$2765,Indicadores!J53,Ofertas!$AG$2242:$AG$2765,$K$48,Ofertas!$L$2242:$L$2765,Indicadores!$L$48) -> 0 | M53: =L53/$L$50*100 -> 0 | N53: =SUMIFS(Ofertas!$W$2242:$W$2765,Ofertas!$T$2242:$T$2765,Indicadores!J53,Ofertas!$AG$2242:$AG$2765,Indicadores!$K$48,Ofertas!$L$2242:$L$2765,Indicadores!$L$48) -> 0 | O53: =N53/$N$50 -> 0 | P53: =SUMIFS(Ofertas!$X$2242:$X$2765,Ofertas!$T$2242:$T$2765,Indicadores!J53,Ofertas!$AG$2242:$AG$2765,Indicadores!$K$48,Ofertas!$L$2242:$L$2765,Indicadores!$L$48) -> 0 | Q53: =P53/$P$50*100 -> 0 | S53: PD | T53: Propuestas Desiertas | U53: =COUNTIFS(Ofertas!$T$2242:$T$2765,Indicadores!S53,Ofertas!$AG$2242:$AG$2765,$T$48,Ofertas!$L$2242:$L$2765,Indicadores!$U$48) -> 0 | V53: =U53/$U$50*100 -> 0 | W53: =SUMIFS(Ofertas!$W$2242:$W$2765,Ofertas!$T$2242:$T$2765,Indicadores!S53,Ofertas!$AG$2242:$AG$2765,Indicadores!$T$48,Ofertas!$L$2242:$L$2765,Indicadores!$U$48) -> 0 | X53: =W53/$W$50*100 -> 0 | Y53: =SUMIFS(Ofertas!$X$2242:$X$2765,Ofertas!$T$2242:$T$2765,Indicadores!S53,Ofertas!$AG$2242:$AG$2765,Indicadores!$T$48,Ofertas!$L$2242:$L$2765,Indicadores!$U$48) -> 0 | Z53: =Y53/$Y$50*100 -> 0
A54: DP | B54: Decisión del Cliente Pendiente | C54: =COUNTIFS(Ofertas!$T$2242:$T$2765,Indicadores!A54,Ofertas!$AG$2242:$AG$2765,$B$48) -> 0 | D54: =C54/$C$50 -> 0 | E54: =SUMIFS(Ofertas!$W$2242:$W$2765,Ofertas!$T$2242:$T$2765,Indicadores!A54,Ofertas!$AG$2242:$AG$2765,Indicadores!$B$48) -> 0 | F54: =E54/$E$50 -> 0 | G54: =SUMIFS(Ofertas!$X$2242:$X$2765,Ofertas!$T$2242:$T$2765,Indicadores!A54,Ofertas!$AG$2242:$AG$2765,Indicadores!$B$48) -> 0 | H54: =G54/$G$50 -> 0 | J54: DP | K54: Decisión del Cliente Pendiente | L54: =COUNTIFS(Ofertas!$T$2242:$T$2765,Indicadores!J54,Ofertas!$AG$2242:$AG$2765,$K$48,Ofertas!$L$2242:$L$2765,Indicadores!$L$48) -> 0 | M54: =L54/$L$50*100 -> 0 | N54: =SUMIFS(Ofertas!$W$2242:$W$2765,Ofertas!$T$2242:$T$2765,Indicadores!J54,Ofertas!$AG$2242:$AG$2765,Indicadores!$K$48,Ofertas!$L$2242:$L$2765,Indicadores!$L$48) -> 0 | O54: =N54/$N$50 -> 0 | P54: =SUMIFS(Ofertas!$X$2242:$X$2765,Ofertas!$T$2242:$T$2765,Indicadores!J54,Ofertas!$AG$2242:$AG$2765,Indicadores!$K$48,Ofertas!$L$2242:$L$2765,Indicadores!$L$48) -> 0 | Q54: =P54/$P$50*100 -> 0 | S54: DP | T54: Decisión del Cliente Pendiente | U54: =COUNTIFS(Ofertas!$T$2242:$T$2765,Indicadores!S54,Ofertas!$AG$2242:$AG$2765,$T$48,Ofertas!$L$2242:$L$2765,Indicadores!$U$48) -> 0 | V54: =U54/$U$50*100 -> 0 | W54: =SUMIFS(Ofertas!$W$2242:$W$2765,Ofertas!$T$2242:$T$2765,Indicadores!S54,Ofertas!$AG$2242:$AG$2765,Indicadores!$T$48,Ofertas!$L$2242:$L$2765,Indicadores!$U$48) -> 0 | X54: =W54/$W$50*100 -> 0 | Y54: =SUMIFS(Ofertas!$X$2242:$X$2765,Ofertas!$T$2242:$T$2765,Indicadores!S54,Ofertas!$AG$2242:$AG$2765,Indicadores!$T$48,Ofertas!$L$2242:$L$2765,Indicadores!$U$48) -> 0 | Z54: =Y54/$Y$50*100 -> 0
A55: EP | B55: Propuestas en Preparación | C55: =COUNTIFS(Ofertas!$T$2242:$T$2765,Indicadores!A55,Ofertas!$AG$2242:$AG$2765,$B$48) -> 0 | D55: =C55/$C$50 -> 0 | E55: =SUMIFS(Ofertas!$W$2242:$W$2765,Ofertas!$T$2242:$T$2765,Indicadores!A55,Ofertas!$AG$2242:$AG$2765,Indicadores!$B$48) -> 0 | F55: =E55/$E$50 -> 0 | G55: =SUMIFS(Ofertas!$X$2242:$X$2765,Ofertas!$T$2242:$T$2765,Indicadores!A55,Ofertas!$AG$2242:$AG$2765,Indicadores!$B$48) -> 0 | H55: =G55/$G$50 -> 0 | J55: EP | K55: Propuestas en Preparación | L55: =COUNTIFS(Ofertas!$T$2242:$T$2765,Indicadores!J55,Ofertas!$AG$2242:$AG$2765,$K$48,Ofertas!$L$2242:$L$2765,Indicadores!$L$48) -> 0 | M55: =L55/$L$50*100 -> 0 | N55: =SUMIFS(Ofertas!$W$2242:$W$2765,Ofertas!$T$2242:$T$2765,Indicadores!J55,Ofertas!$AG$2242:$AG$2765,Indicadores!$K$48,Ofertas!$L$2242:$L$2765,Indicadores!$L$48) -> 0 | O55: =N55/$N$50 -> 0 | P55: =SUMIFS(Ofertas!$X$2242:$X$2765,Ofertas!$T$2242:$T$2765,Indicadores!J55,Ofertas!$AG$2242:$AG$2765,Indicadores!$K$48,Ofertas!$L$2242:$L$2765,Indicadores!$L$48) -> 0 | Q55: =P55/$P$50*100 -> 0 | S55: EP | T55: Propuestas en Preparación | U55: =COUNTIFS(Ofertas!$T$2242:$T$2765,Indicadores!S55,Ofertas!$AG$2242:$AG$2765,$T$48,Ofertas!$L$2242:$L$2765,Indicadores!$U$48) -> 0 | V55: =U55/$U$50*100 -> 0 | W55: =SUMIFS(Ofertas!$W$2242:$W$2765,Ofertas!$T$2242:$T$2765,Indicadores!S55,Ofertas!$AG$2242:$AG$2765,Indicadores!$T$48,Ofertas!$L$2242:$L$2765,Indicadores!$U$48) -> 0 | X55: =W55/$W$50*100 -> 0 | Y55: =SUMIFS(Ofertas!$X$2242:$X$2765,Ofertas!$T$2242:$T$2765,Indicadores!S55,Ofertas!$AG$2242:$AG$2765,Indicadores!$T$48,Ofertas!$L$2242:$L$2765,Indicadores!$U$48) -> 0 | Z55: =Y55/$Y$50*100 -> 0
B57: 2016 | K57: 2016 | L57: ND | M57: NEGOCIACIÓN DIRECTA | T57: 2016 | U57: LM | V57: LICITACIÓN MÚLTIPLE
B58: STATUS (a la fecha) | C58: Can. | D58: % | E58: hh Lic. | F58: % hh | G58: M$ Lic. | H58: % M$ | K58: STATUS (a la fecha) | L58: Can. | M58: % | N58: hh Lic. | O58: % hh | P58: M$ Lic. | Q58: % M$ | T58: STATUS (a la fecha) | U58: Can. | V58: % | W58: hh Lic. | X58: % hh | Y58: M$ Lic. | Z58: % M$
B59: Totales | C59: =SUM(C60:C64) -> 104 | D59: =SUM(D60:D64) -> 1 | E59: =SUM(E60:E64) -> 298851 | F59: =SUM(F60:F64) -> 1 | G59: =SUM(G60:G64) -> 10194.542 | H59: =SUM(H60:H64) -> 1 | K59: Totales | L59: =SUM(L60:L64) -> 75 | M59: =SUM(M60:M64) -> 100 | N59: =SUM(N60:N64) -> 83176 | O59: =SUM(O60:O64) -> 1 | P59: =SUM(P60:P64) -> 3113.4859 | Q59: =SUM(Q60:Q64) -> 100 | T59: Totales | U59: =SUM(U60:U64) -> 29 | V59: =SUM(V60:V64) -> 100 | W59: =SUM(W60:W64) -> 215675 | X59: =SUM(X60:X64) -> 1 | Y59: =SUM(Y60:Y64) -> 7081.0561 | Z59: =SUM(Z60:Z64) -> 100
A60: PG | B60: Propuestas Ganadas | C60: =COUNTIFS(Ofertas!$T$1870:$T$2765,Indicadores!A60,Ofertas!$AG$1870:$AG$2765,$B$57) -> 52 | D60: =C60/$C$59 -> 0.5 | E60: =SUMIFS(Ofertas!$W$1870:$W$2765,Ofertas!$T$1870:$T$2765,Indicadores!A60,Ofertas!$AG$1870:$AG$2765,Indicadores!$B$57) -> 64097 | F60: =E60/$E$59 -> 0.21447812 | G60: =SUMIFS(Ofertas!$X$1870:$X$2765,Ofertas!$T$1870:$T$2765,Indicadores!A60,Ofertas!$AG$1870:$AG$2765,Indicadores!$B$57) -> 2056.1489 | H60: =G60/$G$59 -> 0.20169115 | J60: PG | K60: Propuestas Ganadas | L60: =COUNTIFS(Ofertas!$T$1870:$T$2765,Indicadores!J60,Ofertas!$AG$1870:$AG$2765,$K$57,Ofertas!$L$1870:$L$2765,Indicadores!$L$57) -> 45 | M60: =L60/$L$59*100 -> 60 | N60: =SUMIFS(Ofertas!$W$1870:$W$2765,Ofertas!$T$1870:$T$2765,Indicadores!J60,Ofertas!$AG$1870:$AG$2765,Indicadores!$K$57,Ofertas!$L$1870:$L$2765,Indicadores!$L$57) -> 29725 | O60: =N60/$N$59 -> 0.35737472 | P60: =SUMIFS(Ofertas!$X$1870:$X$2765,Ofertas!$T$1870:$T$2765,Indicadores!J60,Ofertas!$AG$1870:$AG$2765,Indicadores!$K$57,Ofertas!$L$1870:$L$2765,Indicadores!$L$57) -> 1048.1401 | Q60: =P60/$P$59*100 -> 33.664519 | S60: PG | T60: Propuestas Ganadas | U60: =COUNTIFS(Ofertas!$T$1870:$T$2765,Indicadores!S60,Ofertas!$AG$1870:$AG$2765,$T$57,Ofertas!$L$1870:$L$2765,Indicadores!$U$57) -> 7 | V60: =U60/$U$59*100 -> 24.137931 | W60: =SUMIFS(Ofertas!$W$1870:$W$2765,Ofertas!$T$1870:$T$2765,Indicadores!S60,Ofertas!$AG$1870:$AG$2765,Indicadores!$T$57,Ofertas!$L$1870:$L$2765,Indicadores!$U$57) -> 34372 | X60: =W60/$W$59 -> 0.15936942 | Y60: =SUMIFS(Ofertas!$X$1870:$X$2765,Ofertas!$T$1870:$T$2765,Indicadores!S60,Ofertas!$AG$1870:$AG$2765,Indicadores!$T$57,Ofertas!$L$1870:$L$2765,Indicadores!$U$57) -> 1008.0088 | Z60: =Y60/$Y$59*100 -> 14.235289
A61: PP | B61: Propuestas Perdidas | C61: =COUNTIFS(Ofertas!$T$1870:$T$2765,Indicadores!A61,Ofertas!$AG$1870:$AG$2765,$B$57) -> 52 | D61: =C61/$C$59 -> 0.5 | E61: =SUMIFS(Ofertas!$W$1870:$W$2765,Ofertas!$T$1870:$T$2765,Indicadores!A61,Ofertas!$AG$1870:$AG$2765,Indicadores!$B$57) -> 234754 | F61: =E61/$E$59 -> 0.78552188 | G61: =SUMIFS(Ofertas!$X$1870:$X$2765,Ofertas!$T$1870:$T$2765,Indicadores!A61,Ofertas!$AG$1870:$AG$2765,Indicadores!$B$57) -> 8138.3931 | H61: =G61/$G$59 -> 0.79830885 | J61: PP | K61: Propuestas Perdidas | L61: =COUNTIFS(Ofertas!$T$1870:$T$2765,Indicadores!J61,Ofertas!$AG$1870:$AG$2765,$K$57,Ofertas!$L$1870:$L$2765,Indicadores!$L$57) -> 30 | M61: =L61/$L$59*100 -> 40 | N61: =SUMIFS(Ofertas!$W$1870:$W$2765,Ofertas!$T$1870:$T$2765,Indicadores!J61,Ofertas!$AG$1870:$AG$2765,Indicadores!$K$57,Ofertas!$L$1870:$L$2765,Indicadores!$L$57) -> 53451 | O61: =N61/$N$59 -> 0.64262528 | P61: =SUMIFS(Ofertas!$X$1870:$X$2765,Ofertas!$T$1870:$T$2765,Indicadores!J61,Ofertas!$AG$1870:$AG$2765,Indicadores!$K$57,Ofertas!$L$1870:$L$2765,Indicadores!$L$57) -> 2065.3459 | Q61: =P61/$P$59*100 -> 66.335481 | S61: PP | T61: Propuestas Perdidas | U61: =COUNTIFS(Ofertas!$T$1870:$T$2765,Indicadores!S61,Ofertas!$AG$1870:$AG$2765,$T$57,Ofertas!$L$1870:$L$2765,Indicadores!$U$57) -> 22 | V61: =U61/$U$59*100 -> 75.862069 | W61: =SUMIFS(Ofertas!$W$1870:$W$2765,Ofertas!$T$1870:$T$2765,Indicadores!S61,Ofertas!$AG$1870:$AG$2765,Indicadores!$T$57,Ofertas!$L$1870:$L$2765,Indicadores!$U$57) -> 181303 | X61: =W61/$W$59 -> 0.84063058 | Y61: =SUMIFS(Ofertas!$X$1870:$X$2765,Ofertas!$T$1870:$T$2765,Indicadores!S61,Ofertas!$AG$1870:$AG$2765,Indicadores!$T$57,Ofertas!$L$1870:$L$2765,Indicadores!$U$57) -> 6073.0473 | Z61: =Y61/$Y$59*100 -> 85.764711
A62: PD | B62: Propuestas Desiertas | C62: =COUNTIFS(Ofertas!$T$1870:$T$2765,Indicadores!A62,Ofertas!$AG$1870:$AG$2765,$B$57) -> 0 | D62: =C62/$C$59 -> 0 | E62: =SUMIFS(Ofertas!$W$1870:$W$2765,Ofertas!$T$1870:$T$2765,Indicadores!A62,Ofertas!$AG$1870:$AG$2765,Indicadores!$B$57) -> 0 | F62: =E62/$E$59 -> 0 | G62: =SUMIFS(Ofertas!$X$1870:$X$2765,Ofertas!$T$1870:$T$2765,Indicadores!A62,Ofertas!$AG$1870:$AG$2765,Indicadores!$B$57) -> 0 | H62: =G62/$G$59 -> 0 | J62: PD | K62: Propuestas Desiertas | L62: =COUNTIFS(Ofertas!$T$1870:$T$2765,Indicadores!J62,Ofertas!$AG$1870:$AG$2765,$K$57,Ofertas!$L$1870:$L$2765,Indicadores!$L$57) -> 0 | M62: =L62/$L$59*100 -> 0 | N62: =SUMIFS(Ofertas!$W$1870:$W$2765,Ofertas!$T$1870:$T$2765,Indicadores!J62,Ofertas!$AG$1870:$AG$2765,Indicadores!$K$57,Ofertas!$L$1870:$L$2765,Indicadores!$L$57) -> 0 | O62: =N62/$N$59 -> 0 | P62: =SUMIFS(Ofertas!$X$1870:$X$2765,Ofertas!$T$1870:$T$2765,Indicadores!J62,Ofertas!$AG$1870:$AG$2765,Indicadores!$K$57,Ofertas!$L$1870:$L$2765,Indicadores!$L$57) -> 0 | Q62: =P62/$P$59*100 -> 0 | S62: PD | T62: Propuestas Desiertas | U62: =COUNTIFS(Ofertas!$T$1870:$T$2765,Indicadores!S62,Ofertas!$AG$1870:$AG$2765,$T$57,Ofertas!$L$1870:$L$2765,Indicadores!$U$57) -> 0 | V62: =U62/$U$59*100 -> 0 | W62: =SUMIFS(Ofertas!$W$1870:$W$2765,Ofertas!$T$1870:$T$2765,Indicadores!S62,Ofertas!$AG$1870:$AG$2765,Indicadores!$T$57,Ofertas!$L$1870:$L$2765,Indicadores!$U$57) -> 0 | X62: =W62/$W$59 -> 0 | Y62: =SUMIFS(Ofertas!$X$1870:$X$2765,Ofertas!$T$1870:$T$2765,Indicadores!S62,Ofertas!$AG$1870:$AG$2765,Indicadores!$T$57,Ofertas!$L$1870:$L$2765,Indicadores!$U$57) -> 0 | Z62: =Y62/$Y$59*100 -> 0
A63: DP | B63: Decisión del Cliente Pendiente | C63: =COUNTIFS(Ofertas!$T$1870:$T$2765,Indicadores!A63,Ofertas!$AG$1870:$AG$2765,$B$57) -> 0 | D63: =C63/$C$59 -> 0 | E63: =SUMIFS(Ofertas!$W$1870:$W$2765,Ofertas!$T$1870:$T$2765,Indicadores!A63,Ofertas!$AG$1870:$AG$2765,Indicadores!$B$57) -> 0 | F63: =E63/$E$59 -> 0 | G63: =SUMIFS(Ofertas!$X$1870:$X$2765,Ofertas!$T$1870:$T$2765,Indicadores!A63,Ofertas!$AG$1870:$AG$2765,Indicadores!$B$57) -> 0 | H63: =G63/$G$59 -> 0 | J63: DP | K63: Decisión del Cliente Pendiente | L63: =COUNTIFS(Ofertas!$T$1870:$T$2765,Indicadores!J63,Ofertas!$AG$1870:$AG$2765,$K$57,Ofertas!$L$1870:$L$2765,Indicadores!$L$57) -> 0 | M63: =L63/$L$59*100 -> 0 | N63: =SUMIFS(Ofertas!$W$1870:$W$2765,Ofertas!$T$1870:$T$2765,Indicadores!J63,Ofertas!$AG$1870:$AG$2765,Indicadores!$K$57,Ofertas!$L$1870:$L$2765,Indicadores!$L$57) -> 0 | O63: =N63/$N$59 -> 0 | P63: =SUMIFS(Ofertas!$X$1870:$X$2765,Ofertas!$T$1870:$T$2765,Indicadores!J63,Ofertas!$AG$1870:$AG$2765,Indicadores!$K$57,Ofertas!$L$1870:$L$2765,Indicadores!$L$57) -> 0 | Q63: =P63/$P$59*100 -> 0 | S63: DP | T63: Decisión del Cliente Pendiente | U63: =COUNTIFS(Ofertas!$T$1870:$T$2765,Indicadores!S63,Ofertas!$AG$1870:$AG$2765,$T$57,Ofertas!$L$1870:$L$2765,Indicadores!$U$57) -> 0 | V63: =U63/$U$59*100 -> 0 | W63: =SUMIFS(Ofertas!$W$1870:$W$2765,Ofertas!$T$1870:$T$2765,Indicadores!S63,Ofertas!$AG$1870:$AG$2765,Indicadores!$T$57,Ofertas!$L$1870:$L$2765,Indicadores!$U$57) -> 0 | X63: =W63/$W$59 -> 0 | Y63: =SUMIFS(Ofertas!$X$1870:$X$2765,Ofertas!$T$1870:$T$2765,Indicadores!S63,Ofertas!$AG$1870:$AG$2765,Indicadores!$T$57,Ofertas!$L$1870:$L$2765,Indicadores!$U$57) -> 0 | Z63: =Y63/$Y$59*100 -> 0
A64: EP | B64: Propuestas en Preparación | C64: =COUNTIFS(Ofertas!$T$1870:$T$2765,Indicadores!A64,Ofertas!$AG$1870:$AG$2765,$B$57) -> 0 | D64: =C64/$C$59 -> 0 | E64: =SUMIFS(Ofertas!$W$1870:$W$2765,Ofertas!$T$1870:$T$2765,Indicadores!A64,Ofertas!$AG$1870:$AG$2765,Indicadores!$B$57) -> 0 | F64: =E64/$E$59 -> 0 | G64: =SUMIFS(Ofertas!$X$1870:$X$2765,Ofertas!$T$1870:$T$2765,Indicadores!A64,Ofertas!$AG$1870:$AG$2765,Indicadores!$B$57) -> 0 | H64: =G64/$G$59 -> 0 | J64: EP | K64: Propuestas en Preparación | L64: =COUNTIFS(Ofertas!$T$1870:$T$2765,Indicadores!J64,Ofertas!$AG$1870:$AG$2765,$K$57,Ofertas!$L$1870:$L$2765,Indicadores!$L$57) -> 0 | M64: =L64/$L$59*100 -> 0 | N64: =SUMIFS(Ofertas!$W$1870:$W$2765,Ofertas!$T$1870:$T$2765,Indicadores!J64,Ofertas!$AG$1870:$AG$2765,Indicadores!$K$57,Ofertas!$L$1870:$L$2765,Indicadores!$L$57) -> 0 | O64: =N64/$N$59 -> 0 | P64: =SUMIFS(Ofertas!$X$1870:$X$2765,Ofertas!$T$1870:$T$2765,Indicadores!J64,Ofertas!$AG$1870:$AG$2765,Indicadores!$K$57,Ofertas!$L$1870:$L$2765,Indicadores!$L$57) -> 0 | Q64: =P64/$P$59*100 -> 0 | S64: EP | T64: Propuestas en Preparación | U64: =COUNTIFS(Ofertas!$T$1870:$T$2765,Indicadores!S64,Ofertas!$AG$1870:$AG$2765,$T$57,Ofertas!$L$1870:$L$2765,Indicadores!$U$57) -> 0 | V64: =U64/$U$59*100 -> 0 | W64: =SUMIFS(Ofertas!$W$1870:$W$2765,Ofertas!$T$1870:$T$2765,Indicadores!S64,Ofertas!$AG$1870:$AG$2765,Indicadores!$T$57,Ofertas!$L$1870:$L$2765,Indicadores!$U$57) -> 0 | X64: =W64/$W$59 -> 0 | Y64: =SUMIFS(Ofertas!$X$1870:$X$2765,Ofertas!$T$1870:$T$2765,Indicadores!S64,Ofertas!$AG$1870:$AG$2765,Indicadores!$T$57,Ofertas!$L$1870:$L$2765,Indicadores!$U$57) -> 0 | Z64: =Y64/$Y$59*100 -> 0
B66: 2017 | K66: 2017 | L66: ND | M66: NEGOCIACIÓN DIRECTA | T66: 2017 | U66: LM | V66: LICITACIÓN MÚLTIPLE
B67: STATUS (a la fecha) | C67: Can. | D67: % | E67: hh Lic. | F67: % hh | G67: M$ Lic. | H67: % M$ | K67: STATUS (a la fecha) | L67: Can. | M67: % | N67: hh Lic. | O67: % hh | P67: M$ Lic. | Q67: % M$ | T67: STATUS (a la fecha) | U67: Can. | V67: % | W67: hh Lic. | X67: % hh | Y67: M$ Lic. | Z67: % M$
B68: Totales | C68: =SUM(C69:C73) -> 144 | D68: =SUM(D69:D73) -> 1 | E68: =SUM(E69:E73) -> 299629.5 | F68: =SUM(F69:F73) -> 1 | G68: =SUM(G69:G73) -> 9911.87 | H68: =SUM(H69:H73) -> 1 | K68: Totales | L68: =SUM(L69:L73) -> 71 | M68: =SUM(M69:M73) -> 100 | N68: =SUM(N69:N73) -> 47652 | O68: =SUM(O69:O73) -> 1 | P68: =SUM(P69:P73) -> 1749.6283 | Q68: =SUM(Q69:Q73) -> 100 | T68: Totales | U68: =SUM(U69:U73) -> 73 | V68: =SUM(V69:V73) -> 100 | W68: =SUM(W69:W73) -> 251977.5 | X68: =SUM(X69:X73) -> 1 | Y68: =SUM(Y69:Y73) -> 8162.2418 | Z68: =SUM(Z69:Z73) -> 100
A69: PG | B69: Propuestas Ganadas | C69: =COUNTIFS(Ofertas!$T$1870:$T$2765,Indicadores!A69,Ofertas!$AG$1870:$AG$2765,$B$66) -> 45 | D69: =C69/$C$68 -> 0.3125 | E69: =SUMIFS(Ofertas!$W$1870:$W$2765,Ofertas!$T$1870:$T$2765,Indicadores!A69,Ofertas!$AG$1870:$AG$2765,Indicadores!$B$66) -> 35172 | F69: =E69/$E$68 -> 0.11738497 | G69: =SUMIFS(Ofertas!$X$1870:$X$2765,Ofertas!$T$1870:$T$2765,Indicadores!A69,Ofertas!$AG$1870:$AG$2765,Indicadores!$B$66) -> 1082.3383 | H69: =G69/$G$68 -> 0.10919617 | J69: PG | K69: Propuestas Ganadas | L69: =COUNTIFS(Ofertas!$T$1870:$T$2765,Indicadores!J69,Ofertas!$AG$1870:$AG$2765,$K$66,Ofertas!$L$1870:$L$2765,Indicadores!$L$66) -> 23 | M69: =L69/$L$68*100 -> 32.394366 | N69: =SUMIFS(Ofertas!$W$1870:$W$2765,Ofertas!$T$1870:$T$2765,Indicadores!J69,Ofertas!$AG$1870:$AG$2765,Indicadores!$K$66,Ofertas!$L$1870:$L$2765,Indicadores!$L$66) -> 8851 | O69: =N69/$N$68 -> 0.18574247 | P69: =SUMIFS(Ofertas!$X$1870:$X$2765,Ofertas!$T$1870:$T$2765,Indicadores!J69,Ofertas!$AG$1870:$AG$2765,Indicadores!$K$66,Ofertas!$L$1870:$L$2765,Indicadores!$L$66) -> 343.35367 | Q69: =P69/$P$68*100 -> 19.624378 | S69: PG | T69: Propuestas Ganadas | U69: =COUNTIFS(Ofertas!$T$1870:$T$2765,Indicadores!S69,Ofertas!$AG$1870:$AG$2765,$T$66,Ofertas!$L$1870:$L$2765,Indicadores!$U$66) -> 22 | V69: =U69/$U$68*100 -> 30.136986 | W69: =SUMIFS(Ofertas!$W$1870:$W$2765,Ofertas!$T$1870:$T$2765,Indicadores!S69,Ofertas!$AG$1870:$AG$2765,Indicadores!$T$66,Ofertas!$L$1870:$L$2765,Indicadores!$U$66) -> 26321 | X69: =W69/$W$68 -> 0.10445774 | Y69: =SUMIFS(Ofertas!$X$1870:$X$2765,Ofertas!$T$1870:$T$2765,Indicadores!S69,Ofertas!$AG$1870:$AG$2765,Indicadores!$T$66,Ofertas!$L$1870:$L$2765,Indicadores!$U$66) -> 738.98461 | Z69: =Y69/$Y$68*100 -> 9.0536966
A70: PP | B70: Propuestas Perdidas | C70: =COUNTIFS(Ofertas!$T$1870:$T$2765,Indicadores!A70,Ofertas!$AG$1870:$AG$2765,$B$66) -> 99 | D70: =C70/$C$68 -> 0.6875 | E70: =SUMIFS(Ofertas!$W$1870:$W$2765,Ofertas!$T$1870:$T$2765,Indicadores!A70,Ofertas!$AG$1870:$AG$2765,Indicadores!$B$66) -> 264457.5 | F70: =E70/$E$68 -> 0.88261503 | G70: =SUMIFS(Ofertas!$X$1870:$X$2765,Ofertas!$T$1870:$T$2765,Indicadores!A70,Ofertas!$AG$1870:$AG$2765,Indicadores!$B$66) -> 8829.5317 | H70: =G70/$G$68 -> 0.89080383 | J70: PP | K70: Propuestas Perdidas | L70: =COUNTIFS(Ofertas!$T$1870:$T$2765,Indicadores!J70,Ofertas!$AG$1870:$AG$2765,$K$66,Ofertas!$L$1870:$L$2765,Indicadores!$L$66) -> 48 | M70: =L70/$L$68*100 -> 67.605634 | N70: =SUMIFS(Ofertas!$W$1870:$W$2765,Ofertas!$T$1870:$T$2765,Indicadores!J70,Ofertas!$AG$1870:$AG$2765,Indicadores!$K$66,Ofertas!$L$1870:$L$2765,Indicadores!$L$66) -> 38801 | O70: =N70/$N$68 -> 0.81425753 | P70: =SUMIFS(Ofertas!$X$1870:$X$2765,Ofertas!$T$1870:$T$2765,Indicadores!J70,Ofertas!$AG$1870:$AG$2765,Indicadores!$K$66,Ofertas!$L$1870:$L$2765,Indicadores!$L$66) -> 1406.2746 | Q70: =P70/$P$68*100 -> 80.375622 | S70: PP | T70: Propuestas Perdidas | U70: =COUNTIFS(Ofertas!$T$1870:$T$2765,Indicadores!S70,Ofertas!$AG$1870:$AG$2765,$T$66,Ofertas!$L$1870:$L$2765,Indicadores!$U$66) -> 51 | V70: =U70/$U$68*100 -> 69.863014 | W70: =SUMIFS(Ofertas!$W$1870:$W$2765,Ofertas!$T$1870:$T$2765,Indicadores!S70,Ofertas!$AG$1870:$AG$2765,Indicadores!$T$66,Ofertas!$L$1870:$L$2765,Indicadores!$U$66) -> 225656.5 | X70: =W70/$W$68 -> 0.89554226 | Y70: =SUMIFS(Ofertas!$X$1870:$X$2765,Ofertas!$T$1870:$T$2765,Indicadores!S70,Ofertas!$AG$1870:$AG$2765,Indicadores!$T$66,Ofertas!$L$1870:$L$2765,Indicadores!$U$66) -> 7423.2572 | Z70: =Y70/$Y$68*100 -> 90.946303
A71: PD | B71: Propuestas Desiertas | C71: =COUNTIFS(Ofertas!$T$1870:$T$2765,Indicadores!A71,Ofertas!$AG$1870:$AG$2765,$B$66) -> 0 | D71: =C71/$C$68 -> 0 | E71: =SUMIFS(Ofertas!$W$1870:$W$2765,Ofertas!$T$1870:$T$2765,Indicadores!A71,Ofertas!$AG$1870:$AG$2765,Indicadores!$B$66) -> 0 | F71: =E71/$E$68 -> 0 | G71: =SUMIFS(Ofertas!$X$1870:$X$2765,Ofertas!$T$1870:$T$2765,Indicadores!A71,Ofertas!$AG$1870:$AG$2765,Indicadores!$B$66) -> 0 | H71: =G71/$G$68 -> 0 | J71: PD | K71: Propuestas Desiertas | L71: =COUNTIFS(Ofertas!$T$1870:$T$2765,Indicadores!J71,Ofertas!$AG$1870:$AG$2765,$K$66,Ofertas!$L$1870:$L$2765,Indicadores!$L$66) -> 0 | M71: =L71/$L$68*100 -> 0 | N71: =SUMIFS(Ofertas!$W$1870:$W$2765,Ofertas!$T$1870:$T$2765,Indicadores!J71,Ofertas!$AG$1870:$AG$2765,Indicadores!$K$66,Ofertas!$L$1870:$L$2765,Indicadores!$L$66) -> 0 | O71: =N71/$N$68 -> 0 | P71: =SUMIFS(Ofertas!$X$1870:$X$2765,Ofertas!$T$1870:$T$2765,Indicadores!J71,Ofertas!$AG$1870:$AG$2765,Indicadores!$K$66,Ofertas!$L$1870:$L$2765,Indicadores!$L$66) -> 0 | Q71: =P71/$P$68*100 -> 0 | S71: PD | T71: Propuestas Desiertas | U71: =COUNTIFS(Ofertas!$T$1870:$T$2765,Indicadores!S71,Ofertas!$AG$1870:$AG$2765,$T$66,Ofertas!$L$1870:$L$2765,Indicadores!$U$66) -> 0 | V71: =U71/$U$68*100 -> 0 | W71: =SUMIFS(Ofertas!$W$1870:$W$2765,Ofertas!$T$1870:$T$2765,Indicadores!S71,Ofertas!$AG$1870:$AG$2765,Indicadores!$T$66,Ofertas!$L$1870:$L$2765,Indicadores!$U$66) -> 0 | X71: =W71/$W$68 -> 0 | Y71: =SUMIFS(Ofertas!$X$1870:$X$2765,Ofertas!$T$1870:$T$2765,Indicadores!S71,Ofertas!$AG$1870:$AG$2765,Indicadores!$T$66,Ofertas!$L$1870:$L$2765,Indicadores!$U$66) -> 0 | Z71: =Y71/$Y$68*100 -> 0
A72: DP | B72: Decisión del Cliente Pendiente | C72: =COUNTIFS(Ofertas!$T$1870:$T$2765,Indicadores!A72,Ofertas!$AG$1870:$AG$2765,$B$66) -> 0 | D72: =C72/$C$68 -> 0 | E72: =SUMIFS(Ofertas!$W$1870:$W$2765,Ofertas!$T$1870:$T$2765,Indicadores!A72,Ofertas!$AG$1870:$AG$2765,Indicadores!$B$66) -> 0 | F72: =E72/$E$68 -> 0 | G72: =SUMIFS(Ofertas!$X$1870:$X$2765,Ofertas!$T$1870:$T$2765,Indicadores!A72,Ofertas!$AG$1870:$AG$2765,Indicadores!$B$66) -> 0 | H72: =G72/$G$68 -> 0 | J72: DP | K72: Decisión del Cliente Pendiente | L72: =COUNTIFS(Ofertas!$T$1870:$T$2765,Indicadores!J72,Ofertas!$AG$1870:$AG$2765,$K$66,Ofertas!$L$1870:$L$2765,Indicadores!$L$66) -> 0 | M72: =L72/$L$68*100 -> 0 | N72: =SUMIFS(Ofertas!$W$1870:$W$2765,Ofertas!$T$1870:$T$2765,Indicadores!J72,Ofertas!$AG$1870:$AG$2765,Indicadores!$K$66,Ofertas!$L$1870:$L$2765,Indicadores!$L$66) -> 0 | O72: =N72/$N$68 -> 0 | P72: =SUMIFS(Ofertas!$X$1870:$X$2765,Ofertas!$T$1870:$T$2765,Indicadores!J72,Ofertas!$AG$1870:$AG$2765,Indicadores!$K$66,Ofertas!$L$1870:$L$2765,Indicadores!$L$66) -> 0 | Q72: =P72/$P$68*100 -> 0 | S72: DP | T72: Decisión del Cliente Pendiente | U72: =COUNTIFS(Ofertas!$T$1870:$T$2765,Indicadores!S72,Ofertas!$AG$1870:$AG$2765,$T$66,Ofertas!$L$1870:$L$2765,Indicadores!$U$66) -> 0 | V72: =U72/$U$68*100 -> 0 | W72: =SUMIFS(Ofertas!$W$1870:$W$2765,Ofertas!$T$1870:$T$2765,Indicadores!S72,Ofertas!$AG$1870:$AG$2765,Indicadores!$T$66,Ofertas!$L$1870:$L$2765,Indicadores!$U$66) -> 0 | X72: =W72/$W$68 -> 0 | Y72: =SUMIFS(Ofertas!$X$1870:$X$2765,Ofertas!$T$1870:$T$2765,Indicadores!S72,Ofertas!$AG$1870:$AG$2765,Indicadores!$T$66,Ofertas!$L$1870:$L$2765,Indicadores!$U$66) -> 0 | Z72: =Y72/$Y$68*100 -> 0
A73: EP | B73: Propuestas en Preparación | C73: =COUNTIFS(Ofertas!$T$1870:$T$2765,Indicadores!A73,Ofertas!$AG$1870:$AG$2765,$B$66) -> 0 | D73: =C73/$C$68 -> 0 | E73: =SUMIFS(Ofertas!$W$1870:$W$2765,Ofertas!$T$1870:$T$2765,Indicadores!A73,Ofertas!$AG$1870:$AG$2765,Indicadores!$B$66) -> 0 | F73: =E73/$E$68 -> 0 | G73: =SUMIFS(Ofertas!$X$1870:$X$2765,Ofertas!$T$1870:$T$2765,Indicadores!A73,Ofertas!$AG$1870:$AG$2765,Indicadores!$B$66) -> 0 | H73: =G73/$G$68 -> 0 | J73: EP | K73: Propuestas en Preparación | L73: =COUNTIFS(Ofertas!$T$1870:$T$2765,Indicadores!J73,Ofertas!$AG$1870:$AG$2765,$K$66,Ofertas!$L$1870:$L$2765,Indicadores!$L$66) -> 0 | M73: =L73/$L$68*100 -> 0 | N73: =SUMIFS(Ofertas!$W$1870:$W$2765,Ofertas!$T$1870:$T$2765,Indicadores!J73,Ofertas!$AG$1870:$AG$2765,Indicadores!$K$66,Ofertas!$L$1870:$L$2765,Indicadores!$L$66) -> 0 | O73: =N73/$N$68 -> 0 | P73: =SUMIFS(Ofertas!$X$1870:$X$2765,Ofertas!$T$1870:$T$2765,Indicadores!J73,Ofertas!$AG$1870:$AG$2765,Indicadores!$K$66,Ofertas!$L$1870:$L$2765,Indicadores!$L$66) -> 0 | Q73: =P73/$P$68*100 -> 0 | S73: EP | T73: Propuestas en Preparación | U73: =COUNTIFS(Ofertas!$T$1870:$T$2765,Indicadores!S73,Ofertas!$AG$1870:$AG$2765,$T$66,Ofertas!$L$1870:$L$2765,Indicadores!$U$66) -> 0 | V73: =U73/$U$68*100 -> 0 | W73: =SUMIFS(Ofertas!$W$1870:$W$2765,Ofertas!$T$1870:$T$2765,Indicadores!S73,Ofertas!$AG$1870:$AG$2765,Indicadores!$T$66,Ofertas!$L$1870:$L$2765,Indicadores!$U$66) -> 0 | X73: =W73/$W$68 -> 0 | Y73: =SUMIFS(Ofertas!$X$1870:$X$2765,Ofertas!$T$1870:$T$2765,Indicadores!S73,Ofertas!$AG$1870:$AG$2765,Indicadores!$T$66,Ofertas!$L$1870:$L$2765,Indicadores!$U$66) -> 0 | Z73: =Y73/$Y$68*100 -> 0
B75: 2018 | K75: 2018 | L75: ND | M75: NEGOCIACIÓN DIRECTA | T75: 2018 | U75: LM | V75: LICITACIÓN MÚLTIPLE | AC75: 2018 | AD75: LC | AE75: LISTA CORTA
B76: STATUS (a la fecha) | C76: Can. | D76: % | E76: hh Lic. | F76: % hh | G76: M$ Lic. | H76: % M$ | K76: STATUS (a la fecha) | L76: Can. | M76: % | N76: hh Lic. | O76: % hh | P76: M$ Lic. | Q76: % M$ | T76: STATUS (a la fecha) | U76: Can. | V76: % | W76: hh Lic. | X76: % hh | Y76: M$ Lic. | Z76: % M$ | AC76: STATUS (a la fecha) | AD76: Can. | AE76: % | AF76: hh Lic. | AG76: % hh | AH76: M$ Lic. | AI76: % M$
B77: Totales | C77: =SUM(C78:C82) -> 145 | D77: =SUM(D78:D82) -> 1 | E77: =SUM(E78:E82) -> 348196 | F77: =SUM(F78:F82) -> 1 | G77: =SUM(G78:G82) -> 14042.933 | H77: =SUM(H78:H82) -> 1 | K77: Totales | L77: =SUM(L78:L82) -> 101 | M77: =SUM(M78:M82) -> 100 | N77: =SUM(N78:N82) -> 218242 | O77: =SUM(O78:O82) -> 1 | P77: =SUM(P78:P82) -> 9458.5502 | Q77: =SUM(Q78:Q82) -> 100 | T77: Totales | U77: =SUM(U78:U82) -> 23 | V77: =SUM(V78:V82) -> 100 | W77: =SUM(W78:W82) -> 92588 | X77: =SUM(X78:X82) -> 1 | Y77: =SUM(Y78:Y82) -> 1360.0528 | Z77: =SUM(Z78:Z82) -> 100 | AC77: Totales | AD77: =SUM(AD78:AD82) -> 21 | AE77: =SUM(AE78:AE82) -> 100 | AF77: =SUM(AF78:AF82) -> 37366 | AG77: =SUM(AG78:AG82) -> 1 | AH77: =SUM(AH78:AH82) -> 448.1926 | AI77: =SUM(AI78:AI82) -> 100
A78: PG | B78: Propuestas Ganadas | C78: =COUNTIFS(Ofertas!$T$1757:$T$2765,Indicadores!A78,Ofertas!$AG$1757:$AG$2765,$B$75) -> 47 | D78: =C78/$C$77 -> 0.32413793 | E78: =SUMIFS(Ofertas!$W$1757:$W$2765,Ofertas!$T$1757:$T$2765,Indicadores!A78,Ofertas!$AG$1757:$AG$2765,Indicadores!$B$75) -> 89613 | F78: =E78/$E$77 -> 0.25736367 | G78: =SUMIFS(Ofertas!$X$1757:$X$2765,Ofertas!$T$1757:$T$2765,Indicadores!A78,Ofertas!$AG$1757:$AG$2765,Indicadores!$B$75) -> 3206.0805 | H78: =G78/$G$77 -> 0.22830562 | J78: PG | K78: Propuestas Ganadas | L78: =COUNTIFS(Ofertas!$T$1757:$T$2765,Indicadores!J78,Ofertas!$AG$1757:$AG$2765,$K$75,Ofertas!$L$1757:$L$2765,Indicadores!$L$75) -> 37 | M78: =L78/$L$77*100 -> 36.633663 | N78: =SUMIFS(Ofertas!$W$1757:$W$2765,Ofertas!$T$1757:$T$2765,Indicadores!J78,Ofertas!$AG$1757:$AG$2765,Indicadores!$K$75,Ofertas!$L$1757:$L$2765,Indicadores!$L$75) -> 30903 | O78: =N78/$N$77 -> 0.14159969 | P78: =SUMIFS(Ofertas!$X$1757:$X$2765,Ofertas!$T$1757:$T$2765,Indicadores!J78,Ofertas!$AG$1757:$AG$2765,Indicadores!$K$75,Ofertas!$L$1757:$L$2765,Indicadores!$L$75) -> 1051.8471 | Q78: =P78/$P$77*100 -> 11.120595 | S78: PG | T78: Propuestas Ganadas | U78: =COUNTIFS(Ofertas!$T$1757:$T$2765,Indicadores!S78,Ofertas!$AG$1757:$AG$2765,$T$75,Ofertas!$L$1757:$L$2765,Indicadores!$U$75) -> 6 | V78: =U78/$U$77*100 -> 26.086957 | W78: =SUMIFS(Ofertas!$W$1757:$W$2765,Ofertas!$T$1757:$T$2765,Indicadores!S78,Ofertas!$AG$1757:$AG$2765,Indicadores!$T$75,Ofertas!$L$1757:$L$2765,Indicadores!$U$75) -> 55029 | X78: =W78/$W$77 -> 0.59434268 | Y78: =SUMIFS(Ofertas!$X$1870:$X$2765,Ofertas!$T$1870:$T$2765,Indicadores!S78,Ofertas!$AG$1870:$AG$2765,Indicadores!$T$75,Ofertas!$L$1870:$L$2765,Indicadores!$U$75) -> 416.5052 | Z78: =Y78/$Y$77*100 -> 30.624194 | AB78: PG | AC78: Propuestas Ganadas | AD78: =COUNTIFS(Ofertas!$T$1757:$T$2765,Indicadores!AB78,Ofertas!$AG$1757:$AG$2765,$AC$75,Ofertas!$L$1757:$L$2765,Indicadores!$AD$75) -> 4 | AE78: =AD78/$AD$77*100 -> 19.047619 | AF78: =SUMIFS(Ofertas!$W$1757:$W$2765,Ofertas!$T$1757:$T$2765,Indicadores!AB78,Ofertas!$AG$1757:$AG$2765,Indicadores!$AC$75,Ofertas!$L$1757:$L$2765,Indicadores!$AD$75) -> 3681 | AG78: =AF78/$AF$77 -> 0.098512016 | AH78: =SUMIFS(Ofertas!$X$1870:$X$2765,Ofertas!$T$1870:$T$2765,Indicadores!AB78,Ofertas!$AG$1870:$AG$2765,Indicadores!$AC$75,Ofertas!$L$1870:$L$2765,Indicadores!$AD$75) -> 93.1694 | AI78: =AH78/$AH$77*100 -> 20.787804
A79: PP | B79: Propuestas Perdidas | C79: =COUNTIFS(Ofertas!$T$1757:$T$2765,Indicadores!A79,Ofertas!$AG$1757:$AG$2765,$B$75) -> 97 | D79: =C79/$C$77 -> 0.66896552 | E79: =SUMIFS(Ofertas!$W$1757:$W$2765,Ofertas!$T$1757:$T$2765,Indicadores!A79,Ofertas!$AG$1757:$AG$2765,Indicadores!$B$75) -> 257791 | F79: =E79/$E$77 -> 0.74036175 | G79: =SUMIFS(Ofertas!$X$1757:$X$2765,Ofertas!$T$1757:$T$2765,Indicadores!A79,Ofertas!$AG$1757:$AG$2765,Indicadores!$B$75) -> 10786.206 | H79: =G79/$G$77 -> 0.76808788 | J79: PP | K79: Propuestas Perdidas | L79: =COUNTIFS(Ofertas!$T$1757:$T$2765,Indicadores!J79,Ofertas!$AG$1757:$AG$2765,$K$75,Ofertas!$L$1757:$L$2765,Indicadores!$L$75) -> 63 | M79: =L79/$L$77*100 -> 62.376238 | N79: =SUMIFS(Ofertas!$W$1757:$W$2765,Ofertas!$T$1757:$T$2765,Indicadores!J79,Ofertas!$AG$1757:$AG$2765,Indicadores!$K$75,Ofertas!$L$1757:$L$2765,Indicadores!$L$75) -> 186547 | O79: =N79/$N$77 -> 0.85477131 | P79: =SUMIFS(Ofertas!$X$1757:$X$2765,Ofertas!$T$1757:$T$2765,Indicadores!J79,Ofertas!$AG$1757:$AG$2765,Indicadores!$K$75,Ofertas!$L$1757:$L$2765,Indicadores!$L$75) -> 8356.0574 | Q79: =P79/$P$77*100 -> 88.343955 | S79: PP | T79: Propuestas Perdidas | U79: =COUNTIFS(Ofertas!$T$1757:$T$2765,Indicadores!S79,Ofertas!$AG$1757:$AG$2765,$T$75,Ofertas!$L$1757:$L$2765,Indicadores!$U$75) -> 17 | V79: =U79/$U$77*100 -> 73.913043 | W79: =SUMIFS(Ofertas!$W$1757:$W$2765,Ofertas!$T$1757:$T$2765,Indicadores!S79,Ofertas!$AG$1757:$AG$2765,Indicadores!$T$75,Ofertas!$L$1757:$L$2765,Indicadores!$U$75) -> 37559 | X79: =W79/$W$77 -> 0.40565732 | Y79: =SUMIFS(Ofertas!$X$1870:$X$2765,Ofertas!$T$1870:$T$2765,Indicadores!S79,Ofertas!$AG$1870:$AG$2765,Indicadores!$T$75,Ofertas!$L$1870:$L$2765,Indicadores!$U$75) -> 943.5476 | Z79: =Y79/$Y$77*100 -> 69.375806 | AB79: PP | AC79: Propuestas Perdidas | AD79: =COUNTIFS(Ofertas!$T$1757:$T$2765,Indicadores!AB79,Ofertas!$AG$1757:$AG$2765,$AC$75,Ofertas!$L$1757:$L$2765,Indicadores!$AD$75) -> 17 | AE79: =AD79/$AD$77*100 -> 80.952381 | AF79: =SUMIFS(Ofertas!$W$1757:$W$2765,Ofertas!$T$1757:$T$2765,Indicadores!AB79,Ofertas!$AG$1757:$AG$2765,Indicadores!$AC$75,Ofertas!$L$1757:$L$2765,Indicadores!$AD$75) -> 33685 | AG79: =AF79/$AF$77 -> 0.90148798 | AH79: =SUMIFS(Ofertas!$X$1870:$X$2765,Ofertas!$T$1870:$T$2765,Indicadores!AB79,Ofertas!$AG$1870:$AG$2765,Indicadores!$AC$75,Ofertas!$L$1870:$L$2765,Indicadores!$AD$75) -> 355.0232 | AI79: =AH79/$AH$77*100 -> 79.212196
A80: PD | B80: Propuestas Desiertas | C80: =COUNTIFS(Ofertas!$T$1757:$T$2765,Indicadores!A80,Ofertas!$AG$1757:$AG$2765,$B$75) -> 1 | D80: =C80/$C$77 -> 0.0068965517 | E80: =SUMIFS(Ofertas!$W$1757:$W$2765,Ofertas!$T$1757:$T$2765,Indicadores!A80,Ofertas!$AG$1757:$AG$2765,Indicadores!$B$75) -> 792 | F80: =E80/$E$77 -> 0.002274581 | G80: =SUMIFS(Ofertas!$X$1757:$X$2765,Ofertas!$T$1757:$T$2765,Indicadores!A80,Ofertas!$AG$1757:$AG$2765,Indicadores!$B$75) -> 50.645755 | H80: =G80/$G$77 -> 0.0036064942 | J80: PD | K80: Propuestas Desiertas | L80: =COUNTIFS(Ofertas!$T$1757:$T$2765,Indicadores!J80,Ofertas!$AG$1757:$AG$2765,$K$75,Ofertas!$L$1757:$L$2765,Indicadores!$L$75) -> 1 | M80: =L80/$L$77*100 -> 0.99009901 | N80: =SUMIFS(Ofertas!$W$1757:$W$2765,Ofertas!$T$1757:$T$2765,Indicadores!J80,Ofertas!$AG$1757:$AG$2765,Indicadores!$K$75,Ofertas!$L$1757:$L$2765,Indicadores!$L$75) -> 792 | O80: =N80/$N$77 -> 0.003628999 | P80: =SUMIFS(Ofertas!$X$1757:$X$2765,Ofertas!$T$1757:$T$2765,Indicadores!J80,Ofertas!$AG$1757:$AG$2765,Indicadores!$K$75,Ofertas!$L$1757:$L$2765,Indicadores!$L$75) -> 50.645755 | Q80: =P80/$P$77*100 -> 0.53544945 | S80: PD | T80: Propuestas Desiertas | U80: =COUNTIFS(Ofertas!$T$1757:$T$2765,Indicadores!S80,Ofertas!$AG$1757:$AG$2765,$T$75,Ofertas!$L$1757:$L$2765,Indicadores!$U$75) -> 0 | V80: =U80/$U$77*100 -> 0 | W80: =SUMIFS(Ofertas!$W$1757:$W$2765,Ofertas!$T$1757:$T$2765,Indicadores!S80,Ofertas!$AG$1757:$AG$2765,Indicadores!$T$75,Ofertas!$L$1757:$L$2765,Indicadores!$U$75) -> 0 | X80: =W80/$W$77 -> 0 | Y80: =SUMIFS(Ofertas!$X$1870:$X$2765,Ofertas!$T$1870:$T$2765,Indicadores!S80,Ofertas!$AG$1870:$AG$2765,Indicadores!$T$75,Ofertas!$L$1870:$L$2765,Indicadores!$U$75) -> 0 | Z80: =Y80/$Y$77*100 -> 0 | AB80: PD | AC80: Propuestas Desiertas | AD80: =COUNTIFS(Ofertas!$T$1757:$T$2765,Indicadores!AB80,Ofertas!$AG$1757:$AG$2765,$AC$75,Ofertas!$L$1757:$L$2765,Indicadores!$AD$75) -> 0 | AE80: =AD80/$AD$77*100 -> 0 | AF80: =SUMIFS(Ofertas!$W$1757:$W$2765,Ofertas!$T$1757:$T$2765,Indicadores!AB80,Ofertas!$AG$1757:$AG$2765,Indicadores!$AC$75,Ofertas!$L$1757:$L$2765,Indicadores!$AD$75) -> 0 | AG80: =AF80/$AF$77 -> 0 | AH80: =SUMIFS(Ofertas!$X$1870:$X$2765,Ofertas!$T$1870:$T$2765,Indicadores!AB80,Ofertas!$AG$1870:$AG$2765,Indicadores!$AC$75,Ofertas!$L$1870:$L$2765,Indicadores!$AD$75) -> 0 | AI80: =AH80/$AH$77*100 -> 0
A81: DP | B81: Decisión del Cliente Pendiente | C81: =COUNTIFS(Ofertas!$T$1757:$T$2765,Indicadores!A81,Ofertas!$AG$1757:$AG$2765,$B$75) -> 0 | D81: =C81/$C$77 -> 0 | E81: =SUMIFS(Ofertas!$W$1757:$W$2765,Ofertas!$T$1757:$T$2765,Indicadores!A81,Ofertas!$AG$1757:$AG$2765,Indicadores!$B$75) -> 0 | F81: =E81/$E$77 -> 0 | G81: =SUMIFS(Ofertas!$X$1757:$X$2765,Ofertas!$T$1757:$T$2765,Indicadores!A81,Ofertas!$AG$1757:$AG$2765,Indicadores!$B$75) -> 0 | H81: =G81/$G$77 -> 0 | J81: DP | K81: Decisión del Cliente Pendiente | L81: =COUNTIFS(Ofertas!$T$1757:$T$2765,Indicadores!J81,Ofertas!$AG$1757:$AG$2765,$K$75,Ofertas!$L$1757:$L$2765,Indicadores!$L$75) -> 0 | M81: =L81/$L$77*100 -> 0 | N81: =SUMIFS(Ofertas!$W$1757:$W$2765,Ofertas!$T$1757:$T$2765,Indicadores!J81,Ofertas!$AG$1757:$AG$2765,Indicadores!$K$75,Ofertas!$L$1757:$L$2765,Indicadores!$L$75) -> 0 | O81: =N81/$N$77 -> 0 | P81: =SUMIFS(Ofertas!$X$1757:$X$2765,Ofertas!$T$1757:$T$2765,Indicadores!J81,Ofertas!$AG$1757:$AG$2765,Indicadores!$K$75,Ofertas!$L$1757:$L$2765,Indicadores!$L$75) -> 0 | Q81: =P81/$P$77*100 -> 0 | S81: DP | T81: Decisión del Cliente Pendiente | U81: =COUNTIFS(Ofertas!$T$1757:$T$2765,Indicadores!S81,Ofertas!$AG$1757:$AG$2765,$T$75,Ofertas!$L$1757:$L$2765,Indicadores!$U$75) -> 0 | V81: =U81/$U$77*100 -> 0 | W81: =SUMIFS(Ofertas!$W$1757:$W$2765,Ofertas!$T$1757:$T$2765,Indicadores!S81,Ofertas!$AG$1757:$AG$2765,Indicadores!$T$75,Ofertas!$L$1757:$L$2765,Indicadores!$U$75) -> 0 | X81: =W81/$W$77 -> 0 | Y81: =SUMIFS(Ofertas!$X$1870:$X$2765,Ofertas!$T$1870:$T$2765,Indicadores!S81,Ofertas!$AG$1870:$AG$2765,Indicadores!$T$75,Ofertas!$L$1870:$L$2765,Indicadores!$U$75) -> 0 | Z81: =Y81/$Y$77*100 -> 0 | AB81: DP | AC81: Decisión del Cliente Pendiente | AD81: =COUNTIFS(Ofertas!$T$1757:$T$2765,Indicadores!AB81,Ofertas!$AG$1757:$AG$2765,$AC$75,Ofertas!$L$1757:$L$2765,Indicadores!$AD$75) -> 0 | AE81: =AD81/$AD$77*100 -> 0 | AF81: =SUMIFS(Ofertas!$W$1757:$W$2765,Ofertas!$T$1757:$T$2765,Indicadores!AB81,Ofertas!$AG$1757:$AG$2765,Indicadores!$AC$75,Ofertas!$L$1757:$L$2765,Indicadores!$AD$75) -> 0 | AG81: =AF81/$AF$77 -> 0 | AH81: =SUMIFS(Ofertas!$X$1870:$X$2765,Ofertas!$T$1870:$T$2765,Indicadores!AB81,Ofertas!$AG$1870:$AG$2765,Indicadores!$AC$75,Ofertas!$L$1870:$L$2765,Indicadores!$AD$75) -> 0 | AI81: =AH81/$AH$77*100 -> 0
A82: EP | B82: Propuestas en Preparación | C82: =COUNTIFS(Ofertas!$T$1757:$T$2765,Indicadores!A82,Ofertas!$AG$1757:$AG$2765,$B$75) -> 0 | D82: =C82/$C$77 -> 0 | E82: =SUMIFS(Ofertas!$W$1757:$W$2765,Ofertas!$T$1757:$T$2765,Indicadores!A82,Ofertas!$AG$1757:$AG$2765,Indicadores!$B$75) -> 0 | F82: =E82/$E$77 -> 0 | G82: =SUMIFS(Ofertas!$X$1757:$X$2765,Ofertas!$T$1757:$T$2765,Indicadores!A82,Ofertas!$AG$1757:$AG$2765,Indicadores!$B$75) -> 0 | H82: =G82/$G$77 -> 0 | J82: EP | K82: Propuestas en Preparación | L82: =COUNTIFS(Ofertas!$T$1757:$T$2765,Indicadores!J82,Ofertas!$AG$1757:$AG$2765,$K$75,Ofertas!$L$1757:$L$2765,Indicadores!$L$75) -> 0 | M82: =L82/$L$77*100 -> 0 | N82: =SUMIFS(Ofertas!$W$1757:$W$2765,Ofertas!$T$1757:$T$2765,Indicadores!J82,Ofertas!$AG$1757:$AG$2765,Indicadores!$K$75,Ofertas!$L$1757:$L$2765,Indicadores!$L$75) -> 0 | O82: =N82/$N$77 -> 0 | P82: =SUMIFS(Ofertas!$X$1757:$X$2765,Ofertas!$T$1757:$T$2765,Indicadores!J82,Ofertas!$AG$1757:$AG$2765,Indicadores!$K$75,Ofertas!$L$1757:$L$2765,Indicadores!$L$75) -> 0 | Q82: =P82/$P$77*100 -> 0 | S82: EP | T82: Propuestas en Preparación | U82: =COUNTIFS(Ofertas!$T$1757:$T$2765,Indicadores!S82,Ofertas!$AG$1757:$AG$2765,$T$75,Ofertas!$L$1757:$L$2765,Indicadores!$U$75) -> 0 | V82: =U82/$U$77*100 -> 0 | W82: =SUMIFS(Ofertas!$W$1757:$W$2765,Ofertas!$T$1757:$T$2765,Indicadores!S82,Ofertas!$AG$1757:$AG$2765,Indicadores!$T$75,Ofertas!$L$1757:$L$2765,Indicadores!$U$75) -> 0 | X82: =W82/$W$77 -> 0 | Y82: =SUMIFS(Ofertas!$X$1870:$X$2765,Ofertas!$T$1870:$T$2765,Indicadores!S82,Ofertas!$AG$1870:$AG$2765,Indicadores!$T$75,Ofertas!$L$1870:$L$2765,Indicadores!$U$75) -> 0 | Z82: =Y82/$Y$77*100 -> 0 | AB82: EP | AC82: Propuestas en Preparación | AD82: =COUNTIFS(Ofertas!$T$1757:$T$2765,Indicadores!AB82,Ofertas!$AG$1757:$AG$2765,$AC$75,Ofertas!$L$1757:$L$2765,Indicadores!$AD$75) -> 0 | AE82: =AD82/$AD$77*100 -> 0 | AF82: =SUMIFS(Ofertas!$W$1757:$W$2765,Ofertas!$T$1757:$T$2765,Indicadores!AB82,Ofertas!$AG$1757:$AG$2765,Indicadores!$AC$75,Ofertas!$L$1757:$L$2765,Indicadores!$AD$75) -> 0 | AG82: =AF82/$AF$77 -> 0 | AH82: =SUMIFS(Ofertas!$X$1870:$X$2765,Ofertas!$T$1870:$T$2765,Indicadores!AB82,Ofertas!$AG$1870:$AG$2765,Indicadores!$AC$75,Ofertas!$L$1870:$L$2765,Indicadores!$AD$75) -> 0 | AI82: =AH82/$AH$77*100 -> 0
B84: 2019 | K84: 2019 | L84: ND | M84: NEGOCIACIÓN DIRECTA | T84: 2019 | U84: LM | V84: LICITACIÓN MÚLTIPLE | AC84: 2019 | AD84: LC | AE84: LISTA CORTA
B85: STATUS (a la fecha) | C85: Can. | D85: % | E85: hh Lic. | F85: % hh | G85: M$ Lic. | H85: % M$ | K85: STATUS (a la fecha) | L85: Can. | M85: % | N85: hh Lic. | O85: % hh | P85: M$ Lic. | Q85: % M$ | T85: STATUS (a la fecha) | U85: Can. | V85: % | W85: hh Lic. | X85: % hh | Y85: M$ Lic. | Z85: % M$ | AC85: STATUS (a la fecha) | AD85: Can. | AE85: % | AF85: hh Lic. | AG85: % hh | AH85: M$ Lic. | AI85: % M$
B86: Totales | C86: =SUM(C87:C91) -> 91 | D86: =SUM(D87:D91) -> 1 | E86: =SUM(E87:E91) -> 258697.18 | F86: =SUM(F87:F91) -> 1 | G86: =SUM(G87:G91) -> 10091.493 | H86: =SUM(H87:H91) -> 1 | K86: Totales | L86: =SUM(L87:L91) -> 56 | M86: =SUM(M87:M91) -> 100 | N86: =SUM(N87:N91) -> 142099.18 | O86: =SUM(O87:O91) -> 1 | P86: =SUM(P87:P91) -> 5316.9766 | Q86: =SUM(Q87:Q91) -> 100 | T86: Totales | U86: =SUM(U87:U91) -> 15 | V86: =SUM(V87:V91) -> 100 | W86: =SUM(W87:W91) -> 81567 | X86: =SUM(X87:X91) -> 1 | Y86: =SUM(Y87:Y91) -> 3452.6537 | Z86: =SUM(Z87:Z91) -> 100 | AC86: Totales | AD86: =SUM(AD87:AD91) -> 20 | AE86: =SUM(AE87:AE91) -> 100 | AF86: =SUM(AF87:AF91) -> 35031 | AG86: =SUM(AG87:AG91) -> 1 | AH86: =SUM(AH87:AH91) -> 1321.8629 | AI86: =SUM(AI87:AI91) -> 100
